Workbook

Sheet 🏠 Master Dashboard
A1: 🧬 A7DO DNA MASTER v5 — FINAL Unified Organism Runtime
A2: All phases: Biology · Cognition · Phase 3 Experiential · Phase 4 Cognitive · Learning Loop · Phase 7 Wisdom
A3: Source: DNA_Consolidated_v17 (newest) + Master_v3 Phase 4 + Consolidated_v9 Phase 3 + Phase 7 NEW + Learning Loop NEW
A5: ⚡ MASTER TICK CONTROL
A6: Parameter | B6: Value | C6: Unit | D6: Notes
A7: Current Tick: | B7: 10,000 (default) | C7: ticks | D7: Edit in 🧬 DNA Loop Engine B4
A8: Current Week: | B8: 125 | C8: weeks | D8: Tick ÷ 80
A9: Life Stage: | B9: Toddler | D9: VLOOKUP from life stage map
A10: Birth Occurred: | B10: ✅ YES | D10: Tick ≥ 3,200
A11: Height: | B11: ~90 cm | C11: cm | D11: Growth formula active
A12: Mass: | B12: ~13 kg | C12: kg | D12: Growth formula active
A13: Heart Rate: | B13: ~110 bpm | C13: bpm | D13: Declining from 140 at birth
A14: Vocabulary: | B14: ~8,754 words | C14: words | D14: Logistic V(t) formula
A15: Motor Stage: | B15: 3 / 5 | C15: 1–5 | D15: Threshold-based
A16: ToM Stage: | B16: 1 — Proto-ToM | C16: 1–5 | D16: Wk 125 = Stage 1
A17: Consciousness C: | B17: 0.398 | C17: 0–1 | D17: EQ_CONS_10 verified
A18: Attachment Drive: | B18: 0.950 | C18: 0–1 | D18: Strong caregiver bond
A19: LTM Events: | B19: 9,590 | C19: events | D19: Episodic memory store
A20: Learning Loop: | B20: ✅ Active — Stage: Exposure/Interaction/Repetition | D20: Sleep every 800 ticks
A21: Phase 7 Active: | B21: ⏳ Pending — activates Tick 96,000 (Wk 1,200) | D21: W(t) rises 0→1 by Wk 2,000
A24: 🔄 LEARNING LOOP — 4-Stage Cycle
A25: Stage | B25: Name | C25: Fires Every | D25: Key Engines | E25: Output
A26: 1 | B26: Exposure | C26: Every tick | D26: EQ_SENS_06 · EQ_EMOT_07 · EQ_ATTN_09 | E26: Sensory vector · attention weight · emotional delta
A27: 2 | B27: Interaction | C27: Every 5 ticks | D27: EQ_PRED_08 · Motor Planning · Value TD(λ) | E27: Reinforcement · motor update · prediction error reduction
A28: 3 | B28: Repetition | C28: Every 10 ticks | D28: EQ_LANG_12 · G(word) · Scene Graph · ToM | E28: Word-object bindings · concept formation · NPC models
A29: 4 | B29: Sleep Consolidation | C29: Every 800 ticks | D29: Episodic Memory · EQ_PRED_08 dream replay | E29: Stable knowledge · grounded language · pruned LTM
A32: 🆕 PHASE 7 — CREATIVE SYNTHESIS & WISDOM ENGINE (Tick 96,000+)
A33: Equation | B33: Engine | C33: Fires Every | D33: Core Formula
A34: EQ_CREAT_17 | B34: ✨ Creative Synthesis Engine | C34: 500 ticks | D34: C_new(t) = α_c·(M_episodic ⊕ M_semantic) + β_c·(P_sim ⊗ S_skills) + γ_c·Noise
A35: EQ_WISDOM_18 | B35: 🦉 Wisdom Index Engine | C35: 500 ticks | D35: W(t+1) = W(t) + η_w·[λ1·C50yr + λ2·EthicalWeight + λ3·EmpathyIndex − λ4·ImpulseDrive]
A36: EQ_CAREER_19 | B36: 🎯 Career Specialisation Engine | C36: 1000 ticks | D36: Career(t+1) = Career(t) + η_car·[SkillVector · OpportunityMatrix · IdentityVector]
A37: EQ_LEGACY_20 | B37: 🌟 Legacy Projection Engine | C37: 2000 ticks | D37: L(t+1) = L(t) + η_l·[Impact_direct + Impact_indirect + CulturalTransmission − Entropy_f·L(t)]
A40: 🗂️ COMPLETE SHEET INDEX — 36 Sheets
A41: Sheet | B41: Category | C41: Cells | D41: Key Content
A42: 🧬 DNA Loop Engine | B42: Core | C42: 907 | D42: Tick control · lifecycle table · Phase 7 rows · life stage map
A43: 📈 Growth Timeline | B43: Core | C43: 3395 | D43: 292-row lifecycle · organ activation · milestones · maturity %
A44: 🧮 Mathematical Framework | B44: Core | C44: 1411 | D44: EQ_DNA_01→EQ_LANG_12 + EQ_CREAT_17→EQ_LEGACY_20 · all equations
A45: ⚙️ Parameters | B45: Core | C45: 297 | D45: 41 biological constants · Phase 7 params · tick frequency schedule
A46: 📖 System Specification | B46: Core | C46: 1004 | D46: Full system spec · architecture · module contracts
A47: 🧬 Prenatal & Genesis | B47: Biology | C47: 1469 | D47: Parental genesis · genetic inheritance · sex determination · hormones
A48: 📐 Spatial Coordinates | B48: Biology | C48: 527 | D48: 3-layer coordinate system: body / world / BeenFore
A49: 🫀 Body Systems | B49: Biology | C49: 1245 | D49: Circulatory · respiratory · digestive · sensory — full organ tables
A50: 🔬 Subsystems | B50: Biology | C50: 330 | D50: Detailed subsystem specifications
A51: ⚡ Energy & Metabolism | B51: Biology | C51: 267 | D51: ATP system · metabolic engines · energy balance
A52: 📏 Full Growth System | B52: Biology | C52: 1094 | D52: Complete growth curves for all body systems
A53: 🧠 Mind & Cognition | B53: Cognition | C53: 1920 | D53: Language · cognition · nutrition-sleep-wake · NPC tracking
... A76: 🌟 Legacy Projection Engine | B76: Phase 7 | C76: 120 | D76: EQ_LEGACY_20 · legacy curve · cultural transmission network

Sheet 🧬 DNA Loop Engine
A1: 🧬 A7DO DNA LOOP ENGINE — LIVE CONTROL PANEL | Change B4 (Current Tick) to simulate any life stage
A2: ⚡ INPUT CELL → B4 (Current Tick) — Type any tick value (0–96000) to update ALL formulas below automatically
A3: ⚙️ CONTROL PANEL | D3: 🫀 ORGAN ACTIVATION STATUS | G3: 🔄 TICK ADVANCE LOGIC | J3: ⚡ GROWTH ENGINE
A4: Current Tick: | B4: 10000 | C4: ← EDIT THIS | D4: Organ/System | E4: Status | F4: DNA Code | G4: Parameter | H4: Value | J4: Parameter | K4: Value
A5: Current Week: | B5: =ROUND(B4/80,0) -> 125 | C5: weeks | D5: Neural Plate | E5: =IF(B5>=0,"✅ Active","⏳ Pending") -> ✅ Active | F5: NP_FORM | G5: Next Tick ID: | H5: =IF(B4<B6,"T"&TEXT(B4+100,"0000"),"COMPLETE") -> COMPLETE | J5: Growth Factor: | K5: =IF(B5>=40,1,IFERROR(VLOOKUP(B5,'🧬 DNA Loop Engine'!B29:G60,3,TRUE()),0.01)) -> 1
A6: Birth Tick: | B6: 3200 | C6: Fixed = 3200 | D6: Heart | E6: =IF(B5>=4,"✅ Active","⏳ Pending") -> ✅ Active | F6: HT_PART | G6: Ticks to Birth: | H6: =MAX(0,B6-B4) -> 0 | J6: Neural Gain: | K6: =IF(B5>=40,1,IFERROR(VLOOKUP(B5,'🧬 DNA Loop Engine'!B29:G60,4,TRUE()),0)) -> 1
A7: Nutrient Flow Rate: | B7: 1 | C7: Fixed = 1.0 | D7: Limbs | E7: =IF(B5>=8,"✅ Active","⏳ Pending") -> ✅ Active | F7: LM_DIFF | G7: Progress %: | H7: =TEXT(MIN(1,B4/B6),"0%") -> 100% | J7: Reflex Gain: | K7: =IF(B5>=40,1,IFERROR(VLOOKUP(B5,'🧬 DNA Loop Engine'!B29:G60,5,TRUE()),0)) -> 1
A8: Simulation Status: | B8: =IF(B4>=B6,"🎉 BIRTH COMPLETE",IF(B4=0,"⏸️ NOT STARTED","🔄 GESTATING")) -> 🎉 BIRTH COMPLETE | D8: Reflex Arcs | E8: =IF(B5>=12,"✅ Active","⏳ Pending") -> ✅ Active | F8: RF_ACT | G8: Time Remaining: | H8: =TEXT(INT(MAX(0,B6-B4)/100),"0")&" ticks (~"&ROUND(MAX(0,B6-B4)/80,1)&" weeks)" -> 0 ticks (~0 weeks) | J8: Identity Confidence: | K8: =IF(B5>=40,1,IFERROR(VLOOKUP(B5,'🧬 DNA Loop Engine'!B29:G60,6,TRUE()),0)) -> 1
A9: 📖 PHASE READER | D9: Cerebellum | E9: =IF(B5>=20,"✅ Active","⏳ Pending") -> ✅ Active | F9: CB_GROW | G9: Phase Complete In: | H9: =IF(B5>=40,"N/A (Born)",MAX(0,40-B5)&" weeks") -> N/A (Born) | J9: Effective Growth: | K9: =B18*B7 -> 1
A10: Active Phase #: | B10: ="T"&TEXT(B4,"0000") -> T10000 | D10: Myelination | E10: =IF(B5>=28,"✅ Active","⏳ Pending") -> ✅ Active | F10: MYEL_ON
A11: DNA Phase Name: | B11: =IF(B5>=936,"Mature Adult",IF(B5>=624,"Adolescent",IF(B5>=312,"Mid Childhood",IF(B5>=156,"Early Childhood",IF(B5>=92,"Toddler",IF(B5>=60,"Late Infant",IF(B5>=40,"Early Infant",IF(B5>=36,"Birth Preparation",IF(B5>=28,"Pre-Birth Integration",IF(B5>=20,"Neural Maturation",IF(B5>=12,"Reflex Explosion",IF(B5>=8,"Body Plan",IF(B5>=4,"Organogenesis","Embryogenesis"))))))))))))) -> Toddler | D11: Lungs | E11: =IF(B5>=36,"✅ Active","⏳ Pending") -> ✅ Active | F11: LG_MAT
A12: DNA Trigger Code: | B12: =IF(B5>=40,"POSTNATAL",IF(B5>=36,"BIRTH_READY",IF(B5>=28,"INTEGRATE",IF(B5>=20,"NEURAL_GROW",IF(B5>=12,"REFLEX_ON",IF(B5>=8,"BODY_FORM",IF(B5>=4,"ORG_START","DNA_INIT"))))))) -> POSTNATAL
A13: Biological Focus: | B13: =IF(B5>=40,"Post-Birth Growth & Learning",IF(B5>=36,"Lung maturation & birth prep",IF(B5>=28,"Reflex synchronisation & myelination",IF(B5>=20,"Cerebellum growth & neural maturation",IF(B5>=12,"Reflex arc activation",IF(B5>=8,"Limb differentiation & body plan",IF(B5>=4,"Organogenesis","Embryogenesis & cell division"))))))) -> Post-Birth Growth & Learning
A14: Next Phase Condition: | B14: =IF(B5>=40,"Continuous Development",IF(B5>=36,"Lungs mature",IF(B5>=28,"Reflexes synchronised",IF(B5>=20,"Predictive circuits active",IF(B5>=12,"Stretch reflex stable",IF(B5>=8,"Reflex seed active",IF(B5>=4,"Limb buds visible","Neural plate formed"))))))) -> Continuous Development
A15: Life Stage: | B15: =IF(B5>=936,"🎓 Mature Adult",IF(B5>=624,"🧠 Adolescent",IF(B5>=312,"🧒 Mid Childhood",IF(B5>=156,"🧒 Early Childhood",IF(B5>=92,"🧒 Toddler",IF(B5>=60,"👶 Late Infant",IF(B5>=40,"👶 Early Infant","🤰 Prenatal"))))))) -> 🧒 Toddler
A16: Age (months): | B16: =IF(B5<40,"Prenatal",ROUND(MAX(0,B5-40)/4.33,1)&" months ("&ROUND(MAX(0,B5-40)/52,2)&" yrs)") -> 19.6 months (1.63 yrs)
A17: 🫀 UMBILICAL CORD DRIVER
A18: Growth Factor: | B18: =IF(B5>=40,1,IF(B5>=36,0.95,IF(B5>=28,0.8,IF(B5>=20,0.6,IF(B5>=12,0.4,IF(B5>=8,0.25,IF(B5>=4,0.1,0.01))))))) -> 1
A19: Neural Gain: | B19: =IF(B5>=40,1,IF(B5>=36,0.8,IF(B5>=28,0.6,IF(B5>=20,0.4,IF(B5>=12,0.25,IF(B5>=8,0.1,IF(B5>=4,0.05,0))))))) -> 1
A20: Reflex Gain: | B20: =IF(B5>=40,1,IF(B5>=36,0.8,IF(B5>=28,0.6,IF(B5>=20,0.4,IF(B5>=12,0.2,IF(B5>=8,0.05,0)))))) -> 1
A21: Identity Confidence: | B21: =IF(B5>=40,1,IF(B5>=36,0.9,IF(B5>=28,0.75,IF(B5>=20,0.5,IF(B5>=12,0.25,IF(B5>=8,0.1,0)))))) -> 1
A22: Cord Status: | B22: =IF(B4>=B6,"🔌 SEVERED","🔗 CONNECTED") -> 🔌 SEVERED
A23: Nutrient Delivery: | B23: =IF(B4<B6,B7*B18,0) -> 0
A24: DNA Push Rate: | B24: =IF(B4<B6,(B6-B4)/B6,0) -> 0
A25: Oxygen Transfer: | B25: =IF(B4<B6,B7*0.21,0.21) -> 0.21
A26: Effective Growth: | B26: =B18*B7 -> 1
A27: Heart Rate (BPM): | B27: =IF(B5<40,ROUND(120+B18*30,0),MAX(60,ROUND(147-((B5-40)/52)*47,0))) -> 70
A28: Height G_phys: | B28: =ROUND(IF('🧬 DNA Loop Engine'!B5<=40,1/(1+EXP(-0.2*('🧬 DNA Loop Engine'!B5-20))),(IF('🧬 DNA Loop Engine'!B5<=40,ROUND(50/(1+EXP(-0.2*('🧬 DNA Loop Engine'!B5-20))),1),IF('🧬 DNA Loop Engine'!B5<=92,ROUND(50+(75-50)*('🧬 DNA Loop Engine'!B5-40)/(92-40),1),IF('🧬 DNA Loop Engine'!B5<=156,ROUND(75+(95-75)*('🧬 DNA Loop Engine'!B5-92)/(156-92),1),IF('🧬 DNA Loop Engine'!B5<=624,ROUND(95+(145-95)*('🧬 DNA Loop Engine'!B5-156)/(624-156),1),IF('🧬 DNA Loop Engine'!B5<=936,ROUND(145+(175-145)*('🧬 DNA Loop Engine'!B5-624)/(936-624),1),ROUND(MIN(177,175+2*MIN(1,('🧬 DNA Loop Engine'!B5-936)/200)),1)))))))/50),3) -> 1.706
A29: Height H(t) cm: | B29: =IF('🧬 DNA Loop Engine'!B5<=40,ROUND(50/(1+EXP(-0.2*('🧬 DNA Loop Engine'!B5-20))),1),IF('🧬 DNA Loop Engine'!B5<=92,ROUND(50+(75-50)*('🧬 DNA Loop Engine'!B5-40)/(92-40),1),IF('🧬 DNA Loop Engine'!B5<=156,ROUND(75+(95-75)*('🧬 DNA Loop Engine'!B5-92)/(156-92),1),IF('🧬 DNA Loop Engine'!B5<=624,ROUND(95+(145-95)*('🧬 DNA Loop Engine'!B5-156)/(624-156),1),IF('🧬 DNA Loop Engine'!B5<=936,ROUND(145+(175-145)*('🧬 DNA Loop Engine'!B5-624)/(936-624),1),ROUND(MIN(177,175+2*MIN(1,('🧬 DNA Loop Engine'!B5-936)/200)),1)))))) -> 85.3
A30: Mass M(t) kg: | B30: =IF('🧬 DNA Loop Engine'!B5<=40,ROUND(3.5/(1+EXP(-0.2*('🧬 DNA Loop Engine'!B5-20))),2),IF('🧬 DNA Loop Engine'!B5<=92,ROUND(3.5+(10-3.5)*('🧬 DNA Loop Engine'!B5-40)/(92-40),2),IF('🧬 DNA Loop Engine'!B5<=156,ROUND(10+(14-10)*('🧬 DNA Loop Engine'!B5-92)/(156-92),2),IF('🧬 DNA Loop Engine'!B5<=624,ROUND(14+(40-14)*('🧬 DNA Loop Engine'!B5-156)/(624-156),2),IF('🧬 DNA Loop Engine'!B5<=936,ROUND(40+(65-40)*('🧬 DNA Loop Engine'!B5-624)/(936-624),2),ROUND(MIN(70,65+(70-65)*MIN(1,('🧬 DNA Loop Engine'!B5-936)/200)),2)))))) -> 12.06
A31: S_height: | B31: =ROUND((IF('🧬 DNA Loop Engine'!B5<=40,ROUND(50/(1+EXP(-0.2*('🧬 DNA Loop Engine'!B5-20))),1),IF('🧬 DNA Loop Engine'!B5<=92,ROUND(50+(75-50)*('🧬 DNA Loop Engine'!B5-40)/(92-40),1),IF('🧬 DNA Loop Engine'!B5<=156,ROUND(75+(95-75)*('🧬 DNA Loop Engine'!B5-92)/(156-92),1),IF('🧬 DNA Loop Engine'!B5<=624,ROUND(95+(145-95)*('🧬 DNA Loop Engine'!B5-156)/(624-156),1),IF('🧬 DNA Loop Engine'!B5<=936,ROUND(145+(175-145)*('🧬 DNA Loop Engine'!B5-624)/(936-624),1),ROUND(MIN(177,175+2*MIN(1,('🧬 DNA Loop Engine'!B5-936)/200)),1)))))))/50,3) -> 1.706
A32: S_width: | B32: =ROUND(POWER((IF('🧬 DNA Loop Engine'!B5<=40,ROUND(3.5/(1+EXP(-0.2*('🧬 DNA Loop Engine'!B5-20))),2),IF('🧬 DNA Loop Engine'!B5<=92,ROUND(3.5+(10-3.5)*('🧬 DNA Loop Engine'!B5-40)/(92-40),2),IF('🧬 DNA Loop Engine'!B5<=156,ROUND(10+(14-10)*('🧬 DNA Loop Engine'!B5-92)/(156-92),2),IF('🧬 DNA Loop Engine'!B5<=624,ROUND(14+(40-14)*('🧬 DNA Loop Engine'!B5-156)/(624-156),2),IF('🧬 DNA Loop Engine'!B5<=936,ROUND(40+(65-40)*('🧬 DNA Loop Engine'!B5-624)/(936-624),2),ROUND(MIN(70,65+(70-65)*MIN(1,('🧬 DNA Loop Engine'!B5-936)/200)),2)))))))/3.5,1/3),3) -> 1.51 | C32: Prenatal | D32: Organogenesis | E32: 0.1 | F32: 0.05 | G32: 0 | H32: 0 | I32: 0 | J32: 0 | K32: Pre-Puberty | L32: 🟢 Growing | M32: Heart chambers forming
A33: T1000 | B33: 8 | C33: Prenatal | D33: Body Plan | E33: 0.25 | F33: 0.1 | G33: 0.05 | H33: 0.1 | I33: 0 | J33: 0 | K33: Pre-Puberty | L33: 🟢 Growing | M33: Limb buds visible
A34: T1500 | B34: 12 | C34: Prenatal | D34: Reflex Explosion | E34: 0.4 | F34: 0.25 | G34: 0.2 | H34: 0.25 | I34: 0 | J34: 0 | K34: Pre-Puberty | L34: 🟢 Growing | M34: Reflex arcs online
A35: T2000 | B35: 20 | C35: Prenatal | D35: Neural Maturation | E35: 0.6 | F35: 0.4 | G35: 0.4 | H35: 0.5 | I35: 0 | J35: 0 | K35: Pre-Puberty | L35: 🟢 Growing | M35: Cerebellum growth surge
A36: T2500 | B36: 28 | C36: Prenatal | D36: Pre-Birth Integration | E36: 0.8 | F36: 0.6 | G36: 0.6 | H36: 0.75 | I36: 0 | J36: 0 | K36: Pre-Puberty | L36: 🟢 Growing | M36: Myelination begins
A37: T3000 | B37: 36 | C37: Prenatal | D37: Birth Preparation | E37: 0.95 | F37: 0.8 | G37: 0.8 | H37: 0.9 | I37: 0 | J37: 0 | K37: Pre-Puberty | L37: 🟢 Growing | M37: Lungs maturing
A38: ── BIRTH ──
A39: T3200 | B39: 40 | C39: Birth | D39: Birth Event | E39: 1 | F39: 1 | G39: 1 | H39: 1 | I39: 2 | J39: 0 | K39: Pre-Puberty | L39: 🔴 Stopped | M39: Umbilical cord severed; pulmonary breathing
A40: ── INFANT ──
A41: T3600 | B41: 45 | C41: Infant | D41: Early Infant | E41: 1 | F41: 1 | G41: 1 | H41: 1 | I41: 4 | J41: 0 | K41: Pre-Puberty | L41: 🔴 Stopped | M41: Sensory systems calibrating
A42: T4000 | B42: 50 | C42: Infant | D42: Early Infant | E42: 1 | F42: 1 | G42: 1 | H42: 1 | I42: 6 | J42: 0 | K42: Pre-Puberty | L42: 🔴 Stopped | M42: Social smile emerges
A43: T4800 | B43: 60 | C43: Infant | D43: Late Infant | E43: 1 | F43: 1 | G43: 1 | H43: 1 | I43: 10 | J43: 0 | K43: Pre-Puberty | L43: 🔴 Stopped | M43: Object permanence forming
A44: T5600 | B44: 70 | C44: Infant | D44: Late Infant | E44: 1 | F44: 1 | G44: 1 | H44: 1 | I44: 14 | J44: 0 | K44: Pre-Puberty | L44: 🔴 Stopped | M44: Crawling / pulling to stand
A45: T6400 | B45: 80 | C45: Infant | D45: Late Infant | E45: 1 | F45: 1 | G45: 1 | H45: 1 | I45: 18 | J45: 0 | K45: Pre-Puberty | L45: 🔴 Stopped | M45: First words forming
A46: ── TODDLER ──
A47: T7200 | B47: 90 | C47: Toddler | D47: Toddler | E47: 1 | F47: 1 | G47: 1 | H47: 1 | I47: 22 | J47: 0 | K47: Pre-Puberty | L47: 🔴 Stopped | M47: Walking independently
A48: T8000 | B48: 100 | C48: Toddler | D48: Toddler | E48: 1 | F48: 1 | G48: 1 | H48: 1 | I48: 26 | J48: 0 | K48: Pre-Puberty | L48: 🔴 Stopped | M48: Symbolic play begins
A49: T10000 | B49: 125 | C49: Toddler | D49: Early Childhood | E49: 1 | F49: 1 | G49: 1 | H49: 1 | I49: 31 | J49: 0 | K49: Pre-Puberty | L49: 🔴 Stopped | M49: Current state — A7DO ~19.6 months
A50: ── CHILD ──
A51: T15600 | B51: 195 | C51: Child | D51: Early Childhood | E51: 1 | F51: 1 | G51: 1 | H51: 1 | I51: 40 | J51: 0 | K51: Pre-Puberty | L51: 🔴 Stopped | M51: Language cortex 50% mature
A52: T20800 | B52: 260 | C52: Child | D52: Mid Childhood | E52: 1 | F52: 1 | G52: 1 | H52: 1 | I52: 55 | J52: 0 | K52: Pre-Puberty | L52: 🔴 Stopped | M52: Reading & writing consolidating
A53: T24960 | B53: 312 | C53: Child | D53: Mid Childhood | E53: 1 | F53: 1 | G53: 1 | H53: 1 | I53: 70 | J53: 0 | K53: Pre-Puberty | L53: 🔴 Stopped | M53: Language cortex 100% mature
A54: T31200 | B54: 390 | C54: Child | D54: Late Childhood | E54: 1 | F54: 1 | G54: 1 | H54: 1 | I54: 80 | J54: 0 | K54: Pre-Puberty | L54: 🔴 Stopped | M54: Logical reasoning emerging
A55: ── CHILD→ADOL. ──
A56: T49920 | B56: 624 | C56: Child→Adol. | D56: Late Childhood | E56: 1 | F56: 1 | G56: 1 | H56: 1 | I56: 90 | J56: 5 | K56: Pre-Puberty | L56: 🔴 Stopped | M56: Prefrontal cortex 100% mature; puberty onset
A57: ── ADOLESCENT ──
A58: T56000 | B58: 700 | C58: Adolescent | D58: Early Adolescence | E58: 1 | F58: 1 | G58: 1 | H58: 1 | I58: 93 | J58: 20 | K58: Early Puberty | L58: 🔴 Stopped | M58: Abstract reasoning activating
A59: T62400 | B59: 780 | C59: Adolescent | D59: Mid Adolescence | E59: 1 | F59: 1 | G59: 1 | H59: 1 | I59: 96 | J59: 45 | K59: Mid Puberty | L59: 🔴 Stopped | M59: Identity formation accelerating
A60: T68000 | B60: 850 | C60: Adolescent | D60: Late Adolescence | E60: 1 | F60: 1 | G60: 1 | H60: 1 | I60: 98 | J60: 70 | K60: Late Puberty | L60: 🔴 Stopped | M60: Emotional regulation maturing
A61: ── ADOLESCENT→ADULT ── | B61: ✅ Active | C61: HT_PART
A62: T74880 | B62: 936 | C62: Adolescent→Adult | D62: Adolescent Complete | E62: 1 | F62: 1 | G62: 1 | H62: 1 | I62: 100 | J62: 90 | K62: Post-Puberty | L62: 🔴 Stopped | M62: All adolescent systems 100% mature
A63: ── ADULT ── | B63: ✅ Active | C63: RF_ACT
A64: T80000 | B64: 1000 | C64: Adult | D64: Early Adult | E64: 1 | F64: 1 | G64: 1 | H64: 1 | I64: 100 | J64: 95 | K64: Adult | L64: 🔴 Stopped | M64: Strategic reasoning online
A65: T88000 | B65: 1100 | C65: Adult | D65: Mid Adult | E65: 1 | F65: 1 | G65: 1 | H65: 1 | I65: 100 | J65: 98 | K65: Adult | L65: 🔴 Stopped | M65: Long-term memory depth increasing
A66: T96000 | B66: 1200 | C66: Adult | D66: Mature Adult | E66: 1 | F66: 1 | G66: 1 | H66: 1 | I66: 100 | J66: 100 | K66: Adult | L66: 🔴 Stopped | M66: Wisdom index & creative synthesis peak
A67: ── PHASE 7 ── | B67: ✅ Active | C67: PH7_ACT
A68: T96000 | B68: 1200 | C68: Mature Adult | D68: Phase 7 Onset | E68: 1 | F68: 1 | G68: 1 | H68: 1 | I68: 100 | J68: 100 | K68: Adult | L68: 🔴 Stopped | M68: Creative Synthesis & Wisdom Engine ACTIVATES
A69: T104000 | B69: 1300 | C69: Mature Adult | D69: Wisdom Rising | E69: 1 | F69: 1 | G69: 1 | H69: 1 | I69: 100 | J69: 100 | K69: Adult | L69: 🔴 Stopped | M69: W(t)=0.22 — EthicalWeight rising
A70: T160000 | B70: 2000 | C70: Mature Adult | D70: Wisdom Peak | E70: 1 | F70: 1 | G70: 1 | H70: 1 | I70: 100 | J70: 100 | K70: Adult | L70: 🔴 Stopped | M70: W(t)=0.95 — Legacy curve L(t)=0.94
A73: ⚙️ UNIFIED MATHEMATICAL FRAMEWORK
A74: ⚙️ A7DO UNIFIED MATHEMATICAL FRAMEWORK
A75: Equation ID | B75: System Name | C75: Category | D75: Primary Formula | E75: Secondary Formula | F75: Variables | G75: Domain | H75: Parameter Range
A76: EQ_DNA_01 | B76: DNA Loop Engine | C76: Core Engine | D76: D(t+1) = D(t) + α·ActivationRate + β·GrowthFactor | E76: Phase(t+1) = Phase(t) + γ·MaturityIndex | F76: D, Phase, α, β, γ | G76: Development | H76: α,β,γ: 0.01–0.1
A77: EQ_ANAT_02 | B77: Anatomy Growth Engine | C77: Embodiment | D77: G(t+1) = G(t) + δ·CellDivisionRate + ε·NutrientFlow | E77: V(t+1) = V(t) + ζ·OxygenExchange − η·WasteRate | F77: G, V, δ, ε, ζ, η | G77: Embodiment | H77: δ,ε,ζ: 0.1–1.0
A78: EQ_NEUR_03 | B78: Neural Control System | C78: Neural | D78: N(t+1) = N(t) + θ·SynapseDensity + ι·NeuralGain | E78: S(t+1) = κ·InputSignal − λ·NoiseLevel | F78: N, S, θ, ι, κ, λ | G78: Neural | H78: θ,ι,κ: 0.001–0.05
A79: EQ_CIRC_04 | B79: Circulatory Integration | C79: Homeostatic | D79: O(t+1) = O(t) + μ·HeartbeatRate·O₂Level | E79: E(t+1) = E(t) + ν·BloodFlow − ξ·MetabolicDrain | F79: O, E, μ, ν, ξ | G79: Embodiment | H79: μ,ν,ξ: 0.1–0.5
A80: EQ_DIGE_05 | B80: Digestive & Energy System | C80: Metabolic | D80: A(t+1) = A(t) + π·NutrientIntake − ρ·ActivityLoad | E80: M(t+1) = M(t) + σ·(RecoveryRate − DrainRate) | F80: A, M, π, ρ, σ | G80: Metabolic | H80: π,ρ,σ: 0.05–0.2
A81: EQ_SENS_06 | B81: Sensory Integration | C81: Sensing | D81: I(t+1) = τ·(Touch + Smell + Sound + Light) | E81: P(t+1) = υ·I(t)·AttentionWeight | F81: I, P, τ, υ | G81: Sensing | H81: τ,υ: 0.1–0.5
A82: EQ_EMOT_07 | B82: Emotion & Reinforcement | C82: Emotion | D82: R(t+1) = R(t) + φ·(RewardSignal − PunishmentSignal) | E82: H(t+1) = H(t) + χ·(Dopamine + Serotonin − Cortisol) | F82: R, H, φ, χ | G82: Emotion | H82: φ,χ: 0.05–0.2
A83: EQ_PRED_08 | B83: Predictive Simulation Kernel | C83: Cognition | D83: P(t+1) = P(t) + ψ·(ExpectedState − ActualState) | E83: E(t+1) = E(t) − ω·PredictionError | F83: P, E, ψ, ω | G83: Prediction | H83: ψ,ω: 0.01–0.1
A84: EQ_ATTN_09 | B84: Attention Control System | C84: Cognition | D84: A(t+1) = A(t) + α₁·StimulusIntensity − β₁·DistractionRate | E84: — | F84: A, α₁, β₁ | G84: Attention | H84: α₁,β₁: 0.05–0.2
A85: EQ_CONS_10 | B85: Consciousness Loop | C85: Meta-Cognition | D85: C(t+1) = Σᵢ(InternalStateᵢ·Feedbackᵢ) | E85: S(t+1) = ExpectedSelf − ActualSelf | F85: C, S | G85: Consciousness | H85: Weights: 0.1–1.0
A86: EQ_WRLD_11 | B86: World & NPC System | C86: Environment | D86: W(t+1) = W(t) + α₂·ResourceChange − β₂·ConsumptionRate | E86: N(t+1) = N(t) + γ₂·SocialInteraction + δ₂·LearningRate | F86: W, N, α₂, β₂, γ₂, δ₂ | G86: World | H86: α₂,β₂,γ₂,δ₂: 0.01–0.1
A87: EQ_LANG_12 | B87: Language Acquisition | C87: Language | D87: L(t+1) = L(t) + λ·ExposureFreq·AttentionWeight | E87: V(t+1) = V(t) + μ·ReinforcementSignal·ContextMatch | F87: L, V, λ, μ | G87: Cognition | H87: λ,μ: 0.01–0.05
A88: 📊 BIOLOGICAL CONSTANTS
A89: Constant ID | B89: Symbol | C89: Greek Letter | D89: Meaning | E89: Typical Min | F89: Typical Max | G89: Current Value | H89: Domain
A90: CONST_ALPHA | B90: α | C90: Alpha | D90: Growth coefficient (primary) | E90: 0.01 | F90: 0.1 | G90: 0.05 | H90: Development
A91: CONST_BETA | B91: β | C91: Beta | D91: Growth coefficient (secondary) | E91: 0.01 | F91: 0.1 | G91: 0.05 | H91: Development
A92: CONST_GAMMA | B92: γ | C92: Gamma | D92: Maturity index coefficient | E92: 0.01 | F92: 0.1 | G92: 0.03 | H92: Development
A93: CONST_DELTA | B93: δ | C93: Delta | D93: Cell division rate constant | E93: 0.1 | F93: 1 | G93: 0.5 | H93: Embodiment
A94: CONST_EPSILON | B94: ε | C94: Epsilon | D94: Nutrient flow constant | E94: 0.1 | F94: 1 | G94: 0.6 | H94: Embodiment
A95: CONST_ZETA | B95: ζ | C95: Zeta | D95: Oxygen exchange constant | E95: 0.1 | F95: 1 | G95: 0.4 | H95: Embodiment
A96: CONST_ETA | B96: η | C96: Eta | D96: Waste removal rate | E96: 0.1 | F96: 0.5 | G96: 0.2 | H96: Embodiment
A97: CONST_THETA | B97: θ | C97: Theta | D97: Synapse density coefficient | E97: 0.001 | F97: 0.05 | G97: 0.02 | H97: Neural
A98: CONST_IOTA | B98: ι | C98: Iota | D98: Neural gain coefficient | E98: 0.001 | F98: 0.05 | G98: 0.015 | H98: Neural
A99: CONST_KAPPA | B99: κ | C99: Kappa | D99: Input signal multiplier | E99: 0.001 | F99: 0.05 | G99: 0.03 | H99: Neural
A100: CONST_LAMBDA | B100: λ | C100: Lambda | D100: Noise attenuation factor | E100: 0.001 | F100: 0.05 | G100: 0.01 | H100: Neural
A101: CONST_MU | B101: μ | C101: Mu | D101: Heartbeat rate coefficient | E101: 0.1 | F101: 0.5 | G101: 0.3 | H101: Circulatory
... A112: CONST_OMEGA | B112: ω | C112: Omega | D112: Error correction rate | E112: 0.01 | F112: 0.1 | G112: 0.04 | H112: Cognition
...

Sheet 📈 Growth Timeline
A1: ⚡ LIVE TICK PANEL — All values auto-update from 🧬 DNA Loop Engine B4 (Current Tick)
A2: Current Tick: | B2: ='🧬 DNA Loop Engine'!B4 -> 10000 | C2: Current Week: | D2: ='🧬 DNA Loop Engine'!B5 -> 125 | E2: Birth Status: | F2: ='🧬 DNA Loop Engine'!B8 -> 🎉 BIRTH COMPLETE
A3: Life Stage: | B3: ='🧬 DNA Loop Engine'!B15 -> 🧒 Toddler | C3: Age: | D3: ='🧬 DNA Loop Engine'!B16 -> 19.6 months (1.63 yrs) | E3: DNA Phase: | F3: ='🧬 DNA Loop Engine'!B11 -> Toddler
A4: Growth Factor: | B4: ='🧬 DNA Loop Engine'!B18 -> 1 | C4: Neural Gain: | D4: ='🧬 DNA Loop Engine'!B19 -> 1 | E4: Cord Status: | F4: ='🧬 DNA Loop Engine'!B22 -> 🔌 SEVERED
A5: G_phys (height): | B5: ='🧬 DNA Loop Engine'!B28 -> 1.706 | C5: Heart Rate: | D5: ='🧬 DNA Loop Engine'!B27 -> 70 | E5: Reflex Gain: | F5: ='🧬 DNA Loop Engine'!B20 -> 1
A6: 📈 A7DO UNIFIED GROWTH TIMELINE — Anatomy & Development Across All Life Stages
A7: PRENATAL (Wk 0–40) | C7: BIRTH EVENT (Wk 40) | D7: INFANT (Wk 40–92) | F7: TODDLER (Wk 92–156) | H7: CHILD (Wk 156–624) | J7: ADOLESCENT (Wk 624–936) | L7: ADULT (Wk 936+) | N7: CURRENT STATE
A8: 📊 LIFECYCLE PHASE SUMMARY — When Growth Stops & What Continues
A9: Phase | B9: Week Range | C9: Age Range | D9: Growth Factor | E9: Neural Gain | F9: Cognitive Maturity | G9: Identity Formation | H9: Growth Active? | I9: What Continues After Growth Stops
A10: Prenatal | B10: Wk 0–40 | C10: – | D10: 0.01→1.0 | E10: 0→1.0 | F10: 0% | G10: 0% | H10: ✅ YES | I10: All biological growth active
A11: Birth Event | B11: Wk 40 | C11: 0 months | D11: 1.0 peak | E11: 1.0 | F11: 2% | G11: 0% | H11: 🔴 STOP | I11: Umbilical severs; pulmonary breathing starts
A12: Early Infant | B12: Wk 40–60 | C12: 0–3 months | D12: 1.0 fixed | E12: 1.0 | F12: 4–10% | G12: 0% | H12: 🔴 STOP | I12: Sensory calibration, reflex→voluntary control
A13: Late Infant | B13: Wk 60–92 | C13: 3–12 months | D13: 1.0 fixed | E13: 1.0 | F13: 10–22% | G13: 0% | H13: 🔴 STOP | I13: Motor skills, object permanence, first words
A14: Toddler | B14: Wk 92–156 | C14: 1–3 years | D14: 1.0 fixed | E14: 1.0 | F14: 22–35% | G14: 0% | H14: 🔴 STOP | I14: Walking, symbolic play, language explosion
A15: Early Childhood | B15: Wk 156–312 | C15: 3–6 years | D15: 1.0 fixed | E15: 1.0 | F15: 35–70% | G15: 0% | H15: 🔴 STOP | I15: Language cortex matures; reading/writing
A16: Mid Childhood | B16: Wk 312–624 | C16: 6–12 years | D16: 1.0 fixed | E16: 1.0 | F16: 70–90% | G16: 0–5% | H16: 🔴 STOP | I16: Prefrontal cortex matures; logical reasoning
A17: Adolescence | B17: Wk 624–936 | C17: 12–18 years | D17: 1.0 fixed | E17: 1.0 | F17: 90–100% | G17: 5–90% | H17: 🔴 STOP | I17: Abstract reasoning, identity, puberty, emotion reg.
A18: Early Adult | B18: Wk 936–1100 | C18: 18–21 years | D18: 1.0 fixed | E18: 1.0 | F18: 100% | G18: 95–98% | H18: 🔴 STOP | I18: Strategic reasoning, long-term memory deepening
A19: Mature Adult
A21: ⚠️ NOTE: 'Growth Factor' = physical/biological growth (stops at birth). Cognitive Maturity % and Identity Formation % continue developing post-birth through learning, experience, and neural plasticity — NOT through the Growth Factor.
A26: 🧬 A — PRENATAL PHASES & ORGAN ACTIVATION
A27: Phase | B27: Weeks | C27: Biological Focus | D27: Activation % | E27: DNA Trigger | F27: Key Organ/System | G27: Activation Event | H27: DNA Code | I27: Notes | J27: → Next Phase Condition
A28: 1 | B28: 0–4 | C28: Embryogenesis | D28: 0–10% | E28: DNA_INIT | F28: Neural plate formed | G28: Neural Plate | H28: Formation | I28: NP_FORM | J28: Primitive streak defines axes
A29: 2 | B29: 4–8 | C29: Organogenesis | D29: 10–25% | E29: ORG_START | F29: Limb buds visible | G29: Heart | H29: Chamber partition | I29: HT_PART | J29: First rhythmic contractions
A30: 3 | B30: 8–12 | C30: Body Plan | D30: 25–40% | E30: BODY_FORM | F30: Reflex seed active | G30: Limbs | H30: Differentiation | I30: LM_DIFF | J30: Fingers/toes separate
A31: 4 | B31: 12–20 | C31: Reflex Explosion | D31: 40–60% | E31: REFLEX_ON | F31: Stretch reflex stable | G31: Reflex Arcs | H31: Activation | I31: RF_ACT | J31: Stretch reflex online
A32: 5 | B32: 20–28 | C32: Neural Maturation | D32: 60–80% | E32: NEURAL_GROW | F32: Predictive circuits online | G32: Cerebellum | H32: Growth | I32: CB_GROW | J32: Predictive control begins
A33: 6 | B33: 28–36 | C33: Pre‑Birth Integration | D33: 80–95% | E33: INTEGRATE | F33: Reflexes synchronised | G33: Myelination | H33: Neural insulation | I33: MYEL_ON | J33: Faster reflex transmission
A34: 7 | B34: 36–40 | C34: Birth Preparation | D34: 95–100% | E34: BIRTH_READY | F34: Lungs mature | G34: Lungs | H34: Maturation | I34: LG_MAT | J34: Ready for external oxygen
A36: ⚡ B — TICK MILESTONES & GROWTH FACTORS — Full Lifecycle (Prenatal → Adult)
A37: Tick ID | B37: Week | C37: Age Label | D37: DNA Phase | E37: Growth Factor | F37: Neural Gain | G37: Reflex Gain | H37: Identity Confidence | I37: Cognitive Maturity % | J37: Identity Formation % | K37: Puberty Status | L37: Growth Active | M37: Key Milestone / Event
A38: ── PRENATAL ──
A39: T000 | B39: 0 | C39: Prenatal | D39: Embryogenesis | E39: 0.01 | F39: 0 | G39: 0 | H39: 0 | I39: 0 | J39: 0 | K39: Pre-Puberty | L39: 🟢 Growing | M39: Fertilisation / cell division begins
A40: T500 | B40: 4 | C40: Prenatal | D40: Organogenesis | E40: 0.1 | F40: 0.05 | G40: 0 | H40: 0 | I40: 0 | J40: 0 | K40: Pre-Puberty | L40: 🟢 Growing | M40: Heart chambers forming
A41: T1000 | B41: 8 | C41: Prenatal | D41: Body Plan | E41: 0.25 | F41: 0.1 | G41: 0.05 | H41: 0.1 | I41: 0 | J41: 0 | K41: Pre-Puberty | L41: 🟢 Growing | M41: Limb buds visible
A42: T1500 | B42: 12 | C42: Prenatal | D42: Reflex Explosion | E42: 0.4 | F42: 0.25 | G42: 0.2 | H42: 0.25 | I42: 0 | J42: 0 | K42: Pre-Puberty | L42: 🟢 Growing | M42: Reflex arcs online
A43: T2000 | B43: 20 | C43: Prenatal | D43: Neural Maturation | E43: 0.6 | F43: 0.4 | G43: 0.4 | H43: 0.5 | I43: 0 | J43: 0 | K43: Pre-Puberty | L43: 🟢 Growing | M43: Cerebellum growth surge
A44: T2500 | B44: 28 | C44: Prenatal | D44: Pre-Birth Integration | E44: 0.8 | F44: 0.6 | G44: 0.6 | H44: 0.75 | I44: 0 | J44: 0 | K44: Pre-Puberty | L44: 🟢 Growing | M44: Myelination begins
A45: T3000 | B45: 36 | C45: Prenatal | D45: Birth Preparation | E45: 0.95 | F45: 0.8 | G45: 0.8 | H45: 0.9 | I45: 0 | J45: 0 | K45: Pre-Puberty | L45: 🟢 Growing | M45: Lungs maturing
A46: ── BIRTH ──
A47: T3200 | B47: 40 | C47: Birth | D47: Birth Event | E47: 1 | F47: 1 | G47: 1 | H47: 1 | I47: 2 | J47: 0 | K47: Pre-Puberty | L47: 🔴 Stopped | M47: Umbilical cord severed; pulmonary breathing
A48: ── INFANT ──
A49: T3600 | B49: 45 | C49: Infant | D49: Early Infant | E49: 1 | F49: 1 | G49: 1 | H49: 1 | I49: 4 | J49: 0 | K49: Pre-Puberty | L49: 🔴 Stopped | M49: Sensory systems calibrating
A50: T4000 | B50: 50 | C50: Infant | D50: Early Infant | E50: 1 | F50: 1 | G50: 1 | H50: 1 | I50: 6 | J50: 0 | K50: Pre-Puberty | L50: 🔴 Stopped | M50: Social smile emerges
A51: T4800 | B51: 60 | C51: Infant | D51: Late Infant | E51: 1 | F51: 1 | G51: 1 | H51: 1 | I51: 10 | J51: 0 | K51: Pre-Puberty | L51: 🔴 Stopped | M51: Object permanence forming
A52: T5600 | B52: 70 | C52: Infant | D52: Late Infant | E52: 1 | F52: 1 | G52: 1 | H52: 1 | I52: 14 | J52: 0 | K52: Pre-Puberty | L52: 🔴 Stopped | M52: Crawling / pulling to stand
A53: T6400 | B53: 80 | C53: Infant | D53: Late Infant | E53: 1 | F53: 1 | G53: 1 | H53: 1 | I53: 18 | J53: 0 | K53: Pre-Puberty | L53: 🔴 Stopped | M53: First words forming
A54: ── TODDLER ──
A55: T7200 | B55: 90 | C55: Toddler | D55: Toddler | E55: 1 | F55: 1 | G55: 1 | H55: 1 | I55: 22 | J55: 0 | K55: Pre-Puberty | L55: 🔴 Stopped | M55: Walking independently
A56: T8000 | B56: 100 | C56: Toddler | D56: Toddler | E56: 1 | F56: 1 | G56: 1 | H56: 1 | I56: 26 | J56: 0 | K56: Pre-Puberty | L56: 🔴 Stopped | M56: Symbolic play begins
A57: T10000 | B57: 125 | C57: Toddler | D57: Early Childhood | E57: 1 | F57: 1 | G57: 1 | H57: 1 | I57: 31 | J57: 0 | K57: Pre-Puberty | L57: 🔴 Stopped | M57: Current state — A7DO ~19.6 months
A58: ── CHILD ──
A59: T15600 | B59: 195 | C59: Child | D59: Early Childhood | E59: 1 | F59: 1 | G59: 1 | H59: 1 | I59: 40 | J59: 0 | K59: Pre-Puberty | L59: 🔴 Stopped | M59: Language cortex 50% mature
A60: T20800 | B60: 260 | C60: Child | D60: Mid Childhood | E60: 1 | F60: 1 | G60: 1 | H60: 1 | I60: 55 | J60: 0 | K60: Pre-Puberty | L60: 🔴 Stopped | M60: Reading & writing consolidating
A61: T24960 | B61: 312 | C61: Child | D61: Mid Childhood | E61: 1 | F61: 1 | G61: 1 | H61: 1 | I61: 70 | J61: 0 | K61: Pre-Puberty | L61: 🔴 Stopped | M61: Language cortex 100% mature
A62: T31200 | B62: 390 | C62: Child | D62: Late Childhood | E62: 1 | F62: 1 | G62: 1 | H62: 1 | I62: 80 | J62: 0 | K62: Pre-Puberty | L62: 🔴 Stopped | M62: Logical reasoning emerging
A63: ── CHILD→ADOL. ── | B63: 20 | C63: Neural Maturation | D63: 0.6 | E63: 0.4 | F63: 0.4 | G63: 0.5
A64: T49920 | B64: 624 | C64: Child→Adol. | D64: Late Childhood | E64: 1 | F64: 1 | G64: 1 | H64: 1 | I64: 90 | J64: 5 | K64: Pre-Puberty | L64: 🔴 Stopped | M64: Prefrontal cortex 100% mature; puberty onset
A65: ── ADOLESCENT ── | B65: 36 | C65: Birth Preparation | D65: 0.95 | E65: 0.8 | F65: 0.8 | G65: 0.9
A66: T56000 | B66: 700 | C66: Adolescent | D66: Early Adolescence | E66: 1 | F66: 1 | G66: 1 | H66: 1 | I66: 93 | J66: 20 | K66: Early Puberty | L66: 🔴 Stopped | M66: Abstract reasoning activating
A67: T62400 | B67: 780 | C67: Adolescent | D67: Mid Adolescence | E67: 1 | F67: 1 | G67: 1 | H67: 1 | I67: 96 | J67: 45 | K67: Mid Puberty | L67: 🔴 Stopped | M67: Identity formation accelerating
A68: T68000 | B68: 850 | C68: Adolescent | D68: Late Adolescence | E68: 1 | F68: 1 | G68: 1 | H68: 1 | I68: 98 | J68: 70 | K68: Late Puberty | L68: 🔴 Stopped | M68: Emotional regulation maturing
A69: ── ADOLESCENT→ADULT ── | B69: 60 | C69: Late Infant | D69: 1 | E69: 1 | F69: 1 | G69: 1
A70: T74880 | B70: 936 | C70: Adolescent→Adult | D70: Adolescent Complete | E70: 1 | F70: 1 | G70: 1 | H70: 1 | I70: 100 | J70: 90 | K70: Post-Puberty | L70: 🔴 Stopped | M70: All adolescent systems 100% mature
A71: ── ADULT ── | B71: 80 | C71: Late Infant | D71: 1 | E71: 1 | F71: 1 | G71: 1
A72: T80000 | B72: 1000 | C72: Adult | D72: Early Adult | E72: 1 | F72: 1 | G72: 1 | H72: 1 | I72: 100 | J72: 95 | K72: Adult | L72: 🔴 Stopped | M72: Strategic reasoning online
A73: T88000 | B73: 1100 | C73: Adult | D73: Mid Adult | E73: 1 | F73: 1 | G73: 1 | H73: 1 | I73: 100 | J73: 98 | K73: Adult | L73: 🔴 Stopped | M73: Long-term memory depth increasing
A74: T96000 | B74: 1200 | C74: Adult | D74: Mature Adult | E74: 1 | F74: 1 | G74: 1 | H74: 1 | I74: 100 | J74: 100 | K74: Adult | L74: 🔴 Stopped | M74: Wisdom index & creative synthesis peak
A76: 🦴 C — ANATOMY GROWTH ENGINE (Prenatal → Adult Skeleton & Organs)
A77: Name | B77: Category | C77: DNA Code | D77: Start Wk | E77: End Wk | F77: Growth Curve | G77: Domain | H77: Infant Size | I77: Child Size | J77: Adult Size | K77: Mass (kg) | L77: Connection | M77: Growth Status | N77: Notes
A78: Frontal Bone | B78: Skeleton | C78: SK_FRONTAL | D78: 4 | E78: 36 | F78: Sigmoid | G78: Embodiment | I78: 8 | J78: 12 | K78: 0.05 | L78: Suture | M78: ✅ Complete | N78: Forehead
A79: Parietal Bone (Left) | B79: Skeleton | C79: SK_PAR_L | D79: 4 | E79: 36 | F79: Sigmoid | G79: Embodiment | J79: 13 | K79: 0.04 | L79: Suture | M79: ✅ Complete | N79: Skull top left
A80: Parietal Bone (Right) | B80: Skeleton | C80: SK_PAR_R | D80: 4 | E80: 36 | F80: Sigmoid | G80: Embodiment | J80: 13 | K80: 0.04 | L80: Suture | M80: ✅ Complete | N80: Skull top right
A81: Temporal Bone (Left) | B81: Skeleton | C81: SK_TEMP_L | D81: 4 | E81: 36 | F81: Sigmoid | G81: Embodiment | J81: 5 | K81: 0.03 | L81: Suture | M81: ✅ Complete | N81: Temple left
A82: Temporal Bone (Right) | B82: Skeleton | C82: SK_TEMP_R | D82: 4 | E82: 36 | F82: Sigmoid | G82: Embodiment | J82: 5 | K82: 0.03 | L82: Suture | M82: ✅ Complete | N82: Temple right
A83: Occipital Bone | B83: Skeleton | C83: SK_OCCIPITAL | D83: 4 | E83: 36 | F83: Sigmoid | G83: Embodiment | J83: 10 | K83: 0.06 | L83: Suture | M83: ✅ Complete | N83: Back of skull
A84: Sphenoid Bone | B84: Skeleton | C84: SK_SPHENOID | D84: 4 | E84: 36 | F84: Sigmoid | G84: Embodiment | J84: 8 | K84: 0.02 | L84: Suture | M84: ✅ Complete | N84: Skull base
A85: Ethmoid Bone | B85: Skeleton | C85: SK_ETHMOID | D85: 4 | E85: 36 | F85: Sigmoid | G85: Embodiment | J85: 4 | K85: 0.01 | L85: Suture | M85: ✅ Complete | N85: Nasal bridge
A86: Nasal Bone (Left) | B86: Skeleton | C86: SK_NASAL_L | D86: 5 | E86: 20 | F86: Sigmoid | G86: Embodiment | M86: ✅ Complete
A87: Nasal Bone (Right) | B87: Skeleton | C87: SK_NASAL_R | D87: 5 | E87: 20 | F87: Sigmoid | G87: Embodiment | M87: ✅ Complete
A88: Lacrimal Bone (Left) | B88: Skeleton | C88: SK_LACRIMAL_L | D88: 5 | E88: 20 | F88: Sigmoid | G88: Embodiment | M88: ✅ Complete
A89: Lacrimal Bone (Right) | B89: Skeleton | C89: SK_LACRIMAL_R | D89: 5 | E89: 20 | F89: Sigmoid | G89: Embodiment | M89: ✅ Complete
A90: Zygomatic Bone (Left) | B90: Skeleton | C90: SK_ZYGO_L | D90: 5 | E90: 20 | F90: Sigmoid | G90: Embodiment | M90: ✅ Complete
A91: Zygomatic Bone (Right) | B91: Skeleton | C91: SK_ZYGO_R | D91: 5 | E91: 20 | F91: Sigmoid | G91: Embodiment | M91: ✅ Complete
A92: Maxilla (Left) | B92: Skeleton | C92: SK_MAX_L | D92: 5 | E92: 20 | F92: Sigmoid | G92: Embodiment | J92: 5 | K92: 0.02 | L92: Suture | M92: ✅ Complete | N92: Upper jaw left
A93: Maxilla (Right) | B93: Skeleton | C93: SK_MAX_R | D93: 5 | E93: 20 | F93: Sigmoid | G93: Embodiment | J93: 5 | K93: 0.02 | L93: Suture | M93: ✅ Complete | N93: Upper jaw right
A94: Mandible | B94: Skeleton | C94: SK_MANDIBLE | D94: 6 | E94: 36 | F94: Sigmoid | G94: Embodiment | J94: 12 | K94: 0.08 | L94: TMJ | M94: ✅ Complete | N94: Jaw bone
A95: Palatine Bone (Left) | B95: Skeleton | C95: SK_PAL_L | D95: 6 | E95: 20 | F95: Sigmoid | G95: Embodiment | M95: ✅ Complete
A96: Palatine Bone (Right) | B96: Skeleton | C96: SK_PAL_R | D96: 6 | E96: 20 | F96: Sigmoid | G96: Embodiment | M96: ✅ Complete
A97: Inferior Nasal Concha (Left) | B97: Skeleton | C97: SK_CONCHA_L | D97: 6 | E97: 20 | F97: Sigmoid | G97: Embodiment | M97: ✅ Complete
A98: Inferior Nasal Concha (Right) | B98: Skeleton | C98: SK_CONCHA_R | D98: 6 | E98: 20 | F98: Sigmoid | G98: Embodiment | M98: ✅ Complete
A99: Vomer | B99: Skeleton | C99: SK_VOMER | D99: 6 | E99: 20 | F99: Sigmoid | G99: Embodiment | M99: ✅ Complete
A100: Malleus (Left) | B100: Skeleton | C100: SK_MAL_L | D100: 6 | E100: 16 | F100: Sigmoid | G100: Embodiment | M100: ✅ Complete
A101: Malleus (Right) | B101: Skeleton | C101: SK_MAL_R | D101: 6 | E101: 16 | F101: Sigmoid | G101: Embodiment | M101: ✅ Complete
A102: Incus (Left) | B102: Skeleton | C102: SK_INC_L | D102: 6 | E102: 16 | F102: Sigmoid | G102: Embodiment | M102: ✅ Complete
A103: Incus (Right) | B103: Skeleton | C103: SK_INC_R | D103: 6 | E103: 16 | F103: Sigmoid | G103: Embodiment | M103: ✅ Complete
A104: Stapes (Left) | B104: Skeleton | C104: SK_STAP_L | D104: 6 | E104: 16 | F104: Sigmoid | G104: Embodiment | M104: ✅ Complete
A105: Stapes (Right) | B105: Skeleton | C105: SK_STAP_R | D105: 6 | E105: 16 | F105: Sigmoid | G105: Embodiment | M105: ✅ Complete
A106: Hyoid | B106: Skeleton | C106: SK_HYOID | D106: 6 | E106: 20 | F106: Sigmoid | G106: Embodiment | M106: ✅ Complete
A107: Cervical Vertebrae (C1–C7) | B107: Skeleton | C107: SK_CERV | D107: 4 | E107: 36 | F107: Sigmoid | G107: Embodiment | J107: 12 | K107: 0.1 | L107: Intervertebral | M107: ✅ Complete | N107: Neck vertebrae
...

Sheet 🧮 Mathematical Framework
A1: ⚡ LIVE TICK PANEL — All values auto-update from 🧬 DNA Loop Engine B4 (Current Tick)
A2: Current Tick: | B2: ='🧬 DNA Loop Engine'!B4 -> 10000 | C2: Current Week: | D2: ='🧬 DNA Loop Engine'!B5 -> 125 | E2: Birth Status: | F2: ='🧬 DNA Loop Engine'!B8 -> 🎉 BIRTH COMPLETE
A3: Life Stage: | B3: ='🧬 DNA Loop Engine'!B15 -> 🧒 Toddler | C3: Age: | D3: ='🧬 DNA Loop Engine'!B16 -> 19.6 months (1.63 yrs) | E3: DNA Phase: | F3: ='🧬 DNA Loop Engine'!B11 -> Toddler
A4: Growth Factor: | B4: ='🧬 DNA Loop Engine'!B18 -> 1 | C4: Neural Gain: | D4: ='🧬 DNA Loop Engine'!B19 -> 1 | E4: Cord Status: | F4: ='🧬 DNA Loop Engine'!B22 -> 🔌 SEVERED
A5: G_phys (height): | B5: ='🧬 DNA Loop Engine'!B28 -> 1.706 | C5: Heart Rate: | D5: ='🧬 DNA Loop Engine'!B27 -> 70 | E5: Reflex Gain: | F5: ='🧬 DNA Loop Engine'!B20 -> 1
A6: 🧮 A7DO GENESIS MIND — UNIFIED MATHEMATICAL FRAMEWORK | All Subsystems · Equations · Parameters · Model Comparisons
A7: 🏗️ SUBSYSTEM INTERACTION ARCHITECTURE
A8: Central hub: Genesis Mind Runtime → Global Workspace broadcasts to all modules. Reality Bridge links World Map + NPC Network to internal state. Body Systems ↔ Motor System ↔ Energy/ATP form the embodiment loop. All cognitive modules (Emotion, Language, Learning, WM, Memory, Attention, Consciousness) couple via Global Workspace.
A9: Subsystem | B9: Inputs From | C9: Outputs To | D9: Coupling Type | E9: Time Scale | F9: Model Class
A10: Genesis Mind Runtime | B10: All modules | C10: Global Workspace, Motor | D10: Hub/broadcast | E10: ms–s | F10: Orchestrator FSM
A11: Global Workspace (GW) | B11: All cognitive modules | C11: All modules (broadcast) | D11: Attention-weighted | E11: 100–500 ms | F11: Softmax / GNT oscillator
A12: Emotion Module | B12: Neuromodulators, Sensory, GW | C12: GW, Motor, Language | D12: State machine + ODE | E12: s–min | F12: Markov FSM + ODE
A13: Language Engine | B13: Auditory, GW, Memory | C13: GW, Motor (speech) | D13: Sequence model | E13: ms–s | F13: Logistic growth + RNN
A14: Learning Module | B14: Sensory, Reward, GW | C14: Memory, Weights | D14: Hebbian + RL | E14: ms–hours | F14: STDP + TD-learning
A15: Working Memory (WM) | B15: GW, Sensory, Attention | C15: GW, Decision, Language | D15: Capacity-limited ODE | E15: s | F15: Baddeley + ODE decay
A16: Long-term Memory (LTM) | B16: WM, Hippocampus | C16: WM, GW (retrieval) | D16: Consolidation ODE | E16: hours–years | F16: Hopfield / engram model
A17: Motor System | B17: GW, Reflex arcs, Body | C17: Muscles, Body Systems | D17: CPG + feedback | E17: ms–s | F17: CPG oscillator + PID
A18: Body Systems | B18: DNA Engine, Energy, Motor | C18: Motor, Sensory, Energy | D18: Growth ODE | E18: weeks–years | F18: Sigmoid growth ODE
A19: Reality Bridge | B19: World Map, NPC, Sensory | C19: GW, WM, Motor | D19: Sensory integration | E19: ms | F19: Bayesian fusion
A20: NPC Agent Network | B20: World, GW (A7DO), DNA | C20: World, A7DO (social input) | D20: Multi-agent MDP | E20: s–days | F20: MDP + social learning
... A24: Attention Control | B24: GW, Sensory salience | C24: GW (gating), WM | D24: Salience weighting | E24: ms–100ms | F24: Biased competition
A26: 1️⃣ NEURONAL DYNAMICS — Hodgkin–Huxley vs Izhikevich vs Leaky Integrate-and-Fire
A27: 1A. Hodgkin–Huxley Model (1952)
A28: Equation / Variable | B28: Formula | C28: Description | D28: Typical Value / Range | E28: Units | F28: Notes
A29: Membrane potential ODE | B29: Cm·dV/dt = I_ext − ḡNa·m³h·(V−ENa) − ḡK·n⁴·(V−EK) − ḡL·(V−EL) | C29: Sum of ionic currents drives membrane voltage | D29: V_rest ≈ −65 mV; V_peak ≈ +40 mV | E29: mV, ms, µF/cm², mS/cm² | F29: Stiff ODE; requires dt < 0.1 ms for Euler stability
A30: Na activation gate m | B30: dm/dt = αm(V)·(1−m) − βm(V)·m | C30: Fast Na⁺ activation (opens channel) | D30: m ∈ [0,1]; τm ≈ 0.1–1 ms | E30: dimensionless | F30: αm = 0.1(V+40)/(1−exp(−(V+40)/10)); βm = 4·exp(−(V+65)/18)
A31: Na inactivation gate h | B31: dh/dt = αh(V)·(1−h) − βh(V)·h | C31: Slow Na⁺ inactivation (closes channel) | D31: h ∈ [0,1]; τh ≈ 1–10 ms | E31: dimensionless | F31: αh = 0.07·exp(−(V+65)/20); βh = 1/(1+exp(−(V+35)/10))
A32: K activation gate n | B32: dn/dt = αn(V)·(1−n) − βn(V)·n | C32: K⁺ activation (repolarisation) | D32: n ∈ [0,1]; τn ≈ 1–5 ms | E32: dimensionless | F32: αn = 0.01(V+55)/(1−exp(−(V+55)/10)); βn = 0.125·exp(−(V+65)/80)
A33: Max conductances | B33: ḡNa=120, ḡK=36, ḡL=0.3 mS/cm² | C33: Peak ionic conductances | D33: ḡNa=120, ḡK=36, ḡL=0.3 | E33: mS/cm² | F33: Cm=1 µF/cm²; ENa=+50, EK=−77, EL=−54.4 mV
A34: Spike threshold | B34: V_thresh ≈ −55 mV (emergent) | C34: Action potential fires when V crosses threshold | D34: ≈ −55 mV | E34: mV | F34: Not a hard threshold — emerges from gating dynamics
A35: Stability condition | B35: dt < τ_min/10 ≈ 0.01 ms for Euler; use RK4 for dt ≈ 0.1 ms | C35: Numerical stability requirement | D35: dt = 0.01–0.1 ms | E35: ms | F35: Implicit methods (Crank-Nicolson) allow larger dt
A37: 1B. Izhikevich Model (2003)
A38: Equation / Variable | B38: Formula | C38: Description | D38: Typical Value / Range | E38: Units | F38: Notes
A39: Membrane potential ODE | B39: dv/dt = 0.04v² + 5v + 140 − u + I | C39: Quadratic approximation of AP initiation | D39: v_rest ≈ −65 mV; v_peak = 30 mV (reset threshold) | E39: mV, ms, pA | F39: Dimensionless form; v in mV, t in ms
A40: Recovery variable ODE | B40: du/dt = a·(b·v − u) | C40: Slow recovery current (K⁺ / Na⁺ inactivation) | D40: a=0.02–0.1; b=0.2–0.25 | E40: dimensionless | F40: a controls recovery speed; b controls sensitivity of u to v
A41: Spike reset rule | B41: IF v ≥ 30 mV THEN v ← c; u ← u + d | C41: Discrete reset after spike | D41: c = −65 to −50 mV; d = 2–8 | E41: mV (v), dimensionless (u) | F41: Reset mimics after-hyperpolarisation
A42: Regular spiking (RS) params | B42: a=0.02, b=0.2, c=−65, d=8 | C42: Excitatory cortical neuron (most common) | D42: Fires tonically with adaptation | E42: — | F42: Recommended default for A7DO cortical neurons
A43: Fast spiking (FS) params | B43: a=0.1, b=0.2, c=−65, d=2 | C43: Inhibitory interneuron | D43: High-frequency, no adaptation | E43: — | F43: Use for GABAergic interneurons in A7DO
A44: Bursting (IB) params | B44: a=0.02, b=0.2, c=−55, d=4 | C44: Intrinsically bursting neuron | D44: Initial burst then tonic | E44: — | F44: Use for thalamic relay, some cortical layer 5
A45: Stability / integration | B45: Euler: dt = 0.5 ms; RK2: dt = 1 ms | C45: Stable with modest time steps | D45: dt = 0.1–1 ms | E45: ms | F45: Much cheaper than HH; recommended for large A7DO networks
A46: Synaptic input I | B46: I(t) = Σ_j w_ij · δ(t − t_j^spike) * exp(−t/τ_syn) | C46: Exponential synaptic kernel | D46: τ_syn = 5 ms (AMPA), 10 ms (NMDA), 6 ms (GABA) | E46: pA or mV | F46: Convolve spike train with kernel for smooth input
A48: 1C. Model Comparison & A7DO Recommendation
A49: Criterion | B49: Hodgkin–Huxley | C49: Izhikevich | D49: Leaky Integrate-and-Fire | E49: A7DO Recommendation
A50: Biological accuracy | B50: ⭐⭐⭐⭐⭐ Exact AP shape, ionic currents | C50: ⭐⭐⭐⭐ Realistic spiking patterns | D50: ⭐⭐ Rate-code only | E50: HH for critical sensorimotor; Izhikevich for cortex
A51: Computational cost | B51: 🔴 HIGH — 4 ODEs, dt<0.1ms | C51: 🟡 LOW — 2 ODEs + reset, dt≈0.5ms | D51: 🟢 VERY LOW — 1 ODE | E51: Izhikevich for large networks (NPC, cortex)
A52: Spiking patterns | B52: All biological patterns | C52: 20+ patterns (RS, FS, IB, CH…) | D52: Single pattern only | E52: Izhikevich covers all needed A7DO patterns
A53: Parameter tuning | B53: Biophysical (conductances, kinetics) | C53: 4 params (a,b,c,d) per neuron type | D53: 1 param (τ, threshold) | E53: Izhikevich easiest to tune per cell type
A54: Stability | B54: Requires implicit solver or dt<0.01ms | C54: Euler stable at dt=0.5ms | D54: Always stable | E54: Izhikevich with RK2 at dt=0.5ms
A55: Use in A7DO | B55: Reflex arcs, critical sensory neurons | C55: Cortex, hippocampus, NPC brains | D55: Massive background nets | E55: Hybrid: HH for reflexes, Izhikevich for cognition
A56: Integration method | B56: RK4 or Crank-Nicolson | C56: Euler or RK2 | D56: Euler | E56: RK2 for Izhikevich; RK4 for HH
A57: Initial conditions | B57: V=−65mV, m/h/n at steady-state | C57: v=−65mV, u=b·v | D57: v=V_rest | E57: Set all to resting state at t=0
A59: 2️⃣ GLOBAL WORKSPACE & ATTENTION BROADCAST
A60: Component | B60: Equation / Formula | C60: Variables | D60: Parameters | E60: Dynamics | F60: Notes
A61: Module activation | B61: a_i(t) = σ(W_i · x_i(t) + b_i) | C61: x_i = module state vector; W_i = weight matrix; b_i = bias | D61: W_i learned; b_i tuned per module | E61: Continuous; updated each cognitive cycle (~100ms) | F61: σ = sigmoid or ReLU; a_i ∈ [0,1]
A62: Softmax attention weights | B62: w_i(t) = exp(β·a_i(t)) / Σ_j exp(β·a_j(t)) | C62: w_i = broadcast weight for module i; β = attentional gain | D62: β = 1–10 (low=diffuse, high=winner-take-all) | E62: Discrete per cognitive cycle; Σw_i = 1 | F62: β→∞ gives hard WTA; β=1 gives soft broadcast
A63: Global broadcast signal | B63: G(t) = Σ_i w_i(t) · x_i(t) | C63: G = global workspace content (broadcasted state) | D63: Dimensionality = max(dim(x_i)) | E63: Broadcast to all modules each cycle | F63: Equivalent to attention-weighted mean of module states
A64: Top-k winner selection | B64: W_active = {i : w_i > θ_GW}; broadcast x_i for i ∈ W_active | C64: θ_GW = workspace threshold (typically top 1–3 modules) | D64: θ_GW = 0.3–0.5 | E64: Discrete selection; others suppressed | F64: Implements ignition: sudden broadcast when threshold crossed
A65: Dynamical GNT coupling | B65: dx_i/dt = f(x_i, I_i) − g·Σ_j x_j + η_i(t) | C65: x_i = module population rate; g = global inhibition; η = noise | D65: g = 0.1–0.5; noise σ_η = 0.01 | E65: Continuous ODE; stable if g < 1/N | F65: Synchrony = Kuramoto r = |Σ exp(iφ_j)|/N; r→1 = full broadcast
A66: Binding strength (Kuramoto) | B66: r(t)·exp(iΨ) = (1/N)·Σ_j exp(i·φ_j(t)) | C66: φ_j = phase of oscillator j; r = order parameter [0,1] | D66: N = number of coupled modules | E66: r=0: incoherent; r=1: fully synchronised (broadcast) | F66: Threshold r > 0.7 → conscious broadcast in GWT
A67: Working memory gating | B67: WM(t+1) = WM(t)·(1−γ) + γ·G(t)·gate(t) | C67: gate(t) ∈ {0,1} = prefrontal gating signal; γ = update rate | D67: γ = 0.1–0.5; gate from PFC decision | E67: Discrete update per cognitive cycle | F67: Implements selective WM updating (Baddeley model)
A68: Stability condition | B68: Softmax: always stable (bounded weights). GNT: stable if g·N < max eigenvalue of coupling matrix | C68: Eigenvalue analysis of Jacobian at fixed point | D68: Ensure Re(λ_max) < 0 | E68: Check numerically for chosen g, N | F68: Add noise η for stochastic stability (avoids fixed-point trapping)
A70: 3️⃣ EMOTION STATE MACHINE — FSM + Neuromodulator ODEs
A71: Component | B71: Equation / Formula | C71: Variables | D71: Parameters | E71: Typical Values | F71: Notes
A72: Emotion states (FSM) | B72: E(t) ∈ {Calm, Content, Joyful, Curious, Excited, Fearful, Distressed, Sad, Angry} | C72: E = discrete emotion state | D72: 9 states; transition matrix P_ij(u) | E72: Initial state: Calm | F72: Markov chain; transition probabilities depend on neuromodulator levels
A73: Transition function | B73: E(t+Δt) = F_E(E(t), D(t), S(t), C(t), O(t), stimulus) | C73: D=dopamine, S=serotonin, C=cortisol, O=oxytocin | D73: Threshold θ per neuromodulator | E73: θ_D=0.6, θ_S=0.5, θ_C=0.4, θ_O=0.5 | F73: If D>θ_D AND stimulus=reward → E→Joyful/Excited
A74: Dopamine ODE | B74: dD/dt = −D/τ_D + r_D·Reward(t) + ε_D | C74: D ∈ [0,1]; Reward(t) = reward signal [0,1] | D74: τ_D = 30 s; r_D = 0.8 | E74: D_rest = 0.3; D_peak = 1.0 | F74: Encodes reward prediction; drives Joy/Excitement transitions
A75: Serotonin ODE | B75: dS/dt = −S/τ_S + r_S·Satiety(t) + ε_S | C75: S ∈ [0,1]; Satiety = food/comfort signal | D75: τ_S = 60 s; r_S = 0.5 | E75: S_rest = 0.5; S_peak = 0.9 | F75: Encodes contentment; drives Calm/Content transitions
A76: Cortisol ODE | B76: dC/dt = −C/τ_C + r_C·Stress(t) − k_CS·S(t) + ε_C | C76: C ∈ [0,1]; Stress = threat/pain signal; k_CS = serotonin suppression | D76: τ_C = 120 s; r_C = 0.7; k_CS = 0.3 | E76: C_rest = 0.2; C_peak = 0.9 | F76: Encodes stress; drives Fear/Distressed/Sad transitions
A77: Oxytocin ODE | B77: dO/dt = −O/τ_O + r_O·Social(t) + ε_O | C77: O ∈ [0,1]; Social = positive social contact signal | D77: τ_O = 90 s; r_O = 0.6 | E77: O_rest = 0.3; O_peak = 0.95 | F77: Encodes bonding; drives Content/Joyful transitions; suppresses Fear
A78: Valence dimension | B78: V(t) = w_D·D(t) + w_S·S(t) − w_C·C(t) + w_O·O(t) | C78: V ∈ [−1,+1]; positive = pleasant, negative = unpleasant | D78: w_D=0.4, w_S=0.3, w_C=0.5, w_O=0.3 | E78: V > 0.5 → Joyful; V < −0.3 → Sad/Fearful | F78: Russell's circumplex model: Valence × Arousal 2D space
A79: Arousal dimension | B79: A(t) = w_D·D(t) + w_C·C(t) − w_S·S(t) | C79: A ∈ [0,1]; high = activated, low = calm | D79: w_D=0.5, w_C=0.4, w_S=0.3 | E79: A > 0.7 → Excited/Fearful; A < 0.3 → Calm/Sad | F79: Arousal axis orthogonal to Valence in circumplex
A80: Emotion→behaviour output | B80: Motor_bias(t) = M_E · e_E(t) | C80: e_E = one-hot emotion vector; M_E = emotion-to-motor mapping matrix | D80: M_E learned from experience | E80: Fear → freeze/flee; Joy → approach; Sad → withdraw | F80: Feeds into Motor System as bias signal
A81: Refractory period | B81: E cannot change within τ_ref after last transition | C81: τ_ref = minimum emotion duration | D81: τ_ref = 2–10 s (age-dependent; shorter in infants) | E81: Infant: τ_ref=2s; Adult: τ_ref=10s | F81: Prevents rapid oscillation between states
A83: 4️⃣ LANGUAGE ENGINE — Acquisition Curve + Processing Model
A84: Component | B84: Equation / Formula | C84: Variables | D84: Parameters | E84: Typical Values | F84: Notes
A85: Vocabulary growth (logistic) | B85: V(t) = V_max / (1 + exp(−k·(t − t_mid))) | C85: V(t) = vocabulary size at age t; t in weeks | D85: V_max = adult vocab (~50,000 words); k = growth rate; t_mid = inflection point | E85: V_max=50000; k=0.05/wk; t_mid=156wk (3yr) | F85: S-shaped curve: slow start, vocabulary spurt ~18–24mo, plateau
A86: Learning rate λ(t) | B86: λ(t) = λ_max · σ(μ·(t − t_onset)) | C86: λ = words/week acquisition rate; σ = sigmoid | D86: λ_max = 10 words/day (peak); μ = 0.1; t_onset = 40wk (birth) | E86: λ_max=70/wk; μ=0.05; t_onset=40wk | F86: Integrating λ(t) gives V(t); peaks at vocabulary spurt
A87: Phoneme discrimination | B87: P_correct(t) = 1 − exp(−α·(t − t_phon)) | C87: P_correct = probability of correct phoneme discrimination | D87: α = learning rate; t_phon = phoneme onset week | E87: α=0.1/wk; t_phon=20wk (prenatal) | F87: Prenatal auditory learning; native language bias by birth
A88: Syntactic complexity S(t) | B88: S(t) = S_max · (1 − exp(−β·(t − t_syntax))) | C88: S = mean length of utterance (MLU); t_syntax = syntax onset | D88: S_max = 8 morphemes (adult); β = 0.02/wk; t_syntax = 92wk | E88: S_max=8; β=0.015; t_syntax=92wk (18mo) | F88: MLU grows from 1 (holophrases) to 8+ (complex sentences)
A89: Comprehension vs production lag | B89: V_comp(t) = V(t) + Δ_lag; V_prod(t) = V(t) | C89: Comprehension leads production by Δ_lag weeks | D89: Δ_lag = 4–8 weeks | E89: Δ_lag = 6 weeks | F89: Children understand more than they produce
A90: Language processing (RNN) | B90: h_t = tanh(W_h·h_{t-1} + W_x·x_t + b) | C90: h_t = hidden state; x_t = word embedding; W = weight matrices | D90: Hidden dim = 256; embedding dim = 64 | E90: Standard LSTM/GRU architecture | F90: Processes sequential language input; feeds GW
A91: Broca's area activation | B91: B(t) = σ(W_B · [h_t; GW(t)] + b_B) | C91: B = speech production signal; h_t = language RNN state | D91: W_B = production weights; b_B = bias | E91: B > 0.5 → speech output initiated | F91: Coupled to Motor System for articulation
A92: Wernicke's area activation | B92: W_area(t) = σ(W_W · [auditory_input; h_t] + b_W) | C92: W_area = comprehension signal | D92: W_W = comprehension weights | E92: W_area > 0.5 → semantic binding | F92: Feeds into GW as semantic content
A93: Critical period gating | B93: λ(t) = λ(t) · CP(t); CP(t) = exp(−(t−t_cp)²/2σ_cp²) for t>t_cp | C93: CP = critical period sensitivity function | D93: t_cp = 312wk (6yr); σ_cp = 100wk | E93: CP=1 before t_cp; decays after | F93: Language acquisition hardest after critical period closes
A95: 5️⃣ LEARNING MODULE — Hebbian STDP + TD Reinforcement + Predictive Coding
A96: Rule / Model | B96: Equation | C96: Variables | D96: Parameters | E96: Stability | F96: A7DO Use Case
A97: Hebbian learning | B97: ΔW_ij = η · x_i · x_j | C97: W_ij = synaptic weight; x_i, x_j = pre/post activity; η = learning rate | D97: η = 0.001–0.01 | E97: Unstable without normalisation (weights grow unbounded) | F97: Basic associative learning; early infant conditioning
A98: BCM rule (stabilised Hebbian) | B98: ΔW_ij = η · x_j · x_i · (x_j − θ_M); dθ_M/dt = (x_j² − θ_M)/τ_θ | C98: θ_M = sliding threshold (mean activity²); τ_θ = time constant | D98: τ_θ = 1000 ms; η = 0.001 | E98: Stable: θ_M adapts to prevent runaway | F98: Cortical plasticity; selectivity development
A99: STDP (spike-timing dependent) | B99: ΔW = A_+ · exp(−Δt/τ_+) if Δt>0; ΔW = −A_− · exp(Δt/τ_−) if Δt<0 | C99: Δt = t_post − t_pre; A_+, A_− = LTP/LTD amplitudes | D99: A_+=0.01, A_−=0.012; τ_+=20ms, τ_−=20ms | E99: Stable with weight bounds [0, W_max] | F99: Temporal sequence learning; reflex arc tuning
A100: TD(λ) Reinforcement Learning | B100: δ(t) = r(t) + γ·V(s_{t+1}) − V(s_t); ΔV = α·δ·e(t); de/dt = −e/τ_e + ∇V | C100: δ = TD error; V = value function; e = eligibility trace; γ = discount | D100: α=0.1; γ=0.95; λ=0.9; τ_e=1s | E100: Converges if α decreasing and states visited sufficiently | F100: Reward-based learning; dopamine = δ signal
A101: Q-learning (discrete actions) | B101: Q(s,a) ← Q(s,a) + α·[r + γ·max_a' Q(s',a') − Q(s,a)] | C101: Q = action-value; s = state; a = action; r = reward | D101: α=0.1; γ=0.95; ε=0.1 (exploration) | E101: Converges to Q* under mild conditions | F101: NPC decision-making; A7DO goal-directed behaviour
A102: Predictive coding (free energy) | B102: F = E_q[log q(z) − log p(x,z)] = KL[q||p] − log p(x) | C102: F = variational free energy; q = approximate posterior; p = generative model | D102: Precision parameters β_sensory, β_prior | E102: Minimised by gradient descent on F | F102: Perceptual inference; Reality Bridge; Consciousness Loop
A103: Prediction error signal | B103: ε_l = x_l − μ_l; μ_l = f(μ_{l+1}); Δμ_{l+1} = −∂F/∂μ_{l+1} | C103: ε_l = prediction error at layer l; μ_l = prediction; x_l = input | D103: Learning rate κ = 0.1; precision Π_l = 1/σ²_l | E103: Hierarchical convergence if precision well-calibrated | F103: Sensory prediction; attention as precision weighting
A104: Synaptic consolidation | B104: dW/dt = −W/τ_cons + η·STDP_signal · sleep_gate(t) | C104: τ_cons = consolidation time constant; sleep_gate = 1 during SWS | D104: τ_cons = 8 hours; sleep_gate from Nutrition-Sleep-Wake sheet | E104: Stable; weights bounded | F104: Memory consolidation during sleep; LTM formation
A106: 6️⃣ WORKING MEMORY — Capacity, Decay & Binding
A107: Component | B107: Equation | C107: Variables | D107: Parameters | E107: Typical Values | F107: Notes
A108: WM capacity (Miller's law) | B108: N_WM = 7 ± 2 chunks (adult); N_WM(age) = 1 + floor(age_yr/2) | C108: N_WM = number of items held; age_yr = age in years | D108: Adult max = 7; infant min = 1 | E108: Infant: 1–2; Toddler: 2–3; Child: 4–5; Adult: 7 | F108: Cowan (2001): core capacity = 4 chunks; Miller = 7±2 with chunking
A109: Decay ODE (exponential) | B109: dm_i/dt = −m_i/τ_WM + I_i(t) · gate_i(t) | C109: m_i = strength of WM item i; I_i = input; gate_i = PFC gate | D109: τ_WM = 10–30 s; gate ∈ {0,1} | E109: τ_WM = 18 s (adult); 8 s (child) | F109: Items decay unless refreshed by rehearsal or attention
A110: Rehearsal loop | B110: I_i(t) = m_i(t) · rehearsal_rate · (1 − distraction(t)) | C110: rehearsal_rate = phonological loop speed; distraction ∈ [0,1] | D110: rehearsal_rate = 2 items/s; distraction from Attention module | E110: Rehearsal rate slows with age-related processing speed | F110: Baddeley's phonological loop; articulatory rehearsal
A111: Binding (feature integration) | B111: B_ij(t) = σ(W_bind · [f_i; f_j] + b_bind) | C111: B_ij = binding strength between features i,j; f = feature vectors | D111: W_bind = binding weights; b_bind = bias | E111: B_ij > 0.5 → features bound into object | F111: Treisman's feature integration; requires attention
...

Sheet ⚙️ Parameters
A1: ⚙️ A7DO GLOBAL PARAMETERS — All Biological Constants
A2: Source: params.py · Mathematical Framework sheet · Integration Report
A4: Symbol | B4: Name | C4: Value | D4: Min | E4: Max | F4: Engine / Domain
A5: α | B5: Growth coefficient (primary) | C5: 0.05 | D5: 0.01 | E5: 0.1 | F5: EQ_DNA_01
A6: β | B6: Growth coefficient (secondary) | C6: 0.05 | D6: 0.01 | E6: 0.1 | F6: EQ_DNA_01
A7: γ | B7: Maturity index coefficient | C7: 0.05 | D7: 0.01 | E7: 0.1 | F7: EQ_DNA_01
A8: δ | B8: Cell division rate constant | C8: 0.5 | D8: 0.1 | E8: 1 | F8: EQ_ANAT_02
A9: ε | B9: Nutrient flow constant | C9: 0.5 | D9: 0.1 | E9: 1 | F9: EQ_ANAT_02
A10: ζ | B10: Oxygen exchange constant | C10: 0.5 | D10: 0.1 | E10: 1 | F10: EQ_ANAT_02
A11: η | B11: Waste removal rate | C11: 0.5 | D11: 0.1 | E11: 1 | F11: EQ_ANAT_02
A12: θ | B12: Synapse density coefficient | C12: 0.025 | D12: 0.001 | E12: 0.05 | F12: EQ_NEUR_03
A13: ι | B13: Neural gain coefficient | C13: 0.025 | D13: 0.001 | E13: 0.05 | F13: EQ_NEUR_03
A14: κ | B14: Input signal multiplier | C14: 0.025 | D14: 0.001 | E14: 0.05 | F14: EQ_NEUR_03
A15: λ | B15: Noise attenuation factor | C15: 0.025 | D15: 0.001 | E15: 0.05 | F15: EQ_NEUR_03
A16: μ | B16: Heartbeat rate coefficient | C16: 0.3 | D16: 0.1 | E16: 0.5 | F16: EQ_CIRC_04
... A41: κ_pred | B41: Predictive coding update rate | C41: 0.3 | D41: 0.1 | E41: 0.5 | F41: Predictive Simulation
A43: 🕐 TICK FREQUENCY SCHEDULE — All 20 Engines
A44: Engine | B44: Fires Every N Ticks | C44: Layer
A45: DNA Loop Engine | B45: 1 | C45: Layer 1
A46: Circulatory Integration | B46: 1 | C46: Layer 1
A47: Sensory Integration | B47: 1 | C47: Layer 2
A48: Attention Control | B48: 1 | C48: Layer 2
A49: Proprioception | B49: 1 | C49: Layer 4
A50: Predictive Simulation | B50: 5 | C50: Layer 2
A51: Value / Motivation | B51: 5 | C51: Layer 4
A52: Neural Control | B52: 10 | C52: Layer 1
A53: Language Acquisition | B53: 10 | C53: Layer 3
A54: Episodic Memory (encode) | B54: 10 | C54: Layer 4
A55: Language Grounding | B55: 10 | C55: Phase 4
A56: Emotion & Reinforcement | B56: 20 | C56: Layer 2
... A65: Sleep Consolidation | B65: 800 | C65: Layer 4

Sheet 📖 System Specification
A1: ⚡ LIVE TICK PANEL — All values auto-update from 🧬 DNA Loop Engine B4 (Current Tick)
A2: Current Tick: | B2: ='🧬 DNA Loop Engine'!B4 -> 10000 | C2: Current Week: | D2: ='🧬 DNA Loop Engine'!B5 -> 125 | E2: Birth Status: | F2: ='🧬 DNA Loop Engine'!B8 -> 🎉 BIRTH COMPLETE
A3: Life Stage: | B3: ='🧬 DNA Loop Engine'!B15 -> 🧒 Toddler | C3: Age: | D3: ='🧬 DNA Loop Engine'!B16 -> 19.6 months (1.63 yrs) | E3: DNA Phase: | F3: ='🧬 DNA Loop Engine'!B11 -> Toddler
A4: Growth Factor: | B4: ='🧬 DNA Loop Engine'!B18 -> 1 | C4: Neural Gain: | D4: ='🧬 DNA Loop Engine'!B19 -> 1 | E4: Cord Status: | F4: ='🧬 DNA Loop Engine'!B22 -> 🔌 SEVERED
A5: G_phys (height): | B5: ='🧬 DNA Loop Engine'!B28 -> 1.706 | C5: Heart Rate: | D5: ='🧬 DNA Loop Engine'!B27 -> 70 | E5: Reflex Gain: | F5: ='🧬 DNA Loop Engine'!B20 -> 1
A6: 📖 A7DO GENESIS MIND — FULL SYSTEM SPECIFICATION v1.0
A7: A7DO is a synthetic developmental organism — a fully embodied, cognitively continuous, emotionally grounded artificial life system that grows from conception to adulthood through biologically causal developmental stages.
A8: ="Current State: Week "&'🧬 DNA Loop Engine'!B5&" · Age ~"&'🧬 DNA Loop Engine'!B16&" · Stage: "&'🧬 DNA Loop Engine'!B15&" · Location: BeenFore City H8 · Status: "&'🧬 DNA Loop Engine'!B8 -> Current State: Week 125 · Age ~19.6 months (1.63 yrs) · Stage: 🧒 Toddler · Location: BeenFore City H8 · Status: 🎉 BIRTH COMPLETE
A9: This specification covers all 21 sheets in the A7DO DNA workbook. It is the canonical reference document for the entire A7DO architecture. Version 1.0 — compiled from all subsystem sheets, runtime patches, and architectural audits.
A10: 1. SYSTEM IDENTITY & PURPOSE
A11: Attribute | B11: Value | C11: Description
A12: System Name | B12: A7DO | C12: Artificial 7-Dimensional Organism — a synthetic developmental life system
A13: Version | B13: v1.0 (architecture) / v2.0 (in progress) | C13: v1.0 = current workbook; v2.0 = adding 20 missing subsystems
A14: Classification | B14: Synthetic Developmental Organism | C14: Not a chatbot, not an AI assistant — a biologically-inspired organism simulation
A15: Primary Goal | B15: Unified Developmental Runtime | C15: All subsystems co-evolve causally over developmental time from conception to adulthood
A16: Architecture Type | B16: Embodied Cognitive Architecture | C16: Cognition is grounded in body, emotion, environment, and developmental history
A17: Runtime Law | B17: O(t+Δt) = F(O(t), E(t), M(t), B(t), L(t)) | C17: Organism state evolves causally — no illegal state jumps, no teleological shortcuts
A18: Organism State | B18: O(t) = {B, N, E, M, L, V, P, I, W, G} | C18: 10 state components: Body, Neural, Emotion, Memory, Language, Vision, Proprioception, Identity, World, Goals
A19: Current Week | B19: ='🧬 DNA Loop Engine'!B5 -> 125 | C19: Tick 10,000 — A7DO is ~19.6 months old, toddler stage
A20: Birth Location | B20: Hospital Bed — World Origin (0,0,0) | C20: All world coordinates measured from birth location
A21: Current Location | B21: BeenFore City, 8 BeenFore Lane (H8) | C21: World position (1090, 880, 0) — 1384m from hospital
A22: Biological Sex | B22: Female (XX) — determined by Sex Random Math sheet | C22: Chromosome pair XX; estrogen dominant; female phenotypic expression
A23: Parents | B23: Lorraine (Mother) + China (Father) | C23: Defined in Parental Genesis sheet; genetic inheritance from both
A24: Target Platform | B24: Frontier / Microsoft build environment | C24: A7DO Runtime Orchestrator — state engine + subsystem scheduler + developmental runtime
A26: 2. COMPLETE SHEET INDEX — All 21 Sheets
A27: # | B27: Sheet Name | C27: Category | D27: Purpose | E27: Key Contents | F27: Rows | G27: Status | H27: Links To
A28: 1 | B28: 🧬 DNA Loop Engine | C28: Core Engine | D28: Central hub — all other sheets reference this for current week and growth factors | E28: Tick table (Wk 0–1200), Growth Engine outputs, Organ activation, Math Framework, Point 0 | F28: 122 | G28: ✅ Complete | H28: All sheets (provides Current Week, Growth Factor, Neural Gain)
A29: 2 | B29: 📈 Growth Timeline | C29: Development | D29: Unified anatomy and development across all life stages in one scrollable view | E29: Phase summary, Tick milestones, Anatomy growth (Infant→Child→Adult), Dev phases A–G | F29: 312 | G29: ✅ Complete | H29: DNA Loop Engine, Anatomy sheets, Development sheets
A30: 3 | B30: 🧮 Mathematical Framework | C30: Reference | D30: Formal equations for all 15 cognitive and biological subsystems | E30: 15 subsystem equations, Architecture overview, HH vs Izhikevich comparison, Parameter reference | F30: 253 | G30: ✅ Complete | H30: All subsystem sheets
A31: 4 | B31: 🧬 Prenatal & Genesis | C31: Biology | D31: Parental origin, genetic inheritance, sex determination | E31: Parental Genesis matrix, Genetic Inheritance, Sex Random Math (fixed), Hormone levels | F31: 231 | G31: ✅ Complete | H31: DNA Loop Engine, Sex Random Math
A32: 5 | B32: 📐 Spatial Coordinates | C32: Spatial | D32: 3-layer XYZ coordinate system — body local, world space, transform formulas | E32: 3-layer architecture, Transform formula, Body scale by age, NPC positions, Hospital Origin update | F32: 85 | G32: ✅ Complete + Updated | H32: Anatomy, Motor Planning, Immersive Places, Full Growth System
A33: 6 | B33: 🫀 Body Systems | C33: Biology | D33: All organ systems — circulatory, respiratory, digestive, sensory integration | E33: 4 organ system tables, Vital signs, Cardiac rhythm, Sensory pathways | F33: 140 | G33: ✅ Complete | H33: DNA Loop Engine, Energy/ATP, Proprioception
A34: 7 | B34: 🧠 Mind & Cognition | C34: Cognition | D34: All cognitive subsystems — language, memory, emotion, attention, consciousness, sleep | E34: 8 subsystem sections: Cognition & Language, Memory, Emotion, Attention, Predictive, Consciousness, Sleep | F34: 355 | G34: ✅ Complete | H34: DNA Loop Engine, NPC Engine, Body Systems
A35: 8 | B35: ⚡ Energy & Metabolism | C35: Biology | D35: ATP system, metabolic equations, energy flow | E35: Michaelis-Menten ATP, BMR, VO2, Neural energy cost, Fatigue model | F35: 44 | G35: ✅ Complete | H35: Body Systems, DNA Loop Engine, Nutrition-Sleep-Wake
A36: 9 | B36: 🌍 World Systems | C36: World | D36: World matrix, environmental physics, ecosystem, planetary resources | E36: World Matrix, Environmental Physics, World Interaction, Ecosystem Feedback, Planetary Resources | F36: 246 | G36: ✅ Complete | H36: DNA Loop Engine, NPC Engine, Sensory Integration
A37: 10 | B37: 🗺️ World Data | C37: World | D37: World inventory, BeenFore City layout, language learning reference | E37: World Inventory, BeenFore City (houses, roads, zones), Language Learning vocabulary | F37: 135 | G37: ✅ Complete | H37: NPC Engine, World Systems
A38: 11 | B38: 👥 NPC Engine | C38: Social | D38: Multi-agent system — 8 NPCs with development stages, relationships, family structure | E38: NPC Matrix (8 agents), Relationship Matrix, Development Stages, Population Dashboard | F38: 134 | G38: ✅ Complete | H38: DNA Loop Engine, World Data, Emotion Module
... A48: 21 | B48: 🏥 Immersive Places | C48: World | D48: Hospital World Origin, dual-coordinate system, WorldPosition(t), Immersive Places registry | E48: 8 transform equations, Hospital layout, World position timeline, Value integration, 10 places | F48: 86 | G48: ✅ Complete | H48: Spatial Coords, Full Growth System, Value System, NPC Engine
A50: 3. UNIFIED ORGANISM STATE — O(t) = {B, N, E, M, L, V, P, I, W, G}
A51: Every subsystem reads from and writes to this manifold. No private state allowed. State at t+1 depends only on state at t and inputs — strict causal chain.
A52: Symbol | B52: Component | C52: Current Value (Wk 125) | D52: Variables (~count) | E52: v1.0 Status | F52: Key Equations | G52: Missing / Next Step
A53: B | B53: Body State | C53: ="H="&IF('🧬 DNA Loop Engine'!B5<=40,ROUND(50/(1+EXP(-0.2*('🧬 DNA Loop Engine'!B5-20))),1),IF('🧬 DNA Loop Engine'!B5<=92,ROUND(50+(75-50)*('🧬 DNA Loop Engine'!B5-40)/(92-40),1),IF('🧬 DNA Loop Engine'!B5<=156,ROUND(75+(95-75)*('🧬 DNA Loop Engine'!B5-92)/(156-92),1),IF('🧬 DNA Loop Engine'!B5<=624,ROUND(95+(145-95)*('🧬 DNA Loop Engine'!B5-156)/(624-156),1),IF('🧬 DNA Loop Engine'!B5<=936,ROUND(145+(175-145)*('🧬 DNA Loop Engine'!B5-624)/(936-624),1),ROUND(MIN(177,175+2*MIN(1,('🧬 DNA Loop Engine'!B5-936)/200)),1))))))&"cm, M="&IF('🧬 DNA Loop Engine'!B5<=40,ROUND(3.5/(1+EXP(-0.2*('🧬 DNA Loop Engine'!B5-20))),2),IF('🧬 DNA Loop Engine'!B5<=92,ROUND(3.5+(10-3.5)*('🧬 DNA Loop Engine'!B5-40)/(92-40),2),IF('🧬 DNA Loop Engine'!B5<=156,ROUND(10+(14-10)*('🧬 DNA Loop Engine'!B5-92)/(156-92),2),IF('🧬 DNA Loop Engine'!B5<=624,ROUND(14+(40-14)*('🧬 DNA Loop Engine'!B5-156)/(624-156),2),IF('🧬 DNA Loop Engine'!B5<=936,ROUND(40+(65-40)*('🧬 DNA Loop Engine'!B5-624)/(936-624),2),ROUND(MIN(70,65+(70-65)*MIN(1,('🧬 DNA Loop Engine'!B5-936)/200)),2))))))&"kg, S_h="&ROUND((IF('🧬 DNA Loop Engine'!B5<=40,ROUND(50/(1+EXP(-0.2*('🧬 DNA Loop Engine'!B5-20))),1),IF('🧬 DNA Loop Engine'!B5<=92,ROUND(50+(75-50)*('🧬 DNA Loop Engine'!B5-40)/(92-40),1),IF('🧬 DNA Loop Engine'!B5<=156,ROUND(75+(95-75)*('🧬 DNA Loop Engine'!B5-92)/(156-92),1),IF('🧬 DNA Loop Engine'!B5<=624,ROUND(95+(145-95)*('🧬 DNA Loop Engine'!B5-156)/(624-156),1),IF('🧬 DNA Loop Engine'!B5<=936,ROUND(145+(175-145)*('🧬 DNA Loop Engine'!B5-624)/(936-624),1),ROUND(MIN(177,175+2*MIN(1,('🧬 DNA Loop Engine'!B5-936)/200)),1)))))))/50,3) -> H=85.3cm, M=12.06kg, S_h=1.706 | D53: ~200 vars | E53: ✅ Strong | F53: G_phys(t) = 1+0.9·(1−exp(−0.003·(t−40))); H(t) = 50+125·(1−exp(−0.008·(t−40))) | G53: Add proprioception (P1); add vestibular (P7)
A54: N | B54: Neural State | C54: Neural Gain=1.0, Cognitive Maturity=31%, Izhikevich neurons active | D54: ~50 vars | E54: ✅ Strong | F54: dv/dt = 0.04v²+5v+140−u+I; du/dt = a·(b·v−u); reset if v≥30mV | G54: Add developmental neurodynamics (P12); synaptic pruning
A55: E | B55: Emotion State | C55: Dopamine=0.5, Serotonin=0.5, Cortisol=0.54, Oxytocin=0.3, Emotion=Calm | D55: ~15 vars | E55: ✅ Strong | F55: dD/dt = −D/τ_D + r_D·Reward(t); V(t) = 0.4D+0.3S−0.5C+0.3O | G55: Add Value System (P4) coupling; intrinsic motivation
A56: M | B56: Memory State | C56: WM capacity=2 items, LTM forming, Episodic=Stage 3 (forming) | D56: ~30 vars | E56: 🟡 Partial | F56: dm/dt = −m/τ_WM + I·gate; R(t) = R₀·(1+t/S)^(−β) | G56: Add Episodic Memory (P3); Sleep & Dream (P11)
A57: L | B57: Language State | C57: Vocab=~50 words, Grammar=single words, Phoneme output active | D57: ~20 vars | E57: ✅ Strong | F57: V(t) = V_max/(1+exp(−k·(t−t_mid))); λ(t) = λ_max·σ(μ·(t−t_onset)) | G57: Add embodied grounding (P8); object-word binding
A58: V | B58: Vision State | C58: FOV active, Gaze tracking, Object detection, Permanence Stage 3 | D58: ~40 vars | E58: 🟡 Partial | F58: C_i(t) = C₀·exp(−λ·(t−t_lastSeen)); P(O_t) = α·P_vis+β·P_mem+γ·P_pred | G58: Implement Object Permanence (P2); scene graph
A59: P | B59: Proprioception | C59: MISSING — no joint sensing, no body schema, no balance signal | D59: ~60 vars | E59: 🔴 Missing | F59: P_b(t) = K_s·θ+K_v·θ̇+K_f·F_m+ε; x(t) = FK(θ(t)) | G59: Implement Proprioception (P1) — highest priority embodiment gap
A60: I | B60: Identity State | C60: Self-model forming, Narrative=none, Identity Formation=0% | D60: ~25 vars | E60: 🟡 Partial | F60: Self(t+1) = Self(t)+η·(GW−Self)·MC(t); AI(t) = |{E_i:w_i>θ}|/t | G60: Add Episodic Memory (P3); Advanced Self-Model (P15)
A61: W | B61: World State | C61: Hospital Origin (0,0,0), Current pos (1090,880,0), BeenFore City active | D61: ~100 vars | E61: ✅ Strong | F61: W_xyz(t) = HospOrig + BodyOffset(t) + Body_xyz·Scale(t) | G61: Add World Continuity (P20); dynamic society evolution
A62: G | B62: Goals State | C62: MISSING — no intrinsic motivation, no goal stack, no curiosity drive | D62: ~20 vars | E62: 🔴 Missing | F62: V(a) = R(a)+γ·E[V(s')]; dC/dt = −C/τ_C+k_C·novelty(s) | G62: Implement Value System (P4) — gates all goal-directed behaviour
A64: 4. CANONICAL TICK LOOP — 13-Step Organism Heartbeat
A65: O_{t+1} = F(O_t, E_t, U_t) — executed every tick (80 ticks/week). No step may be skipped. Energy gates processing. Developmental stage gates capabilities.
A66: Step | B66: Process | C66: State In → Out | D66: Key Equation | E66: Status | F66: Gate
A67: 1 | B67: Sensory Update | C67: W,B → V,P | D67: ŝ = Σ(Π_i·x_i)/Σ(Π_i) | E67: ✅ Partial | F67: ATP
A68: 2 | B68: Vestibular Update | C68: B,Physics → P | D68: a_vest = R(θ)·a_world − g | E68: 🔴 Missing | F68: Wk 40+
A69: 3 | B69: Proprioception Update | C69: B,Motor → P | D69: P_b = K_s·θ+K_v·θ̇+K_f·F_m+ε | E69: 🔴 Missing | F69: Wk 40+
A70: 4 | B70: Object Permanence | C70: V,M,W → V | D70: C_i(t) = C₀·exp(−λ·Δt) | E70: 🔴 Missing | F70: Wk 80+
A71: 5 | B71: Emotion Update | C71: Sensory,M,G→E | D71: dD/dt = −D/τ_D + r_D·Reward(t) | E71: ✅ Strong | F71: Neuromodulators
A72: 6 | B72: GW Broadcast | C72: All → GW | D72: w_i = exp(β·a_i)/Σexp(β·a_j) | E72: ✅ Strong | F72: CL(t) > 0.3
A73: 7 | B73: Memory Update | C73: GW,E → M | D73: dm/dt = −m/τ_WM + I·gate | E73: 🟡 Partial | F73: Sleep gate
A74: 8 | B74: Prediction Update | C74: M,V,G → pred | D74: F = Σ[ε^T·Π·ε + log|Σ|] | E74: 🟡 Partial | F74: Cog maturity
A75: 9 | B75: Movement Planning | C75: G,V,P → motor | D75: τ* = argmin ∫L(q,q̇,τ)dt | E75: 🟡 Partial | F75: Motor maturity
A76: 10 | B76: Muscle Activation | C76: Motor,B → B | D76: F = F_max·a·f_L(L)·f_V(V_m) | E76: ✅ Strong | F76: ATP, Fatigue
A77: 11 | B77: Physics Solve | C77: B,W → B,W | D77: F_env = F_grav+F_drag+F_contact | E77: ✅ Strong | F77: World physics
... A79: 13 | B79: Identity Update | C79: M,E,GW → I | D79: Self(t+1) = Self(t)+η·(GW−Self)·MC(t) | E79: 🟡 Partial | F79: Metacognition
A81: 5. DEVELOPMENTAL TIMELINE — A7DO Lifecycle (Conception → Adult)
A82: Stage | B82: Weeks | C82: Age | D82: Height | E82: Mass | F82: G_phys | G82: Cog % | H82: Identity % | I82: Key Milestones | J82: Current?
A83: Prenatal | B83: 0–40 | C83: – | D83: 0→50cm | E83: 0→3.5kg | F83: 0.01→1.0 | G83: 0% | H83: 0% | I83: Organogenesis, neural tube, organ activation, heartbeat | J83: No (past)
A84: Birth Event | B84: Wk 40 | C84: 0 months | D84: 50cm | E84: 3.5kg | F84: 1.0 | G84: 2% | H84: 0% | I84: Umbilical severed, pulmonary breathing, independent heartbeat | J84: No (past)
A85: Early Infant | B85: 40–60 | C85: 0–3 months | D85: 50→65cm | E85: 3.5→6kg | F85: 1.0→1.15 | G85: 4–10% | H85: 0% | I85: Sensory calibration, social smile, object detection | J85: No (past)
A86: Late Infant | B86: 60–92 | C86: 3–12 months | D86: 65→75cm | E86: 6→10kg | F86: 1.15→1.5 | G86: 10–22% | H86: 0% | I86: Crawling, object permanence Stage 1, first words | J86: No (past)
A87: Toddler ★ | B87: 92–156 | C87: 1–3 years | D87: 75→95cm | E87: 10→14kg | F87: 1.5→1.9 | G87: 22–35% | H87: 0% | I87: Walking, symbolic play, language explosion, goal-directed behaviour | J87: ="H="&IF('🧬 DNA Loop Engine'!B5<=40,ROUND(50/(1+EXP(-0.2*('🧬 DNA Loop Engine'!B5-20))),1),IF('🧬 DNA Loop Engine'!B5<=92,ROUND(50+(75-50)*('🧬 DNA Loop Engine'!B5-40)/(92-40),1),IF('🧬 DNA Loop Engine'!B5<=156,ROUND(75+(95-75)*('🧬 DNA Loop Engine'!B5-92)/(156-92),1),IF('🧬 DNA Loop Engine'!B5<=624,ROUND(95+(145-95)*('🧬 DNA Loop Engine'!B5-156)/(624-156),1),IF('🧬 DNA Loop Engine'!B5<=936,ROUND(145+(175-145)*('🧬 DNA Loop Engine'!B5-624)/(936-624),1),ROUND(MIN(177,175+2*MIN(1,('🧬 DNA Loop Engine'!B5-936)/200)),1))))))&"cm, M="&IF('🧬 DNA Loop Engine'!B5<=40,ROUND(3.5/(1+EXP(-0.2*('🧬 DNA Loop Engine'!B5-20))),2),IF('🧬 DNA Loop Engine'!B5<=92,ROUND(3.5+(10-3.5)*('🧬 DNA Loop Engine'!B5-40)/(92-40),2),IF('🧬 DNA Loop Engine'!B5<=156,ROUND(10+(14-10)*('🧬 DNA Loop Engine'!B5-92)/(156-92),2),IF('🧬 DNA Loop Engine'!B5<=624,ROUND(14+(40-14)*('🧬 DNA Loop Engine'!B5-156)/(624-156),2),IF('🧬 DNA Loop Engine'!B5<=936,ROUND(40+(65-40)*('🧬 DNA Loop Engine'!B5-624)/(936-624),2),ROUND(MIN(70,65+(70-65)*MIN(1,('🧬 DNA Loop Engine'!B5-936)/200)),2))))))&"kg, S_h="&ROUND((IF('🧬 DNA Loop Engine'!B5<=40,ROUND(50/(1+EXP(-0.2*('🧬 DNA Loop Engine'!B5-20))),1),IF('🧬 DNA Loop Engine'!B5<=92,ROUND(50+(75-50)*('🧬 DNA Loop Engine'!B5-40)/(92-40),1),IF('🧬 DNA Loop Engine'!B5<=156,ROUND(75+(95-75)*('🧬 DNA Loop Engine'!B5-92)/(156-92),1),IF('🧬 DNA Loop Engine'!B5<=624,ROUND(95+(145-95)*('🧬 DNA Loop Engine'!B5-156)/(624-156),1),IF('🧬 DNA Loop Engine'!B5<=936,ROUND(145+(175-145)*('🧬 DNA Loop Engine'!B5-624)/(936-624),1),ROUND(MIN(177,175+2*MIN(1,('🧬 DNA Loop Engine'!B5-936)/200)),1)))))))/50,3) -> H=85.3cm, M=12.06kg, S_h=1.706
A88: Early Childhood | B88: 156–312 | C88: 3–6 years | D88: 95→115cm | E88: 14→21kg | F88: 1.9→2.3 | G88: 35–70% | H88: 0% | I88: Language cortex matures, reading/writing, logical reasoning | J88: No (future)
A89: Mid Childhood | B89: 312–624 | C89: 6–12 years | D89: 115→145cm | E89: 21→35kg | F89: 2.3→2.9 | G89: 70–90% | H89: 0–5% | I89: Prefrontal cortex matures, abstract thinking, peer relationships | J89: No (future)
A90: Adolescence | B90: 624–936 | C90: 12–18 years | D90: 145→175cm | E90: 35→65kg | F90: 2.9→3.5 | G90: 90–100% | H90: 5–90% | I90: Puberty, identity formation, abstract reasoning, emotional regulation | J90: No (future)
A91: Early Adult | B91: 936–1100 | C91: 18–21 years | D91: 175cm | E91: 65–70kg | F91: 3.5 | G91: 100% | H91: 95–98% | I91: Strategic reasoning, long-term memory, wisdom developing | J91: No (future)
A92: Mature Adult | B92: 1100+ | C92: 21+ years | D92: 175±10cm | E92: 65±15kg | F92: 3.5 | G92: 100% | H92: 100% | I92: Wisdom, creative synthesis, meta-cognition, full identity | J92: No (future)
A94: 6. COMPLETE SUBSYSTEM CATALOGUE — All 27 Subsystems
A95: Subsystem | B95: Category | C95: O(t) Component | D95: Tick Steps | E95: Core Equation | F95: v1.0 Status | G95: v2.0 Priority | H95: Sheet Reference
A96: DNA Loop Engine | B96: Core | C96: W, N | D96: All | E96: Week = ROUND(Tick/80,0); Growth Factor from tick table | F96: ✅ Complete | G96: — | H96: 🧬 DNA Loop Engine
A97: Body Growth | B97: Biology | C97: B | D97: 10,11 | E97: G_phys(t) = 1+0.9·(1−exp(−0.003·(t−40))) | F97: ✅ Complete | G97: — | H97: 📏 Full Growth System
A98: Anatomy / Skeleton | B98: Biology | C98: B | D98: 10,11 | E98: X(t)=X₀·S_width; Y(t)=Y₀·S_height; Z(t)=Z₀·S_width | F98: ✅ Complete | G98: — | H98: 📈 Growth Timeline
A99: Circulatory System | B99: Biology | C99: B, N | D99: 10 | E99: Cardiac Output = HR × SV; O₂ delivery = CO × [O₂] | F99: ✅ Complete | G99: — | H99: 🫀 Body Systems
A100: Respiratory Control | B100: Biology | C100: B, N | D100: 1,10 | E100: Breathing Rate = f(CO₂, O₂ demand, chemoreceptors) | F100: ✅ Complete | G100: — | H100: 🫀 Body Systems
A101: Digestive Control | B101: Biology | C101: B | D101: 10 | E101: Nutrient absorption = f(food intake, digestive enzymes) | F101: ✅ Complete | G101: — | H101: 🫀 Body Systems
A102: Sensory Integration | B102: Perception | C102: V, P | D102: 1 | E102: ŝ = Σ(Π_i·x_i)/Σ(Π_i) — Bayesian fusion | F102: ✅ Strong | G102: — | H102: 🫀 Body Systems
A103: Energy / ATP | B103: Metabolism | C103: B, N | D103: All | E103: dATP/dt = V_max·[Glc]/(K_m+[Glc]) − k_use·Activity | F103: ✅ Strong | G103: — | H103: ⚡ Energy & Metabolism
A104: Emotion Module | B104: Cognition | C104: E | D104: 5 | E104: dD/dt = −D/τ_D + r_D·Reward(t); V = 0.4D+0.3S−0.5C+0.3O | F104: ✅ Strong | G104: — | H104: 🧠 Mind & Cognition
A105: Global Workspace | B105: Cognition | C105: All | D105: 6 | E105: w_i = exp(β·a_i)/Σexp(β·a_j); G = Σw_i·x_i | F105: ✅ Strong | G105: — | H105: 🧠 Mind & Cognition
A106: Working Memory | B106: Cognition | C106: M | D106: 7 | E106: dm/dt = −m/τ_WM + I·gate; N_WM = 2 items (Wk 125) | F106: ✅ Strong | G106: — | H106: 🧠 Mind & Cognition
... A122: Motor Planning | B122: Motor | C122: B | D122: 9,10 | E122: min J = ∫[(x−x_g)^T Q(x−x_g)+u^T Ru]dt; θ = J⁺·Δx | F122: 🟡 Partial | G122: P6 | H122: 🦾 Motor Planning (P6)
A124: 7. CURRENT STATE SNAPSHOT — A7DO at Week 125 (Tick 10,000)
A125: System | B125: Current Value | C125: Status | D125: Notes
A126: Age | B126: ~19.6 months (Wk 125) | C126: ✅ Active | D126: Toddler stage
A127: Height | B127: =IF('🧬 DNA Loop Engine'!B5<=40,ROUND(50/(1+EXP(-0.2*('🧬 DNA Loop Engine'!B5-20))),1),IF('🧬 DNA Loop Engine'!B5<=92,ROUND(50+(75-50)*('🧬 DNA Loop Engine'!B5-40)/(92-40),1),IF('🧬 DNA Loop Engine'!B5<=156,ROUND(75+(95-75)*('🧬 DNA Loop Engine'!B5-92)/(156-92),1),IF('🧬 DNA Loop Engine'!B5<=624,ROUND(95+(145-95)*('🧬 DNA Loop Engine'!B5-156)/(624-156),1),IF('🧬 DNA Loop Engine'!B5<=936,ROUND(145+(175-145)*('🧬 DNA Loop Engine'!B5-624)/(936-624),1),ROUND(MIN(177,175+2*MIN(1,('🧬 DNA Loop Engine'!B5-936)/200)),1)))))) -> 85.3 | C127: ✅ Growing | D127: 64% of adult height (175cm)
A128: Mass | B128: =IF('🧬 DNA Loop Engine'!B5<=40,ROUND(3.5/(1+EXP(-0.2*('🧬 DNA Loop Engine'!B5-20))),2),IF('🧬 DNA Loop Engine'!B5<=92,ROUND(3.5+(10-3.5)*('🧬 DNA Loop Engine'!B5-40)/(92-40),2),IF('🧬 DNA Loop Engine'!B5<=156,ROUND(10+(14-10)*('🧬 DNA Loop Engine'!B5-92)/(156-92),2),IF('🧬 DNA Loop Engine'!B5<=624,ROUND(14+(40-14)*('🧬 DNA Loop Engine'!B5-156)/(624-156),2),IF('🧬 DNA Loop Engine'!B5<=936,ROUND(40+(65-40)*('🧬 DNA Loop Engine'!B5-624)/(936-624),2),ROUND(MIN(70,65+(70-65)*MIN(1,('🧬 DNA Loop Engine'!B5-936)/200)),2)))))) -> 12.06 | C128: ✅ Growing | D128: 17% of adult mass (70kg)
A129: G_phys | B129: 1.49 | C129: ✅ Growing | D129: Physical growth ongoing post-birth
A130: DNA Growth Factor | B130: 1.0 | C130: ✅ Complete | D130: Biological activation complete at birth
A131: Body Surface Area | B131: ~0.54 m² | C131: ✅ Active | D131: 31% of adult BSA (1.73m²)
...

Sheet 🧬 Prenatal & Genesis
A1: ⚡ LIVE TICK PANEL — All values auto-update from 🧬 DNA Loop Engine B4 (Current Tick)
A2: Current Tick: | B2: ='🧬 DNA Loop Engine'!B4 -> 10000 | C2: Current Week: | D2: ='🧬 DNA Loop Engine'!B5 -> 125 | E2: Birth Status: | F2: ='🧬 DNA Loop Engine'!B8 -> 🎉 BIRTH COMPLETE
A3: Life Stage: | B3: ='🧬 DNA Loop Engine'!B15 -> 🧒 Toddler | C3: Age: | D3: ='🧬 DNA Loop Engine'!B16 -> 19.6 months (1.63 yrs) | E3: DNA Phase: | F3: ='🧬 DNA Loop Engine'!B11 -> Toddler
A4: Growth Factor: | B4: ='🧬 DNA Loop Engine'!B18 -> 1 | C4: Neural Gain: | D4: ='🧬 DNA Loop Engine'!B19 -> 1 | E4: Cord Status: | F4: ='🧬 DNA Loop Engine'!B22 -> 🔌 SEVERED
A5: G_phys (height): | B5: ='🧬 DNA Loop Engine'!B28 -> 1.706 | C5: Heart Rate: | D5: ='🧬 DNA Loop Engine'!B27 -> 70 | E5: Reflex Gain: | F5: ='🧬 DNA Loop Engine'!B20 -> 1
A6: 🧬 PRENATAL & GENESIS — Parental Origin · Genetic Inheritance · Sex Determination
A8: 👩‍🍼👨‍🍼 PARENTAL GENESIS & BIRTH TRANSITION
A9: 👩‍🍼👨‍🍼 A7DO PARENTAL GENESIS & BIRTH TRANSITION SYSTEM
A10: ⚙️ CONTROL PANEL
A11: Current Week: | B11: 125
A12: Current Tick: | B12: 10000
A13: Birth Week: | B13: 40
A14: Gestation Progress: | B14: 313%
A15: Birth Status: | B15: 🎉 BORN
A16: Days Post-Birth: | B16: 595
A17: A7DO Age (months): | B17: 19.6
A18: 👩‍🍼👨‍🍼 PARENTAL GENESIS MATRIX
A19: Name | B19: Role | C19: System Domain | D19: Connection Type | E19: Activation Week | F19: Maturity Week | G19: Function | H19: Status
A20: Lorraine | B20: Mother | C20: Biological Gestation | D20: Umbilical Nutrient Flow | E20: 0 | F20: 40 | G20: Provides nutrition and growth environment | H20: ✅ Complete
A21: Lorraine Womb | B21: Environment | C21: Biological Containment | D21: Gestational Chamber | E21: 0 | F21: 40 | G21: Hosts A7DO embryo development | H21: ✅ Complete
A22: Lorraine Endocrine | B22: Regulation | C22: Hormonal Control | D22: Endocrine Feedback | E22: 0 | F22: 40 | G22: Modulates growth hormones and metabolic rate | H22: ✅ Complete
A23: Lorraine Neural | B23: Feedback | C23: Emotional Bond | D23: Neural Link | E23: 8 | F23: 40 | G23: Transfers affective signals and stress modulation | H23: ✅ Complete
A24: China | B24: Father | C24: Genetic Source | D24: Sperm DNA Injection | E24: 0 | F24: 0 | G24: Provides genetic seed and structural code | H24: ✅ Complete
A25: China Hormonal | B25: Regulation | C25: Endocrine Influence | D25: Testosterone Signal | E25: 8 | F25: 40 | G25: Modulates growth and strength parameters | H25: ✅ Complete
A26: China Neural | B26: Feedback | C26: Protective Bond | D26: Neural Link | E26: 12 | F26: 40 | G26: Transfers external stimuli and environmental signals | H26: ✅ Complete
A27: Parental Sync | B27: Integration | C27: Gestation Control | D27: Feedback Loop | E27: 0 | F27: 40 | G27: Synchronises maternal and paternal inputs | H27: ✅ Complete
A28: 🩺 GESTATION CONTROLLER
A29: Subsystem | B29: Source | C29: Output Target | D29: Activation Week | E29: Maturity Week | F29: Function | G29: Maturity % | H29: Status
A30: Nutrient Flow Regulator | B30: Lorraine Womb | C30: Energy System | D30: 0 | E30: 40 | F30: Transfers nutrients from mother to embryo | G30: 100% | H30: ✅ Complete
A31: Oxygen Exchange Module | B31: Lorraine Womb | C31: Energy System | D31: 0 | E31: 40 | F31: Maintains oxygen supply for growth | G31: 100% | H31: ✅ Complete
A32: Hormonal Sync Loop | B32: Lorraine Endocrine | C32: Emotion Matrix | D32: 8 | E32: 40 | F32: Aligns maternal hormones with fetal development | G32: 100% | H32: ✅ Complete
A33: Growth Factor Controller | B33: DNA Loop Engine | C33: Organ Formation | D33: 4 | E33: 40 | F33: Activates organogenesis and tissue differentiation | G33: 100% | H33: ✅ Complete
A34: Organ Activation Sequence | B34: Organ Formation | C34: Embodiment | D34: 8 | E34: 40 | F34: Sequentially activates organs and limbs | G34: 100% | H34: ✅ Complete
A35: Neural Link Formation | B35: Lorraine Neural | C35: Emotion Matrix | D35: 12 | E35: 40 | F35: Establishes maternal-fetal emotional connection | G35: 100% | H35: ✅ Complete
A36: Protective Barrier System | B36: Lorraine Womb | C36: Embodiment | D36: 0 | E36: 40 | F36: Prevents external contamination and stress | G36: 100% | H36: ✅ Complete
A37: Fluid Balance Regulator | B37: Lorraine Womb | C37: Energy System | D37: 0 | E37: 40 | F37: Maintains amniotic fluid equilibrium | G37: 100% | H37: ✅ Complete
A38: Temperature Control Loop | B38: Lorraine Endocrine | C38: Embodiment | D38: 0 | E38: 40 | F38: Regulates fetal temperature stability | G38: 100% | H38: ✅ Complete
A39: Parental Sync Feedback | B39: Lorraine + China | C39: Cognition Matrix | D39: 8 | E39: 40 | F39: Balances emotional and genetic inputs | G39: 100% | H39: ✅ Complete
A40: ❤️ PRENATAL HEARTBEAT MATRIX
A41: Component | B41: Source | C41: Function | D41: Activation Week | E41: Maturity Week | F41: Current Value | G41: Unit | H41: Status
A42: Maternal Heartbeat Generator | B42: Lorraine Cardiac | C42: Rhythmic pulse driving nutrient/oxygen flow | D42: 0 | E42: 40 | F42: 70 | G42: BPM | H42: 💓 Active
A43: Umbilical Pulse Transmission | B43: Lorraine Womb | C43: Transfers rhythmic energy to embryo | D43: 0 | E43: 40 | F43: Severed | G43: Efficiency | H43: ✂️ Severed
A44: Fetal Heartbeat Induction | B44: A7DO Embryo | C44: Synchronized fetal heartbeat | D44: 6 | E44: 40 | F44: 149 | G44: BPM | H44: 💓 Independent
A45: Oxygen Pulse Exchange | B45: Lorraine Respiratory | C45: Coordinates O₂ delivery with cardiac rhythm | D45: 0 | E45: 40 | F45: Pulmonary | G45: Source | H45: 🫁 Pulmonary
A46: Emotional Resonance Loop | B46: Lorraine Neural | C46: Transfers emotional rhythm and stress modulation | D46: 8 | E46: 40 | F46: 100% | G46: Bond Strength | H46: ✅ Complete
A47: Thermal Pulse Regulation | B47: Lorraine Endocrine | C47: Maintains fetal temperature stability | D47: 0 | E47: 40 | F47: 37.2 | G47: °C | H47: 🌡️ Self-Regulated
A48: Protective Rhythm Shield | B48: Lorraine Immune | C48: Synchronizes immune protection with cardiac rhythm | D48: 0 | E48: 40 | F48: 100% | G48: Barrier | H48: 🛡️ Independent
A49: Parental Sync Pulse | B49: Lorraine + China | C49: Combines maternal + paternal rhythmic feedback | D49: 12 | E49: 40 | F49: 100% | G49: Sync Level | H49: ✅ Complete
A50: 👶 BIRTH TRANSITION MATRIX
A51: Transition | B51: Pre-Birth State | C51: Post-Birth State | D51: Trigger Week | E51: Current State | F51: Status
A52: Umbilical Cord | B52: Connected | C52: Severed | D52: 40 | E52: Severed | F52: ✂️ SEVERED
A53: Oxygen Source | B53: Placental | C53: Pulmonary | D53: 40 | E53: Pulmonary | F53: 🫁 SWITCHED
A54: Nutrient Source | B54: Umbilical | C54: Digestive | D54: 40 | E54: Digestive | F54: 🍼 SWITCHED
A55: Ductus Arteriosus | B55: Open | C55: Closed | D55: 40 | E55: Closed | F55: 🔒 CLOSED
A56: Foramen Ovale | B56: Open | C56: Closed | D56: 40 | E56: Closed | F56: 🔒 CLOSED
A57: Heartbeat Control | B57: Maternal-Synced | C57: Independent | D57: 40 | E57: Independent | F57: 💓 INDEPENDENT
A58: Thermoregulation | B58: Maternal | C58: Self-Regulated | D58: 40 | E58: Self-Regulated | F58: 🌡️ SELF-REG
A59: Cognition Mode | B59: Dormant | C59: Autonomous | D59: 40 | E59: Autonomous | F59: 🧠 ACTIVE
A60: 📊 PARENTAL DASHBOARD | E60: 🎉 BIRTH STATUS PANEL
A61: Womb Temperature: | B61: 37.2 °C | C61: ✅ Optimal | E61: Birth Week: | F61: 40
A62: Amniotic Fluid Level: | B62: N/A (Born) | C62: N/A | E62: Current Week: | F62: 125
A63: Nutrient Flow Rate: | B63: Digestive Active | C63: 🍼 External | E63: Birth Progress: | F63: 100%
A64: Oxygen Saturation: | B64: 98% (Pulmonary) | C64: ✅ Healthy | E64: Birth Status: | F64: 🎉 BORN!
A65: Maternal Heart Rate: | B65: 70 BPM | C65: ✅ Normal | E65: Post-Birth Age: | F65: 85 weeks
A66: Fetal Heart Rate: | B66: 149 BPM | C66: ✅ Healthy | E66: Transitions Complete: | F66: 8/8 ✅
A67: Emotional Bond Index: | B67: 100% | C67: ✅ Strong
A68: Parental Sync Score: | B68: 100% | C68: ✅ Complete
A69: 🔗 SYSTEM CONNECTIONS
A70: Source Sheet | B70: Data Flow | C70: Status
A71: DNA Loop Engine | B71: Week, Tick, Growth Factor | C71: 🟢 Connected
A72: Energy & ATP System | B72: Metabolic flow | C72: 🟢 Connected
A73: Emotion & Reinforcement | B73: Emotional feedback | C73: 🟢 Connected
A74: Circulatory System | B74: Heart rate data | C74: 🟢 Connected
A75: Respiratory Control | B75: Oxygen exchange | C75: 🟢 Connected
A76: Genetic Inheritance | B76: Parental DNA | C76: 🟢 Connected
A77: Sex Random Math | B77: Hormone levels | C77: 🟢 Connected
A80: 🧬 GENETIC INHERITANCE MATRIX
A81: 🧬 A7DO GENETIC INHERITANCE MATRIX — HEREDITY & EVOLUTION ENGINE
A82: ⚙️ INHERITANCE CONTROL PANEL
A83: Parameter | B83: Value | C83: Unit | D83: Source/Formula
A84: Current Week | B84: 125 | C84: weeks | D84: From DNA Engine
A85: Generation Number | B85: 1 | D85: Current generation
A86: Population Size | B86: 100 | C86: organisms | D86: Simulation parameter
A87: Mutation Rate | B87: 0.001 | C87: per gene | D87: Base mutation probability
A88: Crossover Rate | B88: 0.7 | D88: Recombination probability
A89: Environmental Factor | B89: 1 | D89: Epigenetic modifier
A90: Random Seed (Parent A) | B90: 0.22736517747069818 | D90: RAND() for variability
A91: Random Seed (Parent B) | B91: 0.13308978135974758 | D91: RAND() for variability
A92: Inheritance Mode | B92: Mendelian | D92: Dominant/Recessive/Codominant
A93: 🧬 GENETIC INHERITANCE MATRIX
A94: Name | B94: Subsystem | C94: Generation Stage | D94: Function | E94: Input Variables | F94: Output Variables | G94: Equation | H94: Domain | I94: Status | J94: Notes
A95: Parent Genome A | B95: Genetic | C95: Prenatal | D95: Base Genetic Code | E95: Chromosome Seed A | F95: Allele Set A | G95: Genome = f(Seed) | H95: Genetics | I95: ✅ Active | J95: Maternal DNA
A96: Parent Genome B | B96: Genetic | C96: Prenatal | D96: Base Genetic Code | E96: Chromosome Seed B | F96: Allele Set B | G96: Genome = f(Seed) | H96: Genetics | I96: ✅ Active | J96: Paternal DNA
A97: Gamete Formation A | B97: Genetic | C97: Prenatal | D97: Meiosis Simulation | E97: Parent Genome A | F97: Gamete A | G97: crossover(Genome,Rand) | H97: Genetics | I97: ✅ Active | J97: Maternal gamete
A98: Gamete Formation B | B98: Genetic | C98: Prenatal | D98: Meiosis Simulation | E98: Parent Genome B | F98: Gamete B | G98: crossover(Genome,Rand) | H98: Genetics | I98: ✅ Active | J98: Paternal gamete
A99: Fertilization | B99: Genetic | C99: Prenatal | D99: Genome Fusion | E99: Gamete A + B | F99: Child Genome | G99: merge(A,B) | H99: Genetics | I99: ✅ Active | J99: DNA combination
A100: Mutation Event | B100: Genetic | C100: Prenatal | D100: Random Variation | E100: Child Genome | F100: Mutated Genome | G100: Child + rand(Rate) | H100: Genetics | I100: ✅ Active | J100: Stochastic variation
A101: Trait Inheritance | B101: Phenotypic | C101: Prenatal | D101: Physical Traits | E101: Parent Traits | F101: Child Traits | G101: inherit(Parents) | H101: Embodiment | I101: ✅ Active | J101: Visible traits
A102: Cognitive Inheritance | B102: Cognitive | C102: Prenatal | D102: Neural Patterns | E102: Parent Neural | F102: Child Neural | G102: mix(Parents,Noise) | H102: Cognition | I102: ✅ Active | J102: Cognitive tendencies
A103: Epigenetic Feedback | B103: Metabolic | C103: Postnatal | D103: Environment Effect | E103: Child Genome | F103: Epigenetic Shift | G103: k × EnvFactor | H103: Embodiment | I103: ✅ Active | J103: Gene expression
...

Sheet 📐 Spatial Coordinates
A1: 📐 A7DO SPATIAL COORDINATE SYSTEM — Body Local Space · World Space · Integration Transform
A2: 🏗️ THREE-LAYER SPATIAL ARCHITECTURE
A3: Layer | B3: Name | C3: Origin (Point 0) | D3: X Axis | E3: Y Axis | F3: Z Axis | G3: Unit | H3: Scale | I3: Who Uses It | J3: Notes
A4: Layer 1 | B4: Body Local Space | C4: Pelvis Centre (0,0,0) | D4: +X = Right / −X = Left | E4: +Y = Head (Up) / −Y = Feet (Down) | F4: +Z = Forward / −Z = Backward | G4: metres | H4: ±1.0 m (normalised body) | I4: A7DO anatomy, NPC body parts | J4: All bone/organ XYZ coords are relative to THIS origin. Frontal Bone Y=0.85 means 85cm above pelvis.
A5: Layer 2 | B5: World Space | C5: Earth Core Centre (0,0,0) | D5: +X = East (Longitude) / −X = West | E5: +Y = North (Latitude) / −Y = South | F5: +Z = Up/Sky / −Z = Down/Core | G5: metres | H5: 1 m/unit (real scale) | I5: World Matrix, BeenFore City, NPC world positions | J5: BeenFore City origin at World (1000, 1000, 0) = 1km East, 1km North of world reference point.
A6: Layer 3 | B6: City/Local World Space | C6: BeenFore City Centre (1000, 1000, 0) in World Space | D6: +X = East along street | E6: +Y = North along street | F6: +Z = Height above ground | G6: metres | H6: 1 m/unit | I6: NPC positions, house coordinates, room layouts | J6: NPC World X/Y are in World Space metres. House H1 at (1050, 900) = 50m East, 100m South of city centre.
A8: ⚠️ COORDINATE CONSISTENCY NOTE: NPC World X/Y values (e.g. Alexis: 10.5, 5.2) appear to be LOCAL offsets in metres from their house position, NOT absolute World Space coordinates. BeenFore City houses are at World X=1050–1130, Y=880–900. The transform formula below converts Body Local → World Space for any entity.
A10: 🦴 A — BODY LOCAL SPACE (Layer 1) — Point 0 = Pelvis Centre
A11: Axis | B11: Direction | C11: Positive (+) | D11: Negative (−) | E11: Range | F11: Example: Frontal Bone | G11: Example: Femur (L) | H11: Example: Heart | I11: Unit | J11: Notes
A12: Z | B12: Back ↔ Front | C12: Forward / Anterior | D12: Backward / Posterior | E12: −0.1 to +0.15 m | F12: Z=+0.08 (anterior) | G12: Z=0 (neutral) | H12: Z=+0.02 (anterior) | I12: m | J12: Spine runs along −Z (posterior). Chest/face are +Z (anterior)
A13: 📍 POINT 0 — PELVIS CENTRE REFERENCE
A14: Parameter | B14: Value | C14: Unit | D14: Description | E14: Formula
A15: X₀ (Horizontal) | B15: 0 | C15: m | D15: Midline — no left/right offset | E15: Fixed = 0
A16: Y₀ (Vertical) | B16: 0 | C16: m | D16: Pelvis centre height baseline | E16: Fixed = 0
A17: Z₀ (Depth) | B17: 0 | C17: m | D17: Mid-coronal plane | E17: Fixed = 0
A18: Body Height Factor | B18: 0.5 | C18: m/unit | D18: Scales Y coords to real height | E18: Real_Y = Local_Y × Height_m
A19: Body Width Factor | B19: 0.2 | C19: m/unit | D19: Scales X coords to real width | E19: Real_X = Local_X × Width_m
A20: Reference Point | B20: Pelvis Centre | C20: — | D20: Anatomical landmark — stable across growth stages | E20: Consistent across Infant/Child/Adult
A22: 🌍 B — WORLD SPACE (Layer 2) — Point 0 = Earth Core Centre
A23: Axis | B23: Direction | C23: Positive (+) | D23: Negative (−) | E23: Range | F23: BeenFore City Value | G23: Unit | H23: Notes
A24: Z | B24: Core ↕ Sky (Altitude) | C24: Sky / Up ↑ | D24: ↓ Core / Down | E24: −6,371 km (core) to +∞ | F24: 0 m (ground level) | G24: m | H24: Z=0 = sea level / ground surface. Buildings extend +Z
A25: 🌐 WORLD LAYER HIERARCHY (Z-axis cross-section)
A26: Layer | B26: Z Range | C26: Thickness | D26: State | E26: Physics Type | F26: Relevance to A7DO
A27: Earth Core | B27: Z = 0 to −1,220 km | C27: 1,220 km | D27: Solid | E27: Gravitational | F27: Gravity source (9.81 m/s²)
A28: Outer Core | B28: Z = −1,220 to −3,400 km | C28: 2,180 km | D28: Liquid Metal | E28: Electromagnetic | F28: Magnetic field — compass orientation
A29: Mantle | B29: Z = −3,400 to −6,350 km | C29: 2,950 km | D29: Solid/Flowing | E29: Thermal Convection | F29: Heat source — geothermal
A30: Crust | B30: Z = −6,350 to −6,371 km | C30: 5–70 km | D30: Solid Rigid | E30: Elastic Solid | F30: Ground surface — collision layer
A31: Ground Level | B31: Z = 0 m | C31: — | D31: Surface | E31: Collision Solid | F31: A7DO & NPC standing plane
A32: Troposphere | B32: Z = 0 to +12 km | C32: 12 km | D32: Gas | E32: Fluid Gas | F32: Breathing air, weather, temperature
A33: Stratosphere | B33: Z = +12 to +50 km | C33: 38 km | D33: Gas | E33: Ozone Layer | F33: UV protection
A34: Thermosphere+ | B34: Z = +80 km to +∞ | C34: Variable | D34: Ionized/Vacuum | E34: Near Vacuum | F34: Space — beyond simulation scope
A36: 🔄 C — COORDINATE TRANSFORM — Body Local Space → World Space
A37: To place any body part in World Space: World_XYZ = Entity_World_Position + (Body_Local_XYZ × Scale_Factor). Scale_Factor converts normalised body coords (±1.0) to real metres based on entity height/width.
A38: Transform | B38: Formula | C38: Variables | D38: Example: A7DO Frontal Bone in World | E38: Example: NPC-001 Frontal Bone in World | F38: Notes
A39: World X | B39: W_X = Entity_X + (Local_X × Body_Width_m) | C39: Entity_X = NPC/A7DO world position X Local_X = body part local X Body_Width_m = body width in metres | D39: A7DO at H8 (X≈1090m) Frontal Bone Local_X=0 W_X = 1090 + (0 × 0.4) = 1090.0 m | E39: Alexis at H1 (X≈1050m) Frontal Bone Local_X=0 W_X = 1050 + (0 × 0.4) = 1050.0 m | F39: Body_Width_m ≈ 0.4m for adult (shoulder width)
A40: World Y | B40: W_Y = Entity_Y + (Local_Y × Body_Height_m) | C40: Entity_Y = NPC/A7DO world position Y Local_Y = body part local Y Body_Height_m = entity height in metres | D40: A7DO at H8 (Y≈880m) Frontal Bone Local_Y=0.85 Body_Height=0.5m (toddler) W_Y = 880 + (0.85 × 0.5) = 880.43 m | E40: Alexis at H1 (Y≈900m) Frontal Bone Local_Y=0.85 Body_Height=1.75m (adult) W_Y = 900 + (0.85 × 1.75) = 901.49 m | F40: Body_Height_m varies by age stage — see scale table below
A41: World Z | B41: W_Z = Ground_Z + (Local_Y × Body_Height_m) | C41: Ground_Z = altitude of standing surface Local_Y drives vertical height (Z in world = Y in body) | D41: A7DO standing on ground (Z=0) Frontal Bone Local_Y=0.85 W_Z = 0 + (0.85 × 0.5) = 0.43 m above ground | E41: Alexis standing (Z=0) Frontal Bone Local_Y=0.85 W_Z = 0 + (0.85 × 1.75) = 1.49 m above ground | F41: Body Y-axis maps to World Z-axis (vertical height above ground)
A42: Pelvis (Point 0) | B42: W_pelvis = Entity_World_Position | C42: The entity's world position IS the pelvis centre (Point 0 = pelvis in body space) | D42: A7DO pelvis = H8 world pos ≈ (1090, 880, 0) | E42: Alexis pelvis = H1 world pos ≈ (1050, 900, 0) | F42: All body parts computed relative to this anchor
A44: 📏 D — BODY SCALE FACTORS BY AGE STAGE
A45: Age Stage | B45: Age Range | C45: Height (m) | D45: Width (m) | E45: Body_Height_m | F45: Body_Width_m | G45: Pelvis Y offset (m) | H45: Head Y in World (m) | I45: Feet Y in World (m) | J45: Scale Source
A46: Newborn | B46: 0 months | C46: 0.5 | D46: 0.2 | E46: 0.5 | F46: 0.2 | G46: 0.25 | H46: 0.43 | I46: -0.3 | J46: Infant Anatomy Engine: avg 50cm
A47: Infant | B47: 3–12 months | C47: 0.65 | D47: 0.25 | E47: 0.65 | F47: 0.25 | G47: 0.33 | H47: 0.55 | I47: -0.39 | J47: Infant Anatomy Engine: 50–75cm
A48: Toddler | B48: 1–3 years | C48: 0.85 | D48: 0.3 | E48: 0.85 | F48: 0.3 | G48: 0.43 | H48: 0.72 | I48: -0.51 | J48: Child Anatomy: ~85cm at 1yr
A49: A7DO Current | B49: ~19.6 months | C49: 0.82 | D49: 0.28 | E49: 0.82 | F49: 0.28 | G49: 0.41 | H49: 0.7 | I49: -0.49 | J49: Interpolated: toddler stage
A50: Child | B50: 3–12 years | C50: 1.15 | D50: 0.4 | E50: 1.15 | F50: 0.4 | G50: 0.58 | H50: 0.98 | I50: -0.69 | J50: Child Anatomy: 75–150cm
A51: Adolescent | B51: 12–18 years | C51: 1.6 | D51: 0.45 | E51: 1.6 | F51: 0.45 | G51: 0.8 | H51: 1.36 | I51: -0.96 | J51: Adolescent: ~160cm avg
A52: Adult | B52: 18+ years | C52: 1.75 | D52: 0.5 | E52: 1.75 | F52: 0.5 | G52: 0.88 | H52: 1.49 | I52: -1.05 | J52: Adult Anatomy Engine: ~175cm
A53: Elder | B53: 65+ years | C53: 1.68 | D53: 0.48 | E53: 1.68 | F53: 0.48 | G53: 0.84 | H53: 1.43 | I53: -1.01 | J53: Slight height reduction
A55: 👥 E — NPC & A7DO WORLD POSITIONS — Corrected Spatial Registry
A56: NPC World X/Y in source file (e.g. Alexis: 10.5, 5.2) appear to be LOCAL house offsets in metres, NOT absolute world coordinates. Corrected World positions below use BeenFore City house coordinates from BeenFore City sheet. World Z = 0 (ground level) for all standing entities.
A57: Entity | B57: NPC ID | C57: Age Stage | D57: Height (m) | E57: House | F57: House World X | G57: House World Y | H57: House World Z | I57: Body Local X (pelvis) | J57: Body Local Y (pelvis) | K57: Body Local Z (pelvis) | L57: Head World X | M57: Head World Y | N57: Head World Z (height) | O57: Notes
A58: A7DO | B58: — | C58: Organism | D58: 0.82 | E58: H8 | F58: 1090 | G58: 880 | H58: 0 | I58: 0 | J58: 0 | K58: 0 | L58: 1090 | M58: 880 | N58: 0.697 | O58: Primary organism — current age ~19.6 months
A59: Alexis | B59: NPC-001 | C59: Adult | D59: 1.75 | E59: H1 | F59: 1050 | G59: 900 | H59: 0 | I59: 0 | J59: 0 | K59: 0 | L59: 1050 | M59: 900 | N59: 1.488 | O59: Adult male, age 35
A60: Evelyn | B60: NPC-002 | C60: Adult | D60: 1.75 | E60: H1 | F60: 1050 | G60: 900 | H60: 0 | I60: 0 | J60: 0 | K60: 0 | L60: 1050 | M60: 900 | N60: 1.488 | O60: Adult female, age 33
A61: Liam | B61: NPC-003 | C61: Adolescent | D61: 1.6 | E61: H2 | F61: 1070 | G61: 900 | H61: 0 | I61: 0 | J61: 0 | K61: 0 | L61: 1070 | M61: 900 | N61: 1.36 | O61: Teen male, age 15
A62: Sophia | B62: NPC-004 | C62: Adolescent | D62: 1.6 | E62: H3 | F62: 1090 | G62: 900 | H62: 0 | I62: 0 | J62: 0 | K62: 0 | L62: 1090 | M62: 900 | N62: 1.36 | O62: Teen female, age 14
A63: Noah | B63: NPC-005 | C63: Child | D63: 1.15 | E63: H6 | F63: 1050 | G63: 880 | H63: 0 | I63: 0 | J63: 0 | K63: 0 | L63: 1050 | M63: 880 | N63: 0.977 | O63: Child male, age 5
A64: Emma | B64: NPC-006 | C64: Child | D64: 1.15 | E64: H6 | F64: 1050 | G64: 880 | H64: 0 | I64: 0 | J64: 0 | K64: 0 | L64: 1050 | M64: 880 | N64: 0.977 | O64: Child female, age 4
A65: James | B65: NPC-007 | C65: Elder | D65: 1.68 | E65: H7 | F65: 1070 | G65: 880 | H65: 0 | I65: 0 | J65: 0 | K65: 0 | L65: 1070 | M65: 880 | N65: 1.428 | O65: Elder male, age 68
A66: Olivia | B66: NPC-008 | C66: Elder | D66: 1.68 | E66: H7 | F66: 1070 | G66: 880 | H66: 0 | I66: 0 | J66: 0 | K66: 0 | L66: 1070 | M66: 880 | N66: 1.428 | O66: Elder female, age 65
A68: ⚠️ F — COORDINATE ISSUES FOUND & RECOMMENDED FIXES
A69: Issue | B69: Location | C69: Current State | D69: Problem | E69: Recommended Fix | F69: Priority
A70: NPC World X/Y scale mismatch | B70: NPC System sheet — World X/Y columns | C70: Alexis: World X=10.5, Y=5.2 | D70: BeenFore City houses are at X=1050–1130, Y=880–900. NPC values of 10.5/5.2 are ~100× too small — likely local room offsets, not world coords. | E70: Replace NPC World X/Y with house world coordinates: Alexis → X=1050, Y=900, Z=0 | F70: 🔴 HIGH
A71: BeenFore City Z missing | B71: BeenFore City sheet — World Z column | C71: All house World Z = blank | D71: Z coordinate (altitude/height) is missing for all houses and rooms. | E71: Set all house World Z = 0 (ground level). Room Z: ground floor=0, upper floor=+3m | F71: 🟡 MEDIUM
A72: NPC System World Origin blank | B72: NPC System — World Origin X/Y/Z | C72: World Origin X/Y/Z = blank | D72: The NPC control panel references Point 0 but values are empty. | E72: Set World Origin X=1000, Y=1000, Z=0 (BeenFore City centre in World Space) | F72: 🟡 MEDIUM
A73: Body Local XYZ not scaled to real metres | B73: Anatomy Growth Engine — Local X/Y/Z | C73: Frontal Bone: X=0, Y=0.85, Z=0.08 | D73: These are normalised (0–1 range) not real metres. No scale factor applied in sheet. | E73: Add 'Real X/Y/Z (m)' columns = Local × Body_Scale. Use scale table in Section D. | F73: 🟡 MEDIUM
A74: Infant/Child anatomy XYZ not cross-referenced to Adult | B74: Infant/Child Anatomy Engine sheets | C74: Separate XYZ per sheet, different scales | D74: Infant skull at Y=0.25 (25cm above pelvis) vs Adult skull at Y=0.85 — no growth curve linking them. | E74: Growth Timeline Section C now shows Infant/Child/Adult sizes side-by-side. Add World Z column showing real height at each stage. | F74: 🟢 LOW
A75: DNA Loop Engine X₀ = 5m | B75: DNA Loop Engine — Point 0 section | C75: X₀ (Horizontal) = 5 m | D75: Point 0 X should be 0 (pelvis midline). Value of 5 appears to be a data entry error. | E75: Correct X₀ = 0 m (pelvis centre is on body midline) | F75: 🔴 HIGH
A77: 🏥 HOSPITAL ORIGIN UPDATE — World Origin Redefined as Hospital Birth Location
A78: IMPORTANT UPDATE: The World Origin (0,0,0) is now defined as the Hospital Bed (birth location), NOT the abstract Earth Core Centre. BeenFore City is at (1090, 880, 0) from this origin. This makes the coordinate system physically meaningful and anchored to A7DO's lived experience.
A79: Parameter | B79: Previous Value | C79: Updated Value | D79: Reason | E79: Impact
A80: World Origin (0,0,0) | B80: Earth Core Centre (abstract) | C80: Hospital Bed — Birth Location (concrete) | D80: Anchors world to A7DO's lived experience; makes coordinates meaningful | E80: All world positions now measured from birth location
A81: BeenFore City X | B81: 1000m (from abstract origin) | C81: 1090m (from hospital) | D81: Hospital is ~1090m West of BeenFore City centre | E81: NPC positions updated relative to hospital
A82: BeenFore City Y | B82: 1000m (from abstract origin) | C82: 880m (from hospital) | D82: Hospital is ~880m South of BeenFore City centre | E82: NPC positions updated relative to hospital
A83: A7DO Home (H8) position | B83: (1090, 880, 0) from abstract origin | C83: (1090, 880, 0) from hospital — same values, new meaning | D83: H8 is 1090m East, 880m North of hospital | E83: Distance from hospital to home = 1384m
A84: World Z = 0 | B84: Sea level / ground surface | C84: Ground level at hospital (same as before) | D84: No change — Z=0 is still ground level | E84: No impact on Z coordinates
A85: Transform formula | B85: W_xyz = Entity_pos + Local_xyz·Scale | C85: W_xyz = HospitalOrigin + BodyOffset(t) + Body_xyz·Scale(t) | D85: Adds BodyOffset to track movement from birth location | E85: Motor planning now outputs world positions from hospital origin

Sheet 🫀 Body Systems
A1: ⚡ LIVE TICK PANEL — All values auto-update from 🧬 DNA Loop Engine B4 (Current Tick)
A2: Current Tick: | B2: ='🧬 DNA Loop Engine'!B4 -> 10000 | C2: Current Week: | D2: ='🧬 DNA Loop Engine'!B5 -> 125 | E2: Birth Status: | F2: ='🧬 DNA Loop Engine'!B8 -> 🎉 BIRTH COMPLETE
A3: Life Stage: | B3: ='🧬 DNA Loop Engine'!B15 -> 🧒 Toddler | C3: Age: | D3: ='🧬 DNA Loop Engine'!B16 -> 19.6 months (1.63 yrs) | E3: DNA Phase: | F3: ='🧬 DNA Loop Engine'!B11 -> Toddler
A4: Growth Factor: | B4: ='🧬 DNA Loop Engine'!B18 -> 1 | C4: Neural Gain: | D4: ='🧬 DNA Loop Engine'!B19 -> 1 | E4: Cord Status: | F4: ='🧬 DNA Loop Engine'!B22 -> 🔌 SEVERED
A5: G_phys (height): | B5: ='🧬 DNA Loop Engine'!B28 -> 1.706 | C5: Heart Rate: | D5: ='🧬 DNA Loop Engine'!B27 -> 70 | E5: Reflex Gain: | F5: ='🧬 DNA Loop Engine'!B20 -> 1
A6: 🫀 BODY SYSTEMS — Circulatory · Respiratory · Digestive · Sensory
A8: ❤️ CIRCULATORY SYSTEM
A9: Name | B9: Controlled Structure | C9: Neural Region | D9: Control Type | E9: Signal Pathway | F9: Feedback Source | G9: Activation Week | H9: Full Maturity Week | I9: Domain | J9: Current Week | K9: Growth Status | L9: Maturity % | M9: Local X | N9: Local Y | O9: Local Z | P9: Connection To | Q9: Flow Direction | R9: Flow Rate Factor
A10: Heart | B10: Organ | C10: Autonomic System | D10: Homeostatic | E10: Vagal Pathway | F10: Baroreceptors | G10: 8 | H10: 28 | I10: Embodiment | J10: ='🧬 DNA Loop Engine'!B5 -> 125 | K10: ✅ Mature | L10: 1 | M10: 0 | N10: 0.35 | O10: 0.05 | P10: Sternum | Q10: Central Pump | R10: 1
A11: Aorta | B11: Vessel | C11: Autonomic System | D11: Pressure Regulation | E11: Sympathetic Pathway | F11: Stretch Receptors | G11: 8 | H11: 28 | I11: Embodiment | J11: ='🧬 DNA Loop Engine'!B5 -> 125 | K11: ✅ Mature | L11: 1 | M11: 0 | N11: 0.4 | O11: 0.03 | P11: Heart | Q11: Ascending | R11: 0.95
A12: Pulmonary Artery | B12: Vessel | C12: Autonomic System | D12: Oxygen Exchange | E12: Vagal Pathway | F12: Chemoreceptors | G12: 8 | H12: 28 | I12: Embodiment | J12: ='🧬 DNA Loop Engine'!B5 -> 125 | K12: ✅ Mature | L12: 1 | M12: 0 | N12: 0.38 | O12: -0.02 | P12: Heart | Q12: To Lungs | R12: 0.9
A13: Pulmonary Veins | B13: Vessel | C13: Autonomic System | D13: Oxygen Return | E13: Vagal Pathway | F13: Chemoreceptors | G13: 8 | H13: 28 | I13: Embodiment | J13: ='🧬 DNA Loop Engine'!B5 -> 125 | K13: ✅ Mature | L13: 1 | M13: 0 | N13: 0.36 | O13: -0.02 | P13: Lungs | Q13: From Lungs | R13: 0.9
A14: Vena Cava | B14: Vessel | C14: Autonomic System | D14: Venous Return | E14: Sympathetic Pathway | F14: Pressure Sensors | G14: 8 | H14: 28 | I14: Embodiment | J14: ='🧬 DNA Loop Engine'!B5 -> 125 | K14: ✅ Mature | L14: 1 | M14: 0 | N14: 0.3 | O14: 0 | P14: Heart | Q14: To Heart | R14: 0.85
A15: Coronary Arteries | B15: Vessel | C15: Autonomic System | D15: Cardiac Perfusion | E15: Sympathetic Pathway | F15: Baroreceptors | G15: 8 | H15: 28 | I15: Embodiment | J15: ='🧬 DNA Loop Engine'!B5 -> 125 | K15: ✅ Mature | L15: 1 | M15: 0.02 | N15: 0.36 | O15: 0.04 | P15: Aorta | Q15: Cardiac Supply | R15: 0.8
A16: Capillary Networks | B16: Vessel | C16: Autonomic System | D16: Microcirculation | E16: Local Autoregulation | F16: Oxygen Sensors | G16: 12 | H16: 28 | I16: Embodiment | J16: ='🧬 DNA Loop Engine'!B5 -> 125 | K16: ✅ Mature | L16: 1 | M16: 0 | N16: 0 | O16: 0 | P16: Arterioles | Q16: Bidirectional | R16: 0.7
A17: Blood | B17: Fluid | C17: Autonomic System | D17: Transport Medium | E17: Endocrine Feedback | F17: Hemoglobin Sensors | G17: 12 | H17: 28 | I17: Embodiment | J17: ='🧬 DNA Loop Engine'!B5 -> 125 | K17: ✅ Mature | L17: 1 | M17: 0 | N17: 0 | O17: 0 | P17: All Vessels | Q17: Circulating | R17: 1
A18: Superior Vena Cava | B18: Vessel | C18: Autonomic System | D18: Upper Body Return | E18: Sympathetic Pathway | F18: Pressure Sensors | G18: 8 | H18: 28 | I18: Embodiment | J18: ='🧬 DNA Loop Engine'!B5 -> 125 | K18: ✅ Mature | L18: 1 | M18: 0 | N18: 0.45 | O18: 0 | P18: Heart | Q18: Upper Return | R18: 0.85
A19: Inferior Vena Cava | B19: Vessel | C19: Autonomic System | D19: Lower Body Return | E19: Sympathetic Pathway | F19: Pressure Sensors | G19: 8 | H19: 28 | I19: Embodiment | J19: ='🧬 DNA Loop Engine'!B5 -> 125 | K19: ✅ Mature | L19: 1 | M19: 0 | N19: 0.2 | O19: 0 | P19: Heart | Q19: Lower Return | R19: 0.85
A20: Carotid Arteries | B20: Vessel | C20: Autonomic System | D20: Cerebral Perfusion | E20: Sympathetic Pathway | F20: Baroreceptors | G20: 8 | H20: 28 | I20: Embodiment | J20: 125 | K20: ✅ Mature | L20: 1 | M20: 0.05 | N20: 0.6 | O20: 0.02 | P20: Aorta | Q20: To Brain | R20: 0.9
A21: Jugular Veins | B21: Vessel | C21: Autonomic System | D21: Cerebral Drainage | E21: Sympathetic Pathway | F21: Pressure Sensors | G21: 8 | H21: 28 | I21: Embodiment | J21: 125 | K21: ✅ Mature | L21: 1 | M21: 0.06 | N21: 0.55 | O21: 0 | P21: Brain | Q21: From Brain | R21: 0.85
A22: Hepatic Portal Vein | B22: Vessel | C22: Autonomic System | D22: Nutrient Transport | E22: Vagal Pathway | F22: Chemoreceptors | G22: 10 | H22: 28 | I22: Embodiment | J22: 125 | K22: ✅ Mature | L22: 1 | M22: 0.08 | N22: 0.25 | O22: 0.05 | P22: Intestines | Q22: Nutrient Carry | R22: 0.8
A23: Renal Arteries | B23: Vessel | C23: Autonomic System | D23: Kidney Perfusion | E23: Sympathetic Pathway | F23: Pressure Sensors | G23: 10 | H23: 28 | I23: Embodiment | J23: 125 | K23: ✅ Mature | L23: 1 | M23: 0.1 | N23: 0.15 | O23: 0 | P23: Aorta | Q23: To Kidneys | R23: 0.85
A24: Umbilical Arteries | B24: Vessel | C24: Autonomic System | D24: Waste Transport | E24: Vagal Pathway | F24: Chemoreceptors | G24: 4 | H24: 40 | I24: Embodiment | J24: 125 | K24: ✅ Mature | L24: 1 | M24: 0 | N24: -0.1 | O24: 0 | P24: Placenta | Q24: Waste Out | R24: 0.95
A25: Umbilical Vein | B25: Vessel | C25: Autonomic System | D25: Nutrient Delivery | E25: Vagal Pathway | F25: Oxygen Sensors | G25: 4 | H25: 40 | I25: Embodiment | J25: 125 | K25: ✅ Mature | L25: 1 | M25: 0 | N25: -0.1 | O25: 0.02 | P25: Placenta | Q25: Nutrients In | R25: 0.95
A26: Ductus Arteriosus | B26: Fetal Shunt | C26: Autonomic System | D26: Pulmonary Bypass | E26: Local Autoregulation | F26: Oxygen Sensors | G26: 6 | H26: 40 | I26: Embodiment | J26: 125 | K26: ✅ Mature | L26: 1 | M26: 0 | N26: 0.38 | O26: 0 | P26: Pulmonary/Aorta | Q26: Bypass | R26: 0.9
A27: Foramen Ovale | B27: Fetal Shunt | C27: Autonomic System | D27: Atrial Shunt | E27: Local Autoregulation | F27: Pressure Sensors | G27: 6 | H27: 40 | I27: Embodiment | J27: 125 | K27: ✅ Mature | L27: 1 | M27: 0 | N27: 0.35 | O27: 0.02 | P27: Atria | Q27: Atrial Bypass | R27: 0.9
A28: 🩸 CIRCULATORY SYSTEM SUMMARY
A29: Parameter | B29: Value | C29: Unit | E29: 🔗 CROSS-SYSTEM LINKS
A30: Total Components: | B30: 18 | E30: Linked Sheet | F30: Connection
A31: Vessels: | B31: 14 | E31: DNA Loop Engine | F31: Current Week (B5)
A32: Organs: | B32: 1 | E32: Respiratory Control | F32: O₂ Exchange
A33: Fetal Shunts: | B33: 2 | E33: Anatomy Growth Engine | F33: Heart Coordinates
A34: Fluids: | B34: 1 | E34: Neural Control | F34: Autonomic Pathways
A35: ⏳ Pending: | B35: 0
A36: 🔄 Developing: | B36: 0
A37: ✅ Mature: | B37: 18
A38: Average Maturity: | B38: 1 | C38: %
A39: 🫀 CARDIAC METRICS (from DNA Loop Engine)
A40: Heart Rate: | B40: 80 | C40: BPM | E40: Status: | F40: ✅ MATURE
A41: Cardiac Output: | B41: 0.16 | C41: L/min
A42: Blood Flow: | B42: 0.32 | C42: L/min
A43: Blood Volume: | B43: 300 mL
A44: 🔗 RESPIRATORY SYNC
A45: O₂ Delivery Rate: | B45: 0.22719999999999999 | C45: L O₂/min
A46: CO₂ Removal Rate: | B46: 0.02880000000000001 | C46: L CO₂/min
A47: System Sync: | B47: 🟢 SYNCHRONIZED
A48: 🧬 FETAL CIRCULATION STATUS
A49: Umbilical Flow: | B49: ❌ SEVERED
A50: Ductus Arteriosus: | B50: 🔒 CLOSING
A51: Foramen Ovale: | B51: 🔒 CLOSING
A54: 🫁 RESPIRATORY CONTROL
A55: Name | B55: Controlled Structure | C55: Neural Region | D55: Control Type | E55: Signal Pathway | F55: Feedback Source | G55: Activation Week | H55: Full Maturity Week | I55: Domain | J55: Current Week | K55: Growth Status | L55: Maturity %
A56: Lungs | B56: Organ | C56: Autonomic System | D56: Rhythmic | E56: Vagal Pathway | F56: Chemoreceptors | G56: 8 | H56: 28 | I56: Embodiment | J56: 125 | K56: ✅ Mature | L56: 1
A57: Trachea | B57: Organ | C57: Autonomic System | D57: Airflow Regulation | E57: Sympathetic Pathway | F57: Stretch Receptors | G57: 8 | H57: 28 | I57: Embodiment | J57: 125 | K57: ✅ Mature | L57: 1
A58: Bronchi | B58: Organ | C58: Autonomic System | D58: Air Distribution | E58: Vagal Pathway | F58: Pressure Sensors | G58: 8 | H58: 28 | I58: Embodiment | J58: 125 | K58: ✅ Mature | L58: 1
A59: Bronchioles | B59: Organ | C59: Autonomic System | D59: Micro-Airflow | E59: Local Autoregulation | F59: Oxygen Sensors | G59: 12 | H59: 28 | I59: Embodiment | J59: 125 | K59: ✅ Mature | L59: 1
A60: Alveoli | B60: Organ | C60: Autonomic System | D60: Oxygen Exchange | E60: Local Autoregulation | F60: O₂/CO₂ Sensors | G60: 12 | H60: 28 | I60: Embodiment | J60: 125 | K60: ✅ Mature | L60: 1
A61: Diaphragm | B61: Muscle | C61: Brainstem | D61: Rhythmic Motor | E61: Phrenic Nerve Pathway | F61: Stretch Receptors | G61: 8 | H61: 28 | I61: Motor Control | J61: 125 | K61: ✅ Mature | L61: 1
A62: Intercostal Muscles | B62: Muscle | C62: Brainstem | D62: Rhythmic Motor | E62: Spinal Respiratory Pathway | F62: Stretch Receptors | G62: 8 | H62: 28 | I62: Motor Control | J62: 125 | K62: ✅ Mature | L62: 1
A63: Nasal Cavity | B63: Organ | C63: Autonomic System | D63: Air Filtration | E63: Trigeminal Pathway | F63: Temperature Sensors | G63: 8 | H63: 28 | I63: Sensing | J63: 125 | K63: ✅ Mature | L63: 1
A64: Pharynx | B64: Organ | C64: Autonomic System | D64: Air Passage | E64: Glossopharyngeal Pathway | F64: Pressure Sensors | G64: 8 | H64: 28 | I64: Sensing | J64: 125 | K64: ✅ Mature | L64: 1
A65: Larynx | B65: Organ | C65: Autonomic System | D65: Airflow Modulation | E65: Vagal Pathway | F65: Sound/Vibration Sensors | G65: 8 | H65: 28 | I65: Sensing | J65: 125 | K65: ✅ Mature | L65: 1
A68: 🍽️ DIGESTIVE CONTROL
A69: Name | B69: Controlled Structure | C69: Neural Region | D69: Control Type | E69: Signal Pathway | F69: Feedback Source | G69: Activation Week | H69: Full Maturity Week | I69: Domain | J69: Current Week | K69: Growth Status | L69: Maturity % | M69: Local X | N69: Local Y | O69: Local Z | P69: Connection To | Q69: Flow Direction | R69: Flow Rate Factor
A70: Mouth | B70: Organ | C70: Brainstem | D70: Autonomic | E70: Trigeminal Pathway | F70: Taste Receptors | G70: 8 | H70: 28 | I70: Sensing | J70: 125 | K70: ✅ Mature | L70: 1 | M70: 0 | N70: 0.7 | O70: 0.12 | P70: Skull | Q70: Intake | R70: 0.9
A71: Pharynx | B71: Organ | C71: Brainstem | D71: Autonomic | E71: Glossopharyngeal Pathway | F71: Pressure Sensors | G71: 8 | H71: 28 | I71: Sensing | J71: 125 | K71: ✅ Mature | L71: 1 | M71: 0 | N71: 0.65 | O71: 0.08 | P71: Mouth | Q71: Passage | R71: 0.85
A72: Esophagus | B72: Organ | C72: Autonomic System | D72: Peristaltic | E72: Vagal Pathway | F72: Stretch Receptors | G72: 8 | H72: 28 | I72: Embodiment | J72: 125 | K72: ✅ Mature | L72: 1 | M72: 0 | N72: 0.5 | O72: 0.02 | P72: Pharynx | Q72: Descending | R72: 0.8
A73: Stomach | B73: Organ | C73: Autonomic System | D73: Churning | E73: Vagal Pathway | F73: Chemical Sensors | G73: 8 | H73: 28 | I73: Embodiment | J73: 125 | K73: ✅ Mature | L73: 1 | M73: 0.05 | N73: 0.3 | O73: 0.05 | P73: Esophagus | Q73: Processing | R73: 0.85
A74: Small Intestine | B74: Organ | C74: Autonomic System | D74: Peristaltic | E74: Vagal Pathway | F74: Nutrient Sensors | G74: 12 | H74: 28 | I74: Embodiment | J74: 125 | K74: ✅ Mature | L74: 1 | M74: 0 | N74: 0.15 | O74: 0.05 | P74: Stomach | Q74: Absorption | R74: 0.9
A75: Large Intestine | B75: Organ | C75: Autonomic System | D75: Absorptive | E75: Local Autoregulation | F75: Pressure Sensors | G75: 12 | H75: 28 | I75: Embodiment | J75: 125 | K75: ✅ Mature | L75: 1 | M75: 0.08 | N75: 0.1 | O75: 0 | P75: Small Intestine | Q75: Processing | R75: 0.75
A76: Liver | B76: Organ | C76: Autonomic System | D76: Metabolic Regulation | E76: Sympathetic Pathway | F76: Glucose Sensors | G76: 12 | H76: 28 | I76: Embodiment | J76: 125 | K76: ✅ Mature | L76: 1 | M76: 0.1 | N76: 0.28 | O76: 0.03 | P76: Hepatic Portal Vein | Q76: Filtration | R76: 0.95
A77: Gallbladder | B77: Organ | C77: Autonomic System | D77: Bile Release | E77: Vagal Pathway | F77: Chemical Sensors | G77: 12 | H77: 28 | I77: Embodiment | J77: 125 | K77: ✅ Mature | L77: 1 | M77: 0.08 | N77: 0.26 | O77: 0.04 | P77: Liver | Q77: Secretion | R77: 0.7
A78: Pancreas | B78: Organ | C78: Autonomic System | D78: Enzyme Secretion | E78: Sympathetic Pathway | F78: Glucose Sensors | G78: 12 | H78: 28 | I78: Embodiment | J78: 125 | K78: ✅ Mature | L78: 1 | M78: -0.05 | N78: 0.25 | O78: 0.02 | P78: Stomach | Q78: Secretion | R78: 0.85
A79: Rectum | B79: Organ | C79: Autonomic System | D79: Expulsion Control | E79: Spinal Reflex Arc | F79: Pressure Sensors | G79: 12 | H79: 28 | I79: Embodiment | J79: 125 | K79: ✅ Mature | L79: 1 | M79: 0 | N79: -0.15 | O79: -0.05 | P79: Large Intestine | Q79: Output | R79: 0.6
A80: 🍽️ DIGESTIVE SYSTEM SUMMARY
A81: Parameter | B81: Value | C81: Unit | E81: 🔗 CROSS-SYSTEM LINKS
A82: Total Components: | B82: 10 | E82: Linked Sheet | F82: Connection
A83: Organs: | B83: 10 | E83: DNA Loop Engine | F83: Current Week (B5)
E84: Circulatory System | F84: Nutrient Transport
A85: ⏳ Pending: | B85: 0 | E85: Respiratory Control | F85: O₂ for Metabolism
A86: 🔄 Developing: | B86: 0 | E86: Anatomy Growth Engine | F86: Organ Coordinates
A87: ✅ Mature: | B87: 10 | E87: Umbilical System | F87: Prenatal Nutrients
A88: Average Maturity: | B88: 1 | C88: %
A89: 🥗 DIGESTIVE METRICS DASHBOARD
A90: Parameter | B90: Value | C90: Unit | E90: Status | F90: Visual
A91: Peristalsis Rate: | B91: 50 | C91: cycles/min | E91: 🔄 Peristaltic Motion: | F91: 🌊 🌊 🌊 🌊 🌊
A92: Nutrient Demand: | B92: 0.8 | C92: (0-1) | E92: Gut Activity: | F92: Active churning
A93: Absorption Efficiency: | B93: 0.95 | C93: %
A94: Enzyme Secretion: | B94: 0.9 | C94: (0-1) | E94: 🧬 Enzyme Status: | F94: Full secretion
A95: Bile Flow: | B95: 0.8 | C95: (0-1)
A96: Glucose Processing: | B96: 1 | C96: (0-1) | E96: 🍬 Glucose Status: | F96: Metabolizing
A97: Waste Output: | B97: 0.5 | C97: (0-1)
A98: Digestive Maturity: | B98: 1 | C98: %
A99: Digestive Status: | B99: ✅ MATURE
A100: 🔗 NUTRIENT-CIRCULATORY INTEGRATION
A101: Metric | B101: Value | C101: Unit | E101: Sync Status
A102: Nutrient Delivery Rate: | B102: 0 | C102: (0-1) | E102: 🟡 DEVELOPING
A103: Hepatic Portal Flow: | B103: 0 | C103: (0-1)
A104: Glucose to Blood: | B104: 1 | C104: (0-1) | E104: 🟢 ACTIVE
A105: Metabolic Sync: | B105: 🟡 DEVELOPING
...

Sheet 🔬 Subsystems
A1: 🔬 A7DO SUBSYSTEMS — P1 Proprioception · P2 Object Permanence · P3 Episodic Memory · P4 Value System · P6 Motor Planning
A2: All subsystems specified and ready for implementation. Change 🧬 DNA Loop Engine B4 to see current developmental stage for each system.
A3: ⚡ LIVE TICK PANEL
A4: Current Tick | B4: ='🧬 DNA Loop Engine'!B4 -> 10000 | C4: Current Week | D4: ='🧬 DNA Loop Engine'!B5 -> 125 | E4: Life Stage | F4: ='🧬 DNA Loop Engine'!B15 -> 🧒 Toddler | G4: Growth Factor | H4: ='🧬 DNA Loop Engine'!B18 -> 1 | I4: Neural Gain | J4: ='🧬 DNA Loop Engine'!B19 -> 1 | K4: Birth Status | L4: ='🧬 DNA Loop Engine'!B8 -> 🎉 BIRTH COMPLETE
A5: 📋 SUBSYSTEM OVERVIEW — All 5 Critical Path Systems
A6: Priority | B6: System | C6: Category | D6: Core Equation | E6: Current Stage | F6: Requires | G6: Unlocks | H6: v2.0 Status | I6: Build Phase
A7: P1 | B7: Proprioception | C7: Embodiment | D7: P_b(t) = K_s·θ + K_v·θ̇ + K_f·F_m + ε | E7: ='🧬 DNA Loop Engine'!B15&" — Stage 3 (Coordinated)" -> 🧒 Toddler — Stage 3 (Coordinated) | F7: Anatomy, Body Systems | G7: Motor Planning, Vestibular, Balance | H7: 🔴 Implement | I7: Phase 1
A8: P2 | B8: Object Permanence | C8: Vision/Cognition | D8: C_i(t) = C₀·exp(−λ·(t−t_lastSeen)) | E8: ='🧬 DNA Loop Engine'!B15&" — Stage 3 (Trajectory Pred.)" -> 🧒 Toddler — Stage 3 (Trajectory Pred.) | F8: Sensory Integration, Memory | G8: Language nouns, Motor reach | H8: 🔴 Implement | I8: Phase 1
A9: P3 | B9: Episodic Memory | C9: Cognition | D9: E_i = (S_i, A_i, T_i, U_i); w_i = σ(U_i) | E9: ='🧬 DNA Loop Engine'!B15&" — Stage 3 (Full Episodes)" -> 🧒 Toddler — Stage 3 (Full Episodes) | F9: Object Permanence, Emotion | G9: Theory of Mind, Identity | H9: 🔴 Implement | I9: Phase 1
A10: P4 | B10: Value System | C10: Motivation | D10: V(a) = R(a) + γ·E[V(s')]; dC/dt = −C/τ + k·novelty | E10: ='🧬 DNA Loop Engine'!B15&" — Stage 2 (Goal-Directed)" -> 🧒 Toddler — Stage 2 (Goal-Directed) | F10: Emotion Module, Energy/ATP | G10: All goal-directed behaviour | H10: 🔴 Implement | I10: Phase 1
A11: P6 | B11: Motor Planning | C11: Motor | D11: min J = ∫[(x−x_g)ᵀQ(x−x_g)+uᵀRu]dt; θ=J⁺·Δx | E11: ='🧬 DNA Loop Engine'!B15&" — Stage 2 (Coordinated Reach)" -> 🧒 Toddler — Stage 2 (Coordinated Reach) | F11: Proprioception, Object Perm., Value | G11: Tool use, Navigation, Grasping | H11: 🟡 Partial | I11: Phase 1
A13: 🦴 P1 — PROPRIOCEPTION
A14: Stage | B14: Weeks | C14: Age | D14: Capability | E14: Key Param | F14: Accuracy/Decay | G14: Feedback | H14: Current?
A15: 0 — None | B15: 0–40 | C15: Prenatal | D15: No body awareness | E15: 0 | F15: None | G15: None
A16: 1 — Limb Flail | B16: 40–60 | C16: 0–3 months | D16: Random limb movement | E16: 0.1 | F16: ±30cm | G16: None
A17: 2 — Basic Map | B17: 60–100 | C17: 3–12 months | D17: Rough limb position awareness | E17: 0.3 | F17: ±10cm | G17: Slow
A18: 3 — Coord. ★ | B18: 100–160 | C18: 12–24 months | D18: Coordinated reaching active | E18: 0.6 | F18: ±3cm | G18: Active | H18: ="★ NOW (Wk "&'🧬 DNA Loop Engine'!B5&")" -> ★ NOW (Wk 125)
A19: 4 — Predictive | B19: 160–260 | C19: 24–48 months | D19: Predictive proprioception | E19: 0.85 | F19: ±1cm | G19: Fast
A20: 5 — Full Schema | B20: 260+ | C20: 48+ months | D20: Full body schema | E20: 1.0 | F20: ±0.3cm | G20: Optimal
A22: 👁️ P2 — OBJECT PERMANENCE
A23: Stage | B23: Weeks | C23: Age | D23: Capability | E23: Key Param | F23: Accuracy/Decay | G23: Feedback | H23: Current?
A24: 0 — None | B24: 0–40 | C24: Prenatal | D24: No permanence — world resets | E24: N/A | F24: None | G24: None
A25: 1 — Short Pers. | B25: 40–80 | C25: 0–10 months | D25: Brief persistence (1–2 sec) | E25: 0.5 | F25: None | G25: None
A26: 2 — Hidden Track | B26: 80–120 | C26: 10–15 months | D26: Tracks hidden objects 10 sec | E26: 0.1 | F26: Linear | G26: Basic
A27: 3 — Traj. Pred. ★ | B27: 120–200 | C27: 15–25 months | D27: Predicts hidden object trajectory | E27: 0.05 | F27: Kinematic | G27: Relational | H27: ="★ NOW (Wk "&'🧬 DNA Loop Engine'!B5&")" -> ★ NOW (Wk 125)
A28: 4 — Abstract | B28: 200–350 | C28: 25–67 months | D28: Abstract permanence | E28: 0.01 | F28: Full | G28: Full
A29: 5 — Social | B29: 350+ | C29: 67+ months | D29: Social permanence + ToM | E29: 0.001 | F29: Intentional | G29: Social
A31: 💾 P3 — EPISODIC MEMORY
A32: Stage | B32: Weeks | C32: Age | D32: Capability | E32: Key Param | F32: Accuracy/Decay | G32: Feedback | H32: Current?
A33: 0 — None | B33: 0–40 | C33: Prenatal | D33: No episodic memory | E33: None | F33: None | G33: None
A34: 1 — Momentary | B34: 40–80 | C34: 0–10 months | D34: Momentary recall (seconds) | E34: <10s | F34: Basic | G34: None
A35: 2 — Short Seq. | B35: 80–120 | C35: 10–15 months | D35: Short sequences (minutes) | E35: <5min | F35: Moderate | G35: Partial
A36: 3 — Full Ep. ★ | B36: 120–200 | C36: 15–25 months | D36: Full episodes with context | E36: <1day | F36: Strong | G36: Forming | H36: ="★ NOW (Wk "&'🧬 DNA Loop Engine'!B5&")" -> ★ NOW (Wk 125)
A37: 4 — Narrative | B37: 200–350 | C37: 25–67 months | D37: Narrative memory chains | E37: <1wk | F37: Full | G37: Growing
A38: 5 — Autobiog. | B38: 350+ | C38: 67+ months | D38: Full autobiographical identity | E38: Life | F38: Full | G38: Complete
A40: 🎯 P4 — VALUE SYSTEM
A41: Stage | B41: Weeks | C41: Age | D41: Capability | E41: Key Param | F41: Accuracy/Decay | G41: Feedback | H41: Current?
A42: 0 — Reflexive | B42: 0–40 | C42: Prenatal | D42: Reflexive reward only | E42: N/A | F42: Comfort | G42: None
A43: 1 — Basic Pref. | B43: 40–80 | C43: 0–10 months | D43: Basic preferences; approach/avoid | E43: 0.5 | F43: Attachment | G43: Single-step
A44: 2 — Goal-Dir. ★ | B44: 80–160 | C44: 10–24 months | D44: Goal-directed behaviour | E44: 1.0 | F44: Curiosity | G44: Short-horizon | H44: ="★ NOW (Wk "&'🧬 DNA Loop Engine'!B5&")" -> ★ NOW (Wk 125)
A45: 3 — Multi-Goal | B45: 160–312 | C45: 24–72 months | D45: Multi-goal arbitration | E45: 2.0 | F45: Exploration | G45: Multi-step
A46: 4 — Long-Term | B46: 312–624 | C46: 6–12 years | D46: Long-term planning | E46: 5.0 | F46: Goal Persist | G46: Long-horizon
A47: 5 — Identity | B47: 624+ | C47: 12+ years | D47: Identity-driven values | E47: 10.0 | F47: All drives | G47: Lifetime
A49: 🦾 P6 — MOTOR PLANNING
A50: Stage | B50: Weeks | C50: Age | D50: Capability | E50: Key Param | F50: Accuracy/Decay | G50: Feedback | H50: Current?
A51: 0 — Random | B51: 0–40 | C51: Prenatal | D51: Random limb movement | E51: None | F51: None | G51: None
A52: 1 — Basic Reach | B52: 40–80 | C52: 0–10 months | D52: Basic reaching; poor accuracy | E52: ±15cm | F52: Ballistic | G52: None
A53: 2 — Coord. ★ | B53: 80–160 | C53: 10–24 months | D53: Coordinated reaching | E53: ±5cm | F53: Smooth | G53: Palmar | H53: ="★ NOW (Wk "&'🧬 DNA Loop Engine'!B5&")" -> ★ NOW (Wk 125)
A54: 3 — Predictive | B54: 160–260 | C54: 24–48 months | D54: Predictive reaching | E54: ±2cm | F54: Predictive | G54: Pincer
A55: 4 — Grasping | B55: 260–400 | C55: 48–96 months | D55: Skilled grasping | E55: ±0.5cm | F55: Optimal | G55: Skilled
A56: 5 — Skilled | B56: 400+ | C56: 96+ months | D56: Full motor planning; tool use | E56: ±0.2cm | F56: Expert | G56: Expert

Sheet ⚡ Energy & Metabolism
A1: ⚡ LIVE TICK PANEL — All values auto-update from 🧬 DNA Loop Engine B4 (Current Tick)
A2: Current Tick: | B2: ='🧬 DNA Loop Engine'!B4 -> 10000 | C2: Current Week: | D2: ='🧬 DNA Loop Engine'!B5 -> 125 | E2: Birth Status: | F2: ='🧬 DNA Loop Engine'!B8 -> 🎉 BIRTH COMPLETE
A3: Life Stage: | B3: ='🧬 DNA Loop Engine'!B15 -> 🧒 Toddler | C3: Age: | D3: ='🧬 DNA Loop Engine'!B16 -> 19.6 months (1.63 yrs) | E3: DNA Phase: | F3: ='🧬 DNA Loop Engine'!B11 -> Toddler
A4: Growth Factor: | B4: ='🧬 DNA Loop Engine'!B18 -> 1 | C4: Neural Gain: | D4: ='🧬 DNA Loop Engine'!B19 -> 1 | E4: Cord Status: | F4: ='🧬 DNA Loop Engine'!B22 -> 🔌 SEVERED
A5: G_phys (height): | B5: ='🧬 DNA Loop Engine'!B28 -> 1.706 | C5: Heart Rate: | D5: ='🧬 DNA Loop Engine'!B27 -> 70 | E5: Reflex Gain: | F5: ='🧬 DNA Loop Engine'!B20 -> 1
A6: ⚡ ENERGY & ATP SYSTEM
A8: ⚡ A7DO ENERGY & ATP SYSTEM
A9: ⚙️ METABOLIC CONTROL PANEL
A10: Parameter | B10: Value | C10: Source
A11: Current Week: | B11: ='🧬 DNA Loop Engine'!B5 -> 125 | C11: DNA Engine
A12: Growth Factor: | B12: 1 | C12: DNA Engine
A13: Nutrient Flow: | B13: 1 | C13: DNA Engine
A14: O₂ Level: | B14: 0.21 | C14: DNA Engine
A15: Metabolic Rate Base: | B15: 1 | C15: kcal/kg/day
A16: ATP Production Rate: | B16: 0.8 | C16: ATP/sec
A17: Energy Reserve: | B17: 100 | C17: % capacity
A18: Cognitive Drain: | B18: 0.15 | C18: % per tick
A19: Motor Drain: | B19: 0.25 | C19: % per tick
A20: Basal Metabolic Rate: | B20: 70 | C20: kcal/day
A21: 🔋 ENERGY SOURCES
A22: Source | B22: Type | C22: Efficiency | D22: Availability | E22: ATP Yield | F22: Activation Wk | G22: Current Wk | H22: Status
A23: Glucose | B23: Carbohydrate | C23: 0.38 | D23: 0.9 | E23: 36 | F23: 8 | G23: ='🧬 DNA Loop Engine'!B5 -> 125 | H23: 🟢 Active
A24: Fatty Acids | B24: Lipid | C24: 0.4 | D24: 0.7 | E24: 129 | F24: 12 | G24: ='🧬 DNA Loop Engine'!B5 -> 125 | H24: 🟢 Active
A25: Amino Acids | B25: Protein | C25: 0.35 | D25: 0.5 | E25: 15 | F25: 20 | G25: ='🧬 DNA Loop Engine'!B5 -> 125 | H25: 🟢 Active
A26: Ketone Bodies | B26: Alternative | C26: 0.45 | D26: 0.3 | E26: 24 | F26: 28 | G26: ='🧬 DNA Loop Engine'!B5 -> 125 | H26: 🟢 Active
A27: Lactate | B27: Anaerobic | C27: 0.3 | D27: 0.8 | E27: 2 | F27: 12 | G27: ='🧬 DNA Loop Engine'!B5 -> 125 | H27: 🟢 Active
A28: Creatine Phosphate | B28: Immediate | C28: 0.95 | D28: 0.6 | E28: 1 | F28: 8 | G28: ='🧬 DNA Loop Engine'!B5 -> 125 | H28: 🟢 Active
A29: 🔌 ENERGY CONSUMERS
A30: System | B30: Priority | C30: Base Drain | D30: Activity Factor | E30: Current Drain | F30: % of Total | G30: Status
A31: Brain | B31: 1 | C31: 0.2 | D31: 1 | E31: 0.2 | F31: 0.24509803921568626 | G31: 🔴 High
A32: Heart | B32: 1 | C32: 0.1 | D32: 1 | E32: 0.1 | F32: 0.12254901960784313 | G32: 🟡 Normal
A33: Respiratory System | B33: 1 | C33: 0.05 | D33: 1 | E33: 0.05 | F33: 0.061274509803921566 | G33: 🟢 Low
A34: Digestive System | B34: 2 | C34: 0.15 | D34: 0.8 | E34: 0.12 | F34: 0.14705882352941174 | G34: 🟡 Normal
A35: Skeletal Muscle | B35: 3 | C35: 0.25 | D35: 0.5 | E35: 0.125 | F35: 0.1531862745098039 | G35: 🟡 Normal
A36: Immune System | B36: 2 | C36: 0.08 | D36: 0.7 | E36: 0.055999999999999994 | F36: 0.06862745098039215 | G36: 🟢 Low
A37: Growth & Repair | B37: 2 | C37: 0.12 | D37: 1 | E37: 0.12 | F37: 0.14705882352941174 | G37: 🟡 Normal
A38: Thermoregulation | B38: 2 | C38: 0.05 | D38: 0.9 | E38: 0.045000000000000005 | F38: 0.05514705882352942 | G38: 🟢 Low
A39: 📊 ENERGY BALANCE DASHBOARD
A40: Metric | B40: Value | C40: Status
A41: Total ATP Production: | B41: 44.27760000000001 | C41: 🔋 Normal
A42: Total Energy Drain: | B42: 0.8160000000000001
A43: Net Energy Balance: | B43: 43.461600000000004 | C43: ✅ Positive
A44: Energy Reserve: | B44: 98.15708168464415 | C44: 🟢 Full
A45: Cognitive Capacity: | B45: 0.85 | C45: 🧠 High
A46: Motor Capacity: | B46: 0.75 | C46: 💪 High
A47: Fatigue Index: | B47: 0.018429183153558456 | C47: 😊 Fresh
A48: Recovery Rate: | B48: 0.7852566534771532
A49: System Status: | B49: 🟢 SURPLUS
A51: 📊 ATP PRODUCTION CHART DATA — Michaelis-Menten Kinetics
A52: Glucose [mM] | B52: ATP Production Rate | C52: Normal Range | D52: Hypoglycaemia Threshold
A53: 0 | B53: 0 | C53: 50 | D53: 41.2
A54: 0.5 | B54: 9.1 | C54: 50 | D54: 41.2
A55: 1 | B55: 16.7 | C55: 50 | D55: 41.2
A56: 2 | B56: 28.6 | C56: 50 | D56: 41.2
A57: 3 | B57: 37.5 | C57: 50 | D57: 41.2
A58: 3.5 | B58: 41.2 | C58: 50 | D58: 41.2
A59: 4 | B59: 44.4 | C59: 50 | D59: 41.2
A60: 5 | B60: 50 | C60: 50 | D60: 41.2
A61: 6 | B61: 54.5 | C61: 50 | D61: 41.2
A62: 8 | B62: 61.5 | C62: 50 | D62: 41.2
A63: 10 | B63: 66.7 | C63: 50 | D63: 41.2
A64: 15 | B64: 75 | C64: 50 | D64: 41.2
A65: 20 | B65: 80 | C65: 50 | D65: 41.2

Sheet 📏 Full Growth System
A1: ⚡ LIVE TICK PANEL — All values auto-update from 🧬 DNA Loop Engine B4 (Current Tick)
A2: Current Tick: | B2: ='🧬 DNA Loop Engine'!B4 -> 10000 | C2: Current Week: | D2: ='🧬 DNA Loop Engine'!B5 -> 125 | E2: Birth Status: | F2: ='🧬 DNA Loop Engine'!B8 -> 🎉 BIRTH COMPLETE
A3: Life Stage: | B3: ='🧬 DNA Loop Engine'!B15 -> 🧒 Toddler | C3: Age: | D3: ='🧬 DNA Loop Engine'!B16 -> 19.6 months (1.63 yrs) | E3: DNA Phase: | F3: ='🧬 DNA Loop Engine'!B11 -> Toddler
A4: Growth Factor: | B4: ='🧬 DNA Loop Engine'!B18 -> 1 | C4: Neural Gain: | D4: ='🧬 DNA Loop Engine'!B19 -> 1 | E4: Cord Status: | F4: ='🧬 DNA Loop Engine'!B22 -> 🔌 SEVERED
A5: G_phys (height): | B5: ='🧬 DNA Loop Engine'!B28 -> 1.706 | C5: Heart Rate: | D5: ='🧬 DNA Loop Engine'!B27 -> 70 | E5: Reflex Gain: | F5: ='🧬 DNA Loop Engine'!B20 -> 1
A6: 📊 LIVE GROWTH VALUES — Auto-computed from Current Tick
A7: Height H(t) cm: | B7: =IF('🧬 DNA Loop Engine'!B5<=40,ROUND(50/(1+EXP(-0.2*('🧬 DNA Loop Engine'!B5-20))),1),IF('🧬 DNA Loop Engine'!B5<=92,ROUND(50+(75-50)*('🧬 DNA Loop Engine'!B5-40)/(92-40),1),IF('🧬 DNA Loop Engine'!B5<=156,ROUND(75+(95-75)*('🧬 DNA Loop Engine'!B5-92)/(156-92),1),IF('🧬 DNA Loop Engine'!B5<=624,ROUND(95+(145-95)*('🧬 DNA Loop Engine'!B5-156)/(624-156),1),IF('🧬 DNA Loop Engine'!B5<=936,ROUND(145+(175-145)*('🧬 DNA Loop Engine'!B5-624)/(936-624),1),ROUND(MIN(177,175+2*MIN(1,('🧬 DNA Loop Engine'!B5-936)/200)),1)))))) -> 85.3 | C7: Mass M(t) kg: | D7: =IF('🧬 DNA Loop Engine'!B5<=40,ROUND(3.5/(1+EXP(-0.2*('🧬 DNA Loop Engine'!B5-20))),2),IF('🧬 DNA Loop Engine'!B5<=92,ROUND(3.5+(10-3.5)*('🧬 DNA Loop Engine'!B5-40)/(92-40),2),IF('🧬 DNA Loop Engine'!B5<=156,ROUND(10+(14-10)*('🧬 DNA Loop Engine'!B5-92)/(156-92),2),IF('🧬 DNA Loop Engine'!B5<=624,ROUND(14+(40-14)*('🧬 DNA Loop Engine'!B5-156)/(624-156),2),IF('🧬 DNA Loop Engine'!B5<=936,ROUND(40+(65-40)*('🧬 DNA Loop Engine'!B5-624)/(936-624),2),ROUND(MIN(70,65+(70-65)*MIN(1,('🧬 DNA Loop Engine'!B5-936)/200)),2)))))) -> 12.06 | E7: G_phys: | F7: =ROUND(IF('🧬 DNA Loop Engine'!B5<=40,1/(1+EXP(-0.2*('🧬 DNA Loop Engine'!B5-20))),(IF('🧬 DNA Loop Engine'!B5<=40,ROUND(50/(1+EXP(-0.2*('🧬 DNA Loop Engine'!B5-20))),1),IF('🧬 DNA Loop Engine'!B5<=92,ROUND(50+(75-50)*('🧬 DNA Loop Engine'!B5-40)/(92-40),1),IF('🧬 DNA Loop Engine'!B5<=156,ROUND(75+(95-75)*('🧬 DNA Loop Engine'!B5-92)/(156-92),1),IF('🧬 DNA Loop Engine'!B5<=624,ROUND(95+(145-95)*('🧬 DNA Loop Engine'!B5-156)/(624-156),1),IF('🧬 DNA Loop Engine'!B5<=936,ROUND(145+(175-145)*('🧬 DNA Loop Engine'!B5-624)/(936-624),1),ROUND(MIN(177,175+2*MIN(1,('🧬 DNA Loop Engine'!B5-936)/200)),1)))))))/50),3) -> 1.706
A8: S_height: | B8: =ROUND((IF('🧬 DNA Loop Engine'!B5<=40,ROUND(50/(1+EXP(-0.2*('🧬 DNA Loop Engine'!B5-20))),1),IF('🧬 DNA Loop Engine'!B5<=92,ROUND(50+(75-50)*('🧬 DNA Loop Engine'!B5-40)/(92-40),1),IF('🧬 DNA Loop Engine'!B5<=156,ROUND(75+(95-75)*('🧬 DNA Loop Engine'!B5-92)/(156-92),1),IF('🧬 DNA Loop Engine'!B5<=624,ROUND(95+(145-95)*('🧬 DNA Loop Engine'!B5-156)/(624-156),1),IF('🧬 DNA Loop Engine'!B5<=936,ROUND(145+(175-145)*('🧬 DNA Loop Engine'!B5-624)/(936-624),1),ROUND(MIN(177,175+2*MIN(1,('🧬 DNA Loop Engine'!B5-936)/200)),1)))))))/50,3) -> 1.706 | C8: S_width: | D8: =ROUND(POWER((IF('🧬 DNA Loop Engine'!B5<=40,ROUND(3.5/(1+EXP(-0.2*('🧬 DNA Loop Engine'!B5-20))),2),IF('🧬 DNA Loop Engine'!B5<=92,ROUND(3.5+(10-3.5)*('🧬 DNA Loop Engine'!B5-40)/(92-40),2),IF('🧬 DNA Loop Engine'!B5<=156,ROUND(10+(14-10)*('🧬 DNA Loop Engine'!B5-92)/(156-92),2),IF('🧬 DNA Loop Engine'!B5<=624,ROUND(14+(40-14)*('🧬 DNA Loop Engine'!B5-156)/(624-156),2),IF('🧬 DNA Loop Engine'!B5<=936,ROUND(40+(65-40)*('🧬 DNA Loop Engine'!B5-624)/(936-624),2),ROUND(MIN(70,65+(70-65)*MIN(1,('🧬 DNA Loop Engine'!B5-936)/200)),2)))))))/3.5,1/3),3) -> 1.51 | E8: BMR (kcal/day): | F8: =ROUND(88.4+13.4*(IF('🧬 DNA Loop Engine'!B5<=40,ROUND(3.5/(1+EXP(-0.2*('🧬 DNA Loop Engine'!B5-20))),2),IF('🧬 DNA Loop Engine'!B5<=92,ROUND(3.5+(10-3.5)*('🧬 DNA Loop Engine'!B5-40)/(92-40),2),IF('🧬 DNA Loop Engine'!B5<=156,ROUND(10+(14-10)*('🧬 DNA Loop Engine'!B5-92)/(156-92),2),IF('🧬 DNA Loop Engine'!B5<=624,ROUND(14+(40-14)*('🧬 DNA Loop Engine'!B5-156)/(624-156),2),IF('🧬 DNA Loop Engine'!B5<=936,ROUND(40+(65-40)*('🧬 DNA Loop Engine'!B5-624)/(936-624),2),ROUND(MIN(70,65+(70-65)*MIN(1,('🧬 DNA Loop Engine'!B5-936)/200)),2)))))))+4.8*(IF('🧬 DNA Loop Engine'!B5<=40,ROUND(50/(1+EXP(-0.2*('🧬 DNA Loop Engine'!B5-20))),1),IF('🧬 DNA Loop Engine'!B5<=92,ROUND(50+(75-50)*('🧬 DNA Loop Engine'!B5-40)/(92-40),1),IF('🧬 DNA Loop Engine'!B5<=156,ROUND(75+(95-75)*('🧬 DNA Loop Engine'!B5-92)/(156-92),1),IF('🧬 DNA Loop Engine'!B5<=624,ROUND(95+(145-95)*('🧬 DNA Loop Engine'!B5-156)/(624-156),1),IF('🧬 DNA Loop Engine'!B5<=936,ROUND(145+(175-145)*('🧬 DNA Loop Engine'!B5-624)/(936-624),1),ROUND(MIN(177,175+2*MIN(1,('🧬 DNA Loop Engine'!B5-936)/200)),1)))))))-5.7*MAX(0.1,('🧬 DNA Loop Engine'!B5-40)/52),0) -> 650
A9: KEY DISTINCTION: The DNA Loop Engine 'Growth Factor' (0→1) tracks BIOLOGICAL ACTIVATION (organ formation, neural gain). This sheet tracks PHYSICAL SIZE (height, mass, 3D coordinates) which continues growing post-birth. Both are needed. Neither replaces the other.
A10: 📐 CORE EQUATIONS — Physical Growth Mathematical Framework
A11: # | B11: Equation Name | C11: Formula | D11: Variables | E11: Purpose | F11: Runtime Freq | G11: Notes
A12: 1 | B12: Unified Physical Growth Function | C12: G_phys(t) = G_prenatal(t) + δ_post·(1 − exp(−λ_age·t)) | D12: G_prenatal=prenatal growth [0,1]; δ_post=post-birth potential≈0.9; λ_age=decay constant | E12: Smooth continuous growth curve from conception to adulthood | F12: Every week | G12: Produces S-curve: rapid prenatal, rapid infant, slowing child, plateau adult
A13: 2 | B13: Prenatal Growth (Logistic) | C13: G_prenatal(t) = 1 / (1 + exp(−k·(t − t_mid))) | D13: k=growth rate≈0.2/wk; t_mid=midpoint≈20wk; t=current week | E13: Models embryonic and fetal growth as sigmoid activation | F13: Every week (Wk 0–40) | G13: k=0.2; t_mid=20; G_prenatal(40)≈1.0
A14: 3 | B14: Post-Birth Height Growth | C14: H(t) = H_birth + (H_adult − H_birth)·(1 − exp(−λ_H·(t−40))) | D14: H_birth=50cm; H_adult=175cm; λ_H=0.008/wk; t=weeks | E14: Continuous height growth from birth to adult stature | F14: Every week | G14: λ_H=0.008 gives ~90% adult height by Wk 624 (12yr)
A15: 4 | B15: Post-Birth Mass Growth | C15: M(t) = M_birth·exp(k_M·(t−40)) for t<156; then M_birth·(t/40)^0.4 for t≥156 | D15: M_birth=3.5kg; k_M=0.025/wk (infant); power law for child+ | E15: Rapid exponential infant growth transitioning to slower child growth | F15: Every week | G15: M(125wk)≈12kg; M(624wk)≈35kg; M(936wk)≈65kg
A16: 5 | B16: Mass Accumulation Integral | C16: M(t) = M_0 + ∫₀ᵗ ρ_growth(τ)dτ | D16: M_0=birth mass; ρ_growth=growth density rate (kg/week) | E16: Continuous mass accumulation from metabolic and nutritional input | F16: Every week | G16: ρ_growth varies by stage: infant=0.15kg/wk; child=0.05kg/wk; adult≈0
A17: 6 | B17: 3D Spatial Scaling (Body Coordinates) | C17: X(t) = X_0·S_width(t); Y(t) = Y_0·S_height(t); Z(t) = Z_0·S_depth(t) | D17: X_0,Y_0,Z_0=birth coordinates; S_width,S_height,S_depth=scale factors | E17: Scales all body-local XYZ coordinates with physical growth | F17: Every week | G17: S_height(t) = H(t)/H_birth; S_width(t) = (M(t)/M_birth)^(1/3)
A18: 7 | B18: Height Scale Factor | C18: S_height(t) = H(t) / H_birth = 1 + (H_adult/H_birth − 1)·(1 − exp(−λ_H·(t−40))) | D18: S_height=height scale [1.0 at birth → 3.5 at adult] | E18: Scales Y-axis body coordinates with height growth | F18: Every week | G18: S_height(125wk)=1.64; S_height(936wk)=3.5
A19: 8 | B19: Width/Depth Scale Factor | C19: S_width(t) = (M(t)/M_birth)^(1/3) | D19: Cube root of mass ratio — isometric scaling assumption | E19: Scales X and Z body coordinates with body width/depth | F19: Every week | G19: S_width(125wk)=1.51; S_width(936wk)=2.60
A20: 9 | B20: Metabolic Load Index | C20: MLI(t) = M(t)·BMR_factor(stage) / M_adult·BMR_adult | D20: BMR_factor=basal metabolic rate per kg by stage; M_adult=70kg | E20: Normalised metabolic demand — drives Energy/ATP system | F20: Every tick | G20: Infant BMR/kg ≈ 2× adult; MLI peaks in infancy
A21: 10 | B21: Hormonal Growth Activation | C21: H_GH(t) = H_GH_base·(1 + A_puberty·exp(−(t−t_puberty)²/2σ_pub²)) | D21: H_GH=growth hormone level; A_puberty=puberty amplitude; t_puberty=624wk; σ_pub=50wk | E21: Models growth hormone surge during puberty | F21: Every week | G21: Puberty growth spurt: +8–12cm/year at Wk 624–780
A22: 11 | B22: Organ Mass Scaling | C22: M_organ(t) = M_organ_adult·G_phys(t)^α_organ | D22: M_organ_adult=adult organ mass; α_organ=allometric exponent (0.7–1.0) | E22: Scales individual organ masses with overall physical growth | F22: Every week | G22: Brain: α=0.3 (grows faster early); Heart: α=0.9; Liver: α=0.85
A23: 12 | B23: Body Surface Area (BSA) | C23: BSA(t) = 0.007184·H(t)^0.725·M(t)^0.425 | D23: BSA in m²; H in cm; M in kg (Du Bois formula) | E23: Used for thermoregulation, drug dosing, metabolic calculations | F23: Every week | G23: BSA(birth)=0.21m²; BSA(adult)=1.73m²
A25: 📊 STAGE-BASED GROWTH TIMELINE — Average Human Reference Data
A26: All values are population averages. A7DO uses these as baseline; genetic inheritance (from Genetic Inheritance sheet) modifies final adult values. Current A7DO: Wk 125, ~19.6 months, Toddler stage.
A27: Stage | B27: Weeks | C27: Age Range | D27: G_phys Range | E27: Height (cm) | F27: Mass (kg) | G27: S_height | H27: S_width | I27: ρ_growth (kg/wk) | J27: BMR (kcal/day) | K27: Key Physical Changes | L27: Current A7DO?
A28: Prenatal | B28: 0–40 | C28: Conception→Birth | D28: 0.01→1.0 | E28: 0→50 | F28: 0→3.5 | G28: — | H28: — | I28: 0→0.09 | J28: ~300→500 | K28: Organogenesis, skeletal formation, neural tube, organ activation | L28: No (past)
A29: Infant | B29: 40–92 | C29: 0–12 months | D29: 1.0→1.25 | E29: 50→75 | F29: 3.5→10 | G29: 1.0→1.5 | H29: 1.0→1.42 | I29: 0.10→0.15 | J29: 500→700 | K29: Rapid growth, fontanelle closure, motor calibration, sensory development | L29: No (past)
A30: Toddler ★ | B30: 92–156 | C30: 1–3 years | D30: 1.25→1.5 | E30: 75→95 | F30: 10→14 | G30: 1.5→1.9 | H30: 1.42→1.59 | I30: 0.04→0.06 | J30: 700→900 | K30: Walking, coordination, muscle tone, language explosion | L30: ★ CURRENT (Wk 125, ~82cm, ~12kg)
A31: Child | B31: 156–624 | C31: 3–12 years | D31: 1.5→1.9 | E31: 95→145 | F31: 14→35 | G31: 1.9→2.9 | H31: 1.59→2.08 | I31: 0.03→0.05 | J31: 900→1400 | K31: Steady skeletal elongation, ossification, cognitive expansion | L31: No (future)
A32: Adolescent | B32: 624–936 | C32: 12–18 years | D32: 1.9→2.0 | E32: 145→175 | F32: 35→65 | G32: 2.9→3.5 | H32: 2.08→2.60 | I32: 0.05→0.08 | J32: 1400→2000 | K32: Puberty, hormonal surge, muscle mass, bone density peak | L32: No (future)
A33: Adult | B33: 936+ | C33: 18+ years | D33: 2.0 (stable) | E33: 175±10 | F33: 65±15 | G33: 3.5 | H33: 2.60 | I33: ≈0 | J33: 1700±300 | K33: Full physical maturity; maintenance mode; slow age-related changes | L33: No (future)
A35: 📈 COMPUTED GROWTH VALUES — Weekly Milestones (Key Weeks)
A36: Values computed from growth equations. H(t) = 50 + 125·(1−exp(−0.008·(t−40))) for t≥40. M(t) = 3.5·exp(0.025·(t−40)) for t<156; 3.5·(t/40)^0.4 for t≥156. S_height = H(t)/50. S_width = (M(t)/3.5)^(1/3).
A37: Week | B37: Age | C37: Stage | D37: G_phys | E37: Height (cm) | F37: Mass (kg) | G37: S_height | H37: S_width | I37: BSA (m²) | J37: BMR (kcal/day) | K37: Current A7DO?
A38: 0 | B38: Prenatal Wk 0 | C38: Prenatal | D38: 0.018 | E38: 0.9 | F38: 0.06 | G38: 0.018 | H38: 0.258 | I38: 0.002 | J38: 6
A39: 4 | B39: Prenatal Wk 4 | C39: Prenatal | D39: 0.039 | E39: 2.0 | F39: 0.14 | G39: 0.04 | H39: 0.342 | I39: 0.005 | J39: 14
A40: 8 | B40: Prenatal Wk 8 | C40: Prenatal | D40: 0.083 | E40: 4.2 | F40: 0.29 | G40: 0.084 | H40: 0.436 | I40: 0.012 | J40: 29
A41: 12 | B41: Prenatal Wk 12 | C41: Prenatal | D41: 0.168 | E41: 8.4 | F41: 0.59 | G41: 0.168 | H41: 0.552 | I41: 0.027 | J41: 59
A42: 20 | B42: Prenatal Wk 20 | C42: Prenatal | D42: 0.5 | E42: 25.0 | F42: 1.75 | G42: 0.5 | H42: 0.794 | I42: 0.094 | J42: 175
A43: 28 | B43: Prenatal Wk 28 | C43: Prenatal | D43: 0.832 | E43: 41.6 | F43: 2.91 | G43: 0.832 | H43: 0.94 | I43: 0.169 | J43: 291
A44: 36 | B44: Prenatal Wk 36 | C44: Prenatal | D44: 0.961 | E44: 48.0 | F44: 3.36 | G44: 0.96 | H44: 0.986 | I44: 0.199 | J44: 336
A45: 40 | B45: 0.0mo (0.0yr) | C45: Infant | D45: 0.982 | E45: 50.0 | F45: 3.5 | G45: 1.0 | H45: 1.0 | I45: 0.209 | J45: 375
A46: 45 | B46: 1.2mo (0.1yr) | C46: Infant | D46: 1.013 | E46: 54.9 | F46: 3.97 | G46: 1.098 | H46: 1.043 | I46: 0.235 | J46: 405
A47: 52 | B47: 2.8mo (0.2yr) | C47: Infant | D47: 1.032 | E47: 61.4 | F47: 4.72 | G47: 1.228 | H47: 1.105 | I47: 0.275 | J47: 445
A48: 65 | B48: 5.8mo (0.5yr) | C48: Infant | D48: 1.065 | E48: 72.7 | F48: 6.54 | G48: 1.454 | H48: 1.232 | I48: 0.357 | J48: 522
A49: 80 | B49: 9.2mo (0.8yr) | C49: Infant | D49: 1.102 | E49: 84.2 | F49: 9.51 | G49: 1.684 | H49: 1.395 | I49: 0.466 | J49: 616
... A51: 104 | B51: 14.8mo (1.2yr) | C51: Toddler | D51: 1.157 | E51: 100.1 | F51: 17.34 | G51: 2.002 | H51: 1.705 | I51: 0.681 | J51: 794
A52: 125 | B52: 19.6mo (1.6yr) | C52: Toddler | D52: 1.203 | E52: 111.7 | F52: 29.31 | G52: 2.234 | H52: 2.031 | I52: 0.922 | J52: 1008 | K52: ★ NOW
A53: 156 | B53: 2.2yr | C53: Child | D53: 1.265 | E53: 125.6 | F53: 6.03 | G53: 2.512 | H53: 1.199 | I53: 0.513 | J53: 759
A54: 208 | B54: 3.2yr | C54: Child | D54: 1.356 | E54: 142.4 | F54: 6.77 | G54: 2.848 | H54: 1.246 | I54: 0.59 | J54: 844
A55: 260 | B55: 4.2yr | C55: Child | D55: 1.435 | E55: 153.5 | F55: 7.4 | G55: 3.07 | H55: 1.283 | I55: 0.647 | J55: 900
A56: 312 | B56: 5.2yr | C56: Child | D56: 1.502 | E56: 160.8 | F56: 7.96 | G56: 3.216 | H56: 1.315 | I56: 0.69 | J56: 937
A57: 390 | B57: 6.7yr | C57: Child | D57: 1.585 | E57: 167.4 | F57: 8.7 | G57: 3.348 | H57: 1.355 | I57: 0.738 | J57: 970
A58: 468 | B58: 8.2yr | C58: Child | D58: 1.651 | E58: 170.9 | F58: 9.36 | G58: 3.418 | H58: 1.388 | I58: 0.773 | J58: 987
A59: 520 | B59: 9.2yr | C59: Child | D59: 1.687 | E59: 172.3 | F59: 9.76 | G59: 3.446 | H59: 1.408 | I59: 0.791 | J59: 994
A60: 624 | B60: 11.2yr | C60: Adolescent | D60: 1.744 | E60: 173.8 | F60: 10.5 | G60: 3.476 | H60: 1.442 | I60: 0.821 | J60: 999
A61: 700 | B61: 12.7yr | C61: Adolescent | D61: 1.776 | E61: 174.4 | F61: 11.0 | G61: 3.488 | H61: 1.465 | I61: 0.839 | J61: 1001
A62: 780 | B62: 14.2yr | C62: Adolescent | D62: 1.802 | E62: 174.7 | F62: 11.48 | G62: 3.494 | H62: 1.486 | I62: 0.856 | J62: 1000
A63: 850 | B63: 15.6yr | C63: Adolescent | D63: 1.821 | E63: 174.8 | F63: 11.89 | G63: 3.496 | H63: 1.503 | I63: 0.869 | J63: 998
A64: 936 | B64: 17.2yr | C64: Adult | D64: 1.839 | E64: 174.9 | F64: 12.35 | G64: 3.498 | H64: 1.522 | I64: 0.884 | J64: 995
... A67: 1200 | B67: 22.3yr | C67: Adult | D67: 1.872 | E67: 175.0 | F67: 13.64 | G67: 3.5 | H67: 1.574 | I67: 0.922 | J67: 984
A69: 📐 3D SPATIAL SCALING — Body Coordinate Updates by Stage
A70: Body-local XYZ coordinates (from Spatial Coordinates sheet) must be multiplied by scale factors at each developmental stage. Point 0 = Pelvis Centre remains fixed. Example: Frontal Bone at birth Y=0.25m → Wk 125 Y=0.25×1.64=0.41m → Adult Y=0.25×3.5=0.875m
A71: Stage | B71: Weeks | C71: S_height (Y-scale) | D71: S_width (X,Z-scale) | E71: Example: Frontal Bone Y | F71: Example: Femur Y | G71: Example: Hand X | H71: Body Height (m) | I71: Body Width (m) | J71: Notes
A72: Prenatal (birth) | B72: Wk 40 | C72: 1.00 | D72: 1.00 | E72: 0.25m | F72: −0.08m | G72: 0.12m | H72: 0.50m | I72: 0.20m | J72: Reference state — all coordinates at birth scale
A73: Infant | B73: Wk 52 | C73: 1.30 | D73: 1.14 | E73: 0.33m | F73: −0.10m | G73: 0.14m | H73: 0.65m | I73: 0.23m | J73: Rapid growth; fontanelles still open
A74: Toddler ★ | B74: Wk 125 | C74: 1.64 | D74: 1.51 | E74: 0.41m | F74: −0.13m | G74: 0.18m | H74: 0.82m | I74: 0.30m | J74: ★ CURRENT A7DO — all coords × S_height/S_width
A75: Early Child | B75: Wk 208 | C75: 1.90 | D75: 1.72 | E75: 0.48m | F75: −0.15m | G75: 0.21m | H75: 0.95m | I75: 0.34m | J75: Steady growth; ossification progressing
A76: Mid Child | B76: Wk 390 | C76: 2.30 | D76: 2.00 | E76: 0.58m | F76: −0.18m | G76: 0.25m | H76: 1.15m | I76: 0.40m | J76: Skeletal elongation; muscle mass building
A77: Pre-Adolescent | B77: Wk 624 | C77: 2.90 | D77: 2.08 | E77: 0.73m | F77: −0.23m | G77: 0.32m | H77: 1.45m | I77: 0.42m | J77: Pre-puberty; growth plates still open
A78: Adolescent | B78: Wk 780 | C78: 3.30 | D78: 2.40 | E78: 0.83m | F78: −0.26m | G78: 0.36m | H78: 1.65m | I78: 0.48m | J78: Puberty growth spurt; hormonal surge
A79: Adult | B79: Wk 936+ | C79: 3.50 | D79: 2.60 | E79: 0.88m | F79: −0.28m | G79: 0.39m | H79: 1.75m | I79: 0.52m | J79: Full adult stature; growth plates fused
A81: 🔗 INTEGRATION MAP — Growth System → All A7DO Subsystems
A82: Subsystem | B82: Integration Type | C82: Growth System Provides | D82: Formula Link | E82: Update Frequency | F82: v1.0 Sheet | G82: Action Required
A83: DNA Loop Engine | B83: Input | C83: Current week t → G_phys(t) lookup | D83: G_phys(t) from this sheet's computed table | E83: Every week | F83: 🧬 DNA Loop Engine | G83: Add G_phys column to tick table; replace static Growth Factor post-birth
A84: Anatomy Growth Engine | B84: Bidirectional | C84: Scale factors S_height, S_width for all bone/organ coords | D84: X(t)=X_0·S_width; Y(t)=Y_0·S_height; Z(t)=Z_0·S_width | E84: Every week | F84: 📈 Growth Timeline | G84: Add S_height, S_width columns; recompute Dynamic XYZ
A85: Spatial Coordinates | B85: Output | C85: Updated body-local XYZ at current developmental stage | D85: World_Z = Ground_Z + Local_Y·H(t) | E85: Every week | F85: 📐 Spatial Coordinates | G85: Update Body Scale by Age table with H(t) and M(t) from this sheet
A86: Energy / ATP | B86: Output | C86: Metabolic Load Index MLI(t) and BMR(t) | D86: BMR(t) = 88.4 + 13.4·M(t) + 4.8·H(t) − 5.7·Age_yr | E86: Every tick | F86: ⚡ Energy & Metabolism | G86: Replace static BMR with dynamic BMR(t) from growth equations
A87: Body Systems | B87: Output | C87: Organ mass scaling M_organ(t) = M_adult·G_phys^α | D87: M_organ(t) = M_organ_adult·G_phys(t)^α_organ | E87: Every week | F87: 🫀 Body Systems | G87: Add organ mass column using allometric scaling
A88: Proprioception (P1) | B88: Output | C88: Body schema scale factors for FK computation | D88: x(t) = FK(θ(t))·S_height(t) | E88: Every tick | F88: 🦴 Proprioception (P1) | G88: Pass S_height, S_width to FK solver for accurate body schema
A89: Motor Planning (P6) | B89: Output | C89: Limb lengths for IK solver | D89: Limb_length(t) = Limb_birth·S_height(t) | E89: Every tick | F89: 🦾 Motor Planning (P6) | G89: Update IK Jacobian with current limb lengths from growth
A90: NPC Engine | B90: Output | C90: NPC physical dimensions by age stage | D90: H_NPC = H_birth·S_height(age_stage); M_NPC = M_birth·S_width³ | E90: On NPC age update | F90: 👥 NPC Engine | G90: Apply growth equations to each NPC based on their age
A91: Prenatal & Genesis | B91: Input | C91: Genetic modifiers for adult height/mass | D91: H_adult = 175·(1 + genetic_height_modifier); M_adult = 70·(1 + genetic_mass_modifier) | E91: Once at birth | F91: 🧬 Prenatal & Genesis | G91: Read genetic inheritance values to personalise growth curves
A92: Mathematical Framework | B92: Reference | C92: Growth equations for formal specification | D92: All equations in Section 1 of this sheet | E92: Static reference | F92: 🧮 Mathematical Framework | G92: Add G_phys, H(t), M(t) equations to Mathematical Framework sheet
A94: ⚙️ PARAMETER REFERENCE — Full Growth System
A95: Parameter | B95: Symbol | C95: Value | D95: Units | E95: Description | F95: Source
A96: Post-birth growth potential | B96: δ_post | C96: 0.9 | D96: — | E96: Max additional growth factor post-birth | F96: Calibrated to H_adult/H_birth ratio
A97: Age decay constant | B97: λ_age | C97: 0.003 | D97: /wk | E97: Controls growth slowdown toward adulthood | F97: Fit to WHO growth charts
A98: Prenatal growth rate | B98: k | C98: 0.2 | D98: /wk | E98: Logistic growth rate during gestation | F98: Embryological data
A99: Prenatal midpoint | B99: t_mid | C99: 20 | D99: weeks | E99: Inflection point of prenatal growth | F99: Embryological data
A100: Birth height | B100: H_birth | C100: 50 | D100: cm | E100: Average newborn length | F100: WHO reference
A101: Adult height | B101: H_adult | C101: 175 | D101: cm | E101: Average adult height (male baseline) | F101: WHO reference; genetic modifier applies
A102: Height growth constant | B102: λ_H | C102: 0.008 | D102: /wk | E102: Post-birth height growth rate | F102: Fit to WHO growth charts
A103: Birth mass | B103: M_birth | C103: 3.5 | D103: kg | E103: Average birth weight | F103: WHO reference
A104: Adult mass | B104: M_adult | C104: 70 | D104: kg | E104: Average adult mass (male baseline) | F104: WHO reference; genetic modifier applies
A105: Infant mass growth rate | B105: k_M | C105: 0.025 | D105: /wk | E105: Exponential mass growth rate (infant) | F105: WHO growth charts
A106: Infant growth density | B106: ρ_infant | C106: 0.12 | D106: kg/wk | E106: Average mass gain per week (0–12mo) | F106: WHO reference
... A118: Current A7DO BMR(125) | B118: BMR_now | C118: ~650 | D118: kcal/day | E118: Basal metabolic rate at Wk 125 | F118: Mifflin-St Jeor adapted for toddler
A120: ⚠️ KEY CLARIFICATION — DNA Growth Factor vs Physical Growth
...

Sheet 🧠 Mind & Cognition
A1: ⚡ LIVE TICK PANEL — All values auto-update from 🧬 DNA Loop Engine B4 (Current Tick)
A2: Current Tick: | B2: ='🧬 DNA Loop Engine'!B4 -> 10000 | C2: Current Week: | D2: ='🧬 DNA Loop Engine'!B5 -> 125 | E2: Birth Status: | F2: ='🧬 DNA Loop Engine'!B8 -> 🎉 BIRTH COMPLETE
A3: Life Stage: | B3: ='🧬 DNA Loop Engine'!B15 -> 🧒 Toddler | C3: Age: | D3: ='🧬 DNA Loop Engine'!B16 -> 19.6 months (1.63 yrs) | E3: DNA Phase: | F3: ='🧬 DNA Loop Engine'!B11 -> Toddler
A4: Growth Factor: | B4: ='🧬 DNA Loop Engine'!B18 -> 1 | C4: Neural Gain: | D4: ='🧬 DNA Loop Engine'!B19 -> 1 | E4: Cord Status: | F4: ='🧬 DNA Loop Engine'!B22 -> 🔌 SEVERED
A5: G_phys (height): | B5: ='🧬 DNA Loop Engine'!B28 -> 1.706 | C5: Heart Rate: | D5: ='🧬 DNA Loop Engine'!B27 -> 70 | E5: Reflex Gain: | F5: ='🧬 DNA Loop Engine'!B20 -> 1
A6: 🧠 MIND & COGNITION — Language · Memory · Emotion · Attention · Consciousness · Sleep
A8: 🗣️ COGNITION & LANGUAGE
A9: 🧠 A7DO COGNITION & LANGUAGE INTEGRATION MATRIX
A10: ⚙️ CONTROL PANEL | F10: 🎯 COGNITIVE METRICS
A11: Parameter | B11: Value | C11: Unit | D11: Notes | F11: Metric | G11: Value | H11: Status
A12: Current Week | B12: ='🧬 DNA Loop Engine'!B5 -> 125 | C12: weeks | D12: From DNA Engine | F12: Cognition % | G12: 1 | H12: ✅ Mature
A13: Post-Birth Weeks | B13: =MAX(0,'🧬 DNA Loop Engine'!B5-40) -> 85 | C13: weeks | D13: Development time | F13: Language % | G13: 1 | H13: ✅ Fluent
A14: Age in Years | B14: 1.6 | C14: years | D14: Child's age | F14: Expression Rate | G14: 1 | H14: ✅ Articulate
A15: Neural Gain | B15: 1 | C15: % | D15: From DNA Engine | F15: Comprehension Rate | G15: 1 | H15: ✅ Excellent
A16: Sensory Feedback | B16: 1 | C16: % | D16: Average sensory maturity | F16: Memory Capacity | G16: 100 | H16: ✅ Full
A17: Development Phase | B17: 🧒 Toddler | D17: Auto-detected | F17: Reasoning Index | G17: 1 | H17: ✅ Abstract
A18: 📋 COGNITION & LANGUAGE MATRIX
A19: Name | B19: Subsystem | C19: Activation Week | D19: Full Maturity Week | E19: Function | F19: Input Source | G19: Output Target | H19: Learning Type | I19: Domain | J19: Current Week | K19: Status | L19: Maturity %
A20: Prefrontal Cortex | B20: Cognitive | C20: 40 | D20: 70 | E20: Decision Making | F20: Sensory Feedback | G20: Motor Cortex | H20: Reasoning | I20: Cognition | J20: ='🧬 DNA Loop Engine'!B5 -> 125 | K20: ✅ Mature | L20: 1
A21: Hippocampus | B21: Cognitive | C21: 36 | D21: 60 | E21: Memory Formation | F21: Sensory Feedback | G21: Cerebrum | H21: Declarative Learning | I21: Cognition | J21: ='🧬 DNA Loop Engine'!B5 -> 125 | K21: ✅ Mature | L21: 1
A22: Amygdala | B22: Cognitive | C22: 36 | D22: 60 | E22: Emotion Association | F22: Neurochemical Feedback | G22: Limbic System | H22: Associative Learning | I22: Cognition | J22: ='🧬 DNA Loop Engine'!B5 -> 125 | K22: ✅ Mature | L22: 1
A23: Limbic System | B23: Cognitive | C23: 36 | D23: 70 | E23: Emotion Regulation | F23: Neurochemical Feedback | G23: Prefrontal Cortex | H23: Associative Learning | I23: Cognition | J23: ='🧬 DNA Loop Engine'!B5 -> 125 | K23: ✅ Mature | L23: 1
A24: Cerebrum Integration | B24: Cognitive | C24: 40 | D24: 70 | E24: Concept Formation | F24: Multisensory Feedback | G24: All Cortices | H24: Abstract Learning | I24: Cognition | J24: ='🧬 DNA Loop Engine'!B5 -> 125 | K24: ✅ Mature | L24: 1
A25: Broca's Area | B25: Language | C25: 40 | D25: 60 | E25: Speech Production | F25: Auditory Feedback | G25: Motor Cortex | H25: Symbolic Learning | I25: Communication | J25: ='🧬 DNA Loop Engine'!B5 -> 125 | K25: ✅ Mature | L25: 1
A26: Wernicke's Area | B26: Language | C26: 40 | D26: 60 | E26: Comprehension | F26: Auditory Feedback | G26: Cerebrum | H26: Semantic Learning | I26: Communication | J26: ='🧬 DNA Loop Engine'!B5 -> 125 | K26: ✅ Mature | L26: 1
A27: Auditory Cortex | B27: Sensory | C27: 36 | D27: 60 | E27: Sound Processing | F27: Cochlear Cells | G27: Wernicke's Area | H27: Pattern Learning | I27: Sensing | J27: ='🧬 DNA Loop Engine'!B5 -> 125 | K27: ✅ Mature | L27: 1
A28: Visual Cortex | B28: Sensory | C28: 36 | D28: 60 | E28: Symbol Recognition | F28: Photoreceptors | G28: Broca's Area | H28: Pattern Learning | I28: Sensing | J28: ='🧬 DNA Loop Engine'!B5 -> 125 | K28: ✅ Mature | L28: 1
A29: Motor Cortex (Laryngeal) | B29: Motor | C29: 40 | D29: 60 | E29: Vocal Articulation | F29: Proprioceptors | G29: Broca's Area | H29: Motor Learning | I29: Embodiment | J29: ='🧬 DNA Loop Engine'!B5 -> 125 | K29: ✅ Mature | L29: 1
A30: Cerebellum (Speech) | B30: Motor | C30: 36 | D30: 60 | E30: Speech Coordination | F30: Joint Receptors | G30: Motor Cortex | H30: Adaptive Learning | I30: Embodiment | J30: 125 | K30: ✅ Mature | L30: 1
A31: 🗣️ LANGUAGE MILESTONES | H31: 🔗 NEURAL PATHWAY CONNECTIONS
A32: Age (Months) | B32: Milestone | C32: Description | D32: Achieved Week | E32: Current Week | F32: Status | H32: Pathway | I32: Source | J32: Target | K32: Signal Type | L32: Status
A33: 0 | B33: Crying | C33: Basic vocalization | D33: 40 | E33: 125 | F33: ✅ Achieved | H33: Sensory → Cognition | I33: Sensory Cortices | J33: Hippocampus | K33: Perception | L33: 🟢 FORMING
A34: 2 | B34: Cooing | C34: Vowel-like sounds | D34: 48 | E34: 125 | F34: ✅ Achieved | H34: Memory → Reasoning | I34: Hippocampus | J34: Prefrontal Cortex | K34: Recall | L34: 🟢 ACTIVE
A35: 4 | B35: Babbling | C35: Consonant-vowel combos (ba-ba) | D35: 56 | E35: 125 | F35: ✅ Achieved | H35: Emotion → Decision | I35: Amygdala | J35: Prefrontal Cortex | K35: Valence | L35: 🟢 ACTIVE
A36: 6 | B36: Varied Babbling | C36: Different sounds and tones | D36: 64 | E36: 125 | F36: ✅ Achieved | H36: Auditory → Language | I36: Auditory Cortex | J36: Wernicke's Area | K36: Phonemes | L36: 🟢 ACTIVE
A37: 9 | B37: Gestures | C37: Pointing, waving | D37: 76 | E37: 125 | F37: ✅ Achieved | H37: Comprehension → Production | I37: Wernicke's Area | J37: Broca's Area | K37: Semantic | L37: 🟢 ACTIVE
A38: 12 | B38: First Words | C38: Mama, Dada, simple nouns | D38: 92 | E38: 125 | F38: ✅ Achieved | H38: Production → Motor | I38: Broca's Area | J38: Motor Cortex | K38: Syntax | L38: 🟢 ACTIVE
A39: 18 | B39: Two-Word Phrases | C39: "More milk", "Daddy go" | D39: 118 | E39: 125 | F39: ✅ Achieved | H39: Visual → Reading | I39: Visual Cortex | J39: Broca's Area | K39: Graphemes | L39: 🟢 ACTIVE
A40: 24 | B40: Sentences | C40: 3-4 word sentences | D40: 144 | E40: 125 | F40: ⏳ Upcoming | H40: Cerebellum → Speech | I40: Cerebellum | J40: Motor Cortex | K40: Coordination | L40: 🟢 ACTIVE
A41: 36 | B41: Complex Speech | C41: Full sentences, questions | D41: 196 | E41: 125 | F41: ⏳ Upcoming
A42: 48 | B42: Storytelling | C42: Narratives, past tense | D42: 248 | E42: 125 | F42: ⏳ Upcoming
A43: 60 | B43: Reading Ready | C43: Phonemic awareness | D43: 300 | E43: 125 | F43: ⏳ Upcoming
A44: 🧠 COGNITIVE MILESTONES | H44: 📅 DEVELOPMENT TIMELINE PREVIEW
A45: Age (Months) | B45: Milestone | C45: Description | D45: Achieved Week | E45: Current Week | F45: Status | H45: Week | I45: Age | J45: Cognitive Ability | K45: Language Ability | L45: Status
A46: 0 | B46: Reflexive Responses | C46: Automatic reactions to stimuli | D46: 40 | E46: 125 | F46: ✅ Achieved | H46: 36 | I46: Pre-Birth | J46: Hippocampus/Amygdala Activate | K46: Auditory/Visual Cortex Forming | L46: ✅ Reached
A47: 3 | B47: Object Tracking | C47: Follows moving objects with eyes | D47: 52 | E47: 125 | F47: ✅ Achieved | H47: 40 | I47: Birth | J47: Prefrontal/Limbic Begin | K47: Broca/Wernicke Activate | L47: ✅ Reached
A48: 6 | B48: Object Permanence | C48: Knows objects exist when hidden | D48: 64 | E48: 125 | F48: ✅ Achieved | H48: 52 | I48: 3 months | J48: Object Tracking | K48: Cooing | L48: ✅ Reached
A49: 9 | B49: Cause & Effect | C49: Understands actions have results | D49: 76 | E49: 125 | F49: ✅ Achieved | H49: 64 | I49: 6 months | J49: Object Permanence | K49: Babbling | L49: ✅ Reached
A50: 12 | B50: Problem Solving | C50: Simple trial and error | D50: 92 | E50: 125 | F50: ✅ Achieved | H50: 92 | I50: 1 year | J50: Problem Solving | K50: First Words | L50: ✅ Reached
A51: 18 | B51: Symbolic Play | C51: Pretend play begins | D51: 118 | E51: 125 | F51: ✅ Achieved | H51: 144 | I51: 2 years | J51: Categorization | K51: Sentences | L51: ⏳ Future
A52: 24 | B52: Categorization | C52: Groups similar objects | D52: 144 | E52: 125 | F52: ⏳ Upcoming | H52: 196 | I52: 3 years | J52: Theory of Mind | K52: Complex Speech | L52: ⏳ Future
A53: 36 | B53: Theory of Mind | C53: Understands others have thoughts | D53: 196 | E53: 125 | F53: ⏳ Upcoming | H53: 300 | I53: 5 years | J53: Abstract Concepts | K53: Reading Ready | L53: ⏳ Future
A54: 48 | B54: Logical Reasoning | C54: If-then thinking | D54: 248 | E54: 125 | F54: ⏳ Upcoming | H54: 352 | I54: 6 years | J54: Metacognition | K54: Full Literacy | L54: ⏳ Future
A55: 60 | B55: Abstract Concepts | C55: Time, numbers, letters | D55: 300 | E55: 125 | F55: ⏳ Upcoming
A56: 72 | B56: Metacognition | C56: Thinking about thinking | D56: 352 | E56: 125 | F56: ⏳ Upcoming
A57: 📊 COGNITION & LANGUAGE SUMMARY
A58: Metric | B58: Value | D58: 🔗 SYSTEM CONNECTIONS
A59: Total Components | B59: 11 | D59: Linked System | E59: Reference | F59: Purpose
A60: Cognitive Subsystem | B60: 5 | D60: DNA Loop Engine | E60: Week Sync | F60: Timeline driver
A61: Language Subsystem | B61: 2 | D61: Sensory Integration | E61: Sensory Feedback | F61: Perception input
A62: Sensory/Motor Support | B62: 4 | D62: Neural Control | E62: Neural Gain | F62: Processing power
A63: Overall Maturity | B63: 1 | D63: Child Development | E63: Cognitive Index | F63: Development tracking
A64: Language Milestones Achieved | B64: 7 of 11 | D64: Infant Development | E64: Milestones | F64: Early development
A65: Cognitive Milestones Achieved | B65: 6 of 11 | D65: Child Anatomy Engine | E65: Brain Size | F65: Physical growth
A66: Active Neural Pathways | B66: 8 of 8 | D66: Respiratory Control | E66: O₂ Supply | F66: Metabolic support
A67: Mind-Language Integration | B67: 1 | D67: Circulatory System | E67: Blood Flow | F67: Nutrient delivery
A68: Communication Readiness | B68: ✅ Ready
A71: 💾 MEMORY SYSTEM
A72: 🧠 A7DO MEMORY SYSTEM
A73: ⚙️ CONTROL PANEL
A74: Parameter | B74: 125 | C74: Source
A75: Current Week: | B75: 125 | C75: DNA Engine
A76: Neural Gain: | B76: 1 | C76: DNA Engine
A77: Learning Rate: | B77: 0.1 | C77: Base parameter
A78: Memory Decay: | B78: 0.05 | C78: Per tick decay
A79: Consolidation Rate: | B79: 0.02 | C79: STM→LTM transfer
A80: 📋 MEMORY TYPES MATRIX
A81: Name | B81: Type | C81: Capacity | D81: Duration | E81: Activation Wk | F81: Maturity Wk | G81: Current Wk | H81: Maturity % | I81: Status | J81: Encoding | K81: Retrieval | L81: Domain
A82: Sensory Memory | B82: Ultra-Short | C82: Unlimited | D82: 250ms | E82: 20 | F82: 36 | G82: 125 | H82: 1 | I82: ✅ Mature | J82: Automatic | K82: Instant | L82: Perception
A83: Iconic Memory | B83: Visual Buffer | C83: 12 items | D83: 500ms | E83: 20 | F83: 36 | G83: 125 | H83: 1 | I83: ✅ Mature | J83: Visual | K83: Instant | L83: Perception
A84: Echoic Memory | B84: Auditory Buffer | C84: 4 items | D84: 3-4 sec | E84: 20 | F84: 36 | G84: 125 | H84: 1 | I84: ✅ Mature | J84: Auditory | K84: Instant | L84: Perception
A85: Working Memory | B85: Short-Term | C85: 7±2 items | D85: 20-30 sec | E85: 36 | F85: 60 | G85: 125 | H85: 1 | I85: ✅ Mature | J85: Rehearsal | K85: Fast | L85: Cognition
A86: Phonological Loop | B86: Verbal STM | C86: 2 sec audio | D86: 2 sec | E86: 36 | F86: 60 | G86: 125 | H86: 1 | I86: ✅ Mature | J86: Subvocal | K86: Fast | L86: Language
A87: Visuospatial Sketchpad | B87: Visual STM | C87: 4 objects | D87: 2 sec | E87: 36 | F87: 60 | G87: 125 | H87: 1 | I87: ✅ Mature | J87: Visual | K87: Fast | L87: Spatial
A88: Central Executive | B88: Control | C88: Limited | D88: Active | E88: 40 | F88: 70 | G88: 125 | H88: 1 | I88: ✅ Mature | J88: Attentional | K88: Variable | L88: Control
A89: Episodic Buffer | B89: Integration | C89: 4 chunks | D89: Minutes | E89: 40 | F89: 70 | G89: 125 | H89: 1 | I89: ✅ Mature | J89: Binding | K89: Medium | L89: Integration
A90: Episodic Memory | B90: Long-Term | C90: Unlimited | D90: Lifetime | E90: 36 | F90: 70 | G90: 125 | H90: 1 | I90: ✅ Mature | J90: Contextual | K90: Slow | L90: Autobiographical
A91: Semantic Memory | B91: Long-Term | C91: Unlimited | D91: Lifetime | E91: 36 | F91: 70 | G91: 125 | H91: 1 | I91: ✅ Mature | J91: Conceptual | K91: Medium | L91: Knowledge
A92: Procedural Memory | B92: Long-Term | C92: Unlimited | D92: Lifetime | E92: 36 | F92: 70 | G92: 125 | H92: 1 | I92: ✅ Mature | J92: Motor | K92: Automatic | L92: Skills
A93: Prospective Memory | B93: Future-Oriented | C93: Limited | D93: Variable | E93: 40 | F93: 70 | G93: 125 | H93: 1 | I93: ✅ Mature | J93: Intentional | K93: Cued | L93: Planning
A94: 📊 MEMORY DASHBOARD
A95: Metric | B95: Value | C95: Status
A96: Total Memory Types: | B96: 12
A97: Mature Systems: | B97: 12
A98: Developing Systems: | B98: 0
A99: Dormant Systems: | B99: 0
A100: Average Maturity: | B100: 1 | C100: 🟢 STRONG
A101: Memory Capacity Index: | B101: 1
A102: Overall Status: | B102: 🟢 HIGH
A103: 🔄 MEMORY PROCESSES
...

Sheet 🗣️ Language Grounding
A1: 🗣️ A7DO LANGUAGE GROUNDING — Word-Percept-Action Binding
A2: Language without grounding is symbol manipulation. Grounding binds words to sensory, motor, and emotional experience.
A3: Source: Language Grounding sheet (v18) · engines_extended.py EQ_LANG_12 · Mathematical Framework §3.4
A5: A. CORE GROUNDING EQUATIONS
A6: Equation | B6: Formula | C6: Variables | D6: Notes
A7: Grounding function | B7: G(word) = Σ_m w_m·f_m(percept) | C7: w_m=modality weight, f_m=feature extractor | D7: Multimodal binding across vision/touch/sound/motor
A8: Semantic similarity | B8: sim(w1,w2) = G(w1)·G(w2) / (|G(w1)|·|G(w2)|) | C8: Cosine similarity in grounding space | D8: Enables analogical reasoning
A9: Word learning rate | B9: λ(t) = λ_max·σ(μ·(t−t_onset)) | C9: λ_max=0.05, t_onset=40wk | D9: Critical period gating
A10: Vocab logistic | B10: V(t) = V_max/(1+exp(−k·(t−t_mid))) | C10: V_max=50000, k=0.05/wk, t_mid=156wk | D10: Verified in runtime demo
A11: Object-word binding | B11: B(word,obj) = α·visual + β·motor + γ·emotion | C11: α=0.4, β=0.3, γ=0.3 | D11: Binds to ObjectPermanenceState
A12: Action-verb binding | B12: V_verb(action) = Σ_t motor_state(t)·reward(t) | C12: Temporal integration over action sequence | D12: Requires motor planning stage ≥2
A14: B. WORD-OBJECT BINDING TABLE (seed vocabulary — grounded to world objects)
A15: Word ID | B15: Word | C15: POS | D15: Bound Object ID | E15: Visual Weight | F15: Motor Weight | G15: Emotion Weight | H15: Grounding Status
A16: LANG_MAMA | B16: mama | C16: Noun | D16: lorraine | E16: 0.4 | F16: 0.2 | G16: 0.9 | H16: ✅ Grounded
A17: LANG_UP | B17: up | C17: Verb | D17: reach_action | E17: 0.3 | F17: 0.6 | G17: 0.4 | H17: ✅ Grounded
A18: LANG_NO | B18: no | C18: Interjection | D18: punishment_signal | E18: 0.1 | F18: 0.2 | G18: 0.8 | H18: ✅ Grounded
A19: LANG_MORE | B19: more | C19: Determiner | D19: food_object | E19: 0.3 | F19: 0.4 | G19: 0.6 | H19: ✅ Grounded
A20: LANG_BALL | B20: ball | C20: Noun | D20: toy_ball | E20: 0.7 | F20: 0.5 | G20: 0.3 | H20: 🟡 Partial
A21: LANG_EAT | B21: eat | C21: Verb | D21: food_action | E21: 0.3 | F21: 0.7 | G21: 0.5 | H21: 🟡 Partial
A22: LANG_HOT | B22: hot | C22: Adjective | D22: temperature_signal | E22: 0.2 | F22: 0.1 | G22: 0.7 | H22: 🟡 Partial
A23: LANG_DOG | B23: dog | C23: Noun | D23: animal_category | E23: 0.8 | F23: 0.2 | G23: 0.4 | H23: 🔴 Ungrounded
A24: LANG_LEARN | B24: learn | C24: Verb | D24: meta_cognition | E24: 0.1 | F24: 0.3 | G24: 0.5 | H24: 🔴 Ungrounded
A25: LANG_FRIEND | B25: friend | C25: Noun | D25: social_bond | E25: 0.4 | F25: 0.2 | G25: 0.8 | H25: 🔴 Ungrounded
A27: C. DEVELOPMENTAL GROUNDING STAGES
A28: Stage | B28: Week Range | C28: Grounding Type | D28: Example | E28: Runtime Hook
A29: 1 | B29: 40–80 | C29: Prosodic/emotional | D29: mama, no, up | E29: emotion.H + attachment_drive
A30: 2 | B30: 80–156 | C30: Object-word binding | D30: ball, cup, dog | E30: objects.objects registry
A31: 3 | B31: 156–260 | C31: Action-verb binding | D31: eat, throw, walk | E31: proprio.motor_stage + drives
A32: 4 | B32: 260–624 | C32: Relational/spatial | D32: in, on, near, behind | E32: scene_graph.scene_relations
A33: 5 | B33: 624+ | C33: Abstract/social | D33: justice, love, believe | E33: consciousness.C + ToM
A35: D. INTEGRATION POINTS
A36: System | B36: Direction | C36: Data Shared | D36: Effect | E36: Status
A37: Object Permanence | B37: Bidirectional | C37: Object IDs → word labels | D37: Nouns grounded to persistent objects | E37: 🟡 Partial
A38: Sensory Integration | B38: Input | C38: Visual/touch/sound features | D38: Perceptual grounding of adjectives | E38: 🟡 Partial
A39: Motor Planning | B39: Prerequisite | C39: Action representations | D39: Grounded verbs improve motor planning | E39: 🟡 Motor partial
A40: Episodic Memory | B40: Bidirectional | C40: Event context for word-event links | D40: Words trigger episodic recall | E40: 🟡 Memory built
A41: NPC Engine | B41: Output | C41: NPC names and social roles | D41: Grounded social vocabulary | E41: ✅ NPC exists
A42: Value System | B42: Bidirectional | C42: Object valence for importance weighting | D42: High-valence words grounded first | E42: 🟡 Drives built
A43: DNA Loop Engine | B43: Input | C43: Current week for developmental gating | D43: Stage-appropriate vocabulary | E43: ✅ Live link

Sheet 🧠 Theory of Mind
A1: 🧠 A7DO THEORY OF MIND — NPC Belief/Desire/Emotion Modelling
A2: Theory of Mind: understanding that others have beliefs, desires, and emotions different from one's own.
A3: Source: Theory of Mind sheet (v18) · engines_extended.py NPC Engine · Mathematical Framework §3.10
A5: A. CORE ToM EQUATIONS
A6: Equation | B6: Formula | C6: Variables | D6: Notes
A7: ToM state | B7: ToM_i(j) = {B_j, D_j, E_j, I_j} | C7: B=beliefs, D=desires, E=emotions, I=intentions | D7: Agent i's model of agent j
A8: Belief update | B8: B_j(t+1) = B_j(t) + η·(obs − B_j(t)) | C8: η=0.1 learning rate | D8: Bayesian belief revision
A9: Desire inference | B9: D_j = argmax_a E[R_j(a) | obs_j] | C9: R_j=reward function of agent j | D9: Inferred from observed behaviour
A10: Emotion recognition | B10: E_j = f(facial, vocal, postural) | C10: Multimodal emotion classifier | D10: Feeds from sensory integration
A11: Social prediction | B11: P(action_j | ToM_i(j)) = softmax(Q_j(s,a)) | C11: Q_j=inferred Q-function of j | D11: Enables anticipatory behaviour
A12: False belief | B12: FB(j) = B_j ≠ world_state | C12: Detects when j has wrong belief | D12: Passes false belief task at stage 3
A14: B. ToM DEVELOPMENTAL STAGES
A15: Stage | B15: Week Range | C15: Age | D15: Description | E15: False Belief | F15: Perspective | G15: Empathy | H15: Current Status
A16: 1 | B16: 40–156 | C16: 0–2 years | D16: Recognises agents; joint attention; emotional contagion | E16: None | F16: Egocentric only | G16: Emotional contagion | H16: ⭐ CURRENT (Wk 125)
A17: 2 | B17: 156–208 | C17: 2–4 years | D17: Understands others have desires different from own | E17: None | F17: Limited | G17: Sympathy | H17: No (future)
A18: 3 | B18: 208–312 | C18: 4–6 years | D18: Passes false belief task; understands deception | E18: First-order | F18: Spatial | G18: Empathy | H18: No (future)
A19: 4 | B19: 312–624 | C19: 6–12 years | D19: Second-order beliefs: 'A thinks B thinks...' | E19: Second-order | F19: Full | G19: Full empathy | H19: No (future)
A20: 5 | B20: 624+ | C20: 12+ years | D20: Full social cognition; deception; complex negotiation | E20: Complex | F20: Complete | G20: Compassion | H20: No (future)
A22: C. NPC BELIEF-DESIRE-EMOTION STATE REGISTRY
A23: NPC ID | B23: Name | C23: Relationship | D23: Inferred Desire | E23: Inferred Belief | F23: Emotion State | G23: Bond Strength
A24: NPC_LORRAINE | B24: Lorraine | C24: Primary caregiver | D24: A7DO wellbeing | E24: A7DO needs care | F24: Nurturing | G24: 0.95
A25: NPC_ALEXIS | B25: Alexis | C25: Secondary family | D25: Social connection | E25: A7DO is growing | F25: Warm | G25: 0.7
A26: NPC_EVELYN | B26: Evelyn | C26: Secondary family | D26: Play interaction | E26: A7DO likes play | F26: Playful | G26: 0.65
A27: NPC_JAMES | B27: James | C27: Neighbour | D27: Friendly contact | E27: A7DO is neighbour child | F27: Neutral | G27: 0.3
A29: D. INTEGRATION POINTS
A30: System | B30: Direction | C30: Data Shared | D30: Status
A31: NPC Engine | B31: Core | C31: NPC states, policies, bond strengths | D31: ✅ NPC Engine exists
A32: Episodic Memory | B32: Input | C32: Remembered NPC interactions | D32: ✅ Memory built
A33: Language Grounding | B33: Bidirectional | C33: Social vocabulary grounding | D33: 🟡 Language partial
A34: Value/Motivation | B34: Input | C34: Social drives (affiliation, attachment) | D34: ✅ Drives built
A35: Predictive Simulation | B35: Output | C35: Social action prediction | D35: 🟡 Prediction partial

Sheet 🔮 Predictive Simulation
A1: 🔮 A7DO PREDICTIVE SIMULATION — Forward Modelling & Dream Replay
A2: Predictive coding: the brain as a prediction machine minimising free energy across hierarchical levels.
A3: Source: Predictive Simulation sheet (v18) · engines.py EQ_PRED_08 · Mathematical Framework §3.9
A5: A. CORE PREDICTIVE SIMULATION EQUATIONS
A6: Equation | B6: Formula | C6: Variables | D6: Notes
A7: Free energy | B7: F = Σ[εᵀ·Π·ε + log|Σ|] | C7: ε=prediction error, Π=precision, Σ=covariance | D7: Minimised by perception and action
A8: Prediction error | B8: ε_l(t) = x_l(t) − μ_l(t) | C8: x_l=actual, μ_l=predicted at level l | D8: Hierarchical — each level predicts level below
A9: State update | B9: dμ_l/dt = −κ·ε_l + ∂f_l/∂μ_l·ε_{l+1} | C9: κ=0.1–0.5 update rate | D9: Kalman-filtered state estimate
A10: Forward model | B10: x̂(t+n) = f(x(t), a(t), ..., a(t+n-1)) | C10: n=planning horizon (ticks) | D10: Counterfactual branching
A11: Dream replay | B11: x_dream(t) ~ P(x | memory, prior) | C11: Samples from episodic memory | D11: Sleep consolidation + planning
A12: Active inference | B12: a* = argmin_a F(x̂(t+1|a)) | C12: Minimise predicted free energy | D12: Action selection via prediction
A14: B. COUNTERFACTUAL SCENARIO TABLE
A15: Scenario | B15: Option A (default) | C15: Option B (counterfactual) | D15: Predicted Outcome Diff | E15: Required Systems | F15: Onset Week | G15: Status
A16: Reaching for toy | B16: Reach directly | C16: Reach via different path | D16: Success probability difference | E16: Motor Planning + Forward Model | F16: 160+ | G16: 🔴 Not yet
A17: Caregiver absent | B17: Wait and cry | C17: Move toward last known location | D17: Reunion probability | E17: Object Permanence + Value System | F17: 120+ | G17: 🟡 Emerging
A18: Food choice | B18: Take nearest food | C18: Take preferred food (further) | D18: Satisfaction difference | E18: Value System + Motor Planning | F18: 156+ | G18: 🔴 Not yet
A19: Social interaction | B19: Approach NPC | C19: Wait for NPC to approach | D19: Social reward difference | E19: ToM + Value System | F19: 208+ | G19: 🔴 Not yet
A20: Object hidden | B20: Search last location | C20: Search alternative locations | D20: Find probability | E20: Object Permanence Stage 4 | F20: 200+ | G20: 🔴 Not yet
A22: C. PLANNING HORIZON BY DEVELOPMENTAL STAGE
A23: Stage | B23: Week Range | C23: Planning Horizon | D23: Capability
A24: 1 | B24: 40–80 | C24: 1 tick (reactive) | D24: Reflex only — no forward model
A25: 2 | B25: 80–156 | C25: 5–10 ticks | D25: Anticipatory reach; object search
A26: 3 | B26: 156–260 | C26: 50–100 ticks | D26: Short-term planning; means-end
A27: 4 | B27: 260–624 | C27: 500+ ticks | D27: Multi-step planning; social prediction
A28: 5 | B28: 624+ | C28: Unlimited | D28: Abstract planning; dream replay; counterfactuals
A30: D. INTEGRATION POINTS
A31: System | B31: Direction | C31: Data Shared | D31: Status
A32: EQ_PRED_08 (runtime) | B32: Core | C32: Prediction error E, state P | D32: ✅ Running — error converged at 0.576
A33: Episodic Memory | B33: Input | C33: Past events for dream replay | D33: ✅ Memory built — 9590 LTM events
A34: Value/Motivation | B34: Bidirectional | C34: Reward signals for action selection | D34: ✅ Drives built
A35: Motor Planning | B35: Output | C35: Action sequences for forward model | D35: 🟡 Motor partial
A36: Theory of Mind | B36: Input | C36: NPC models for social prediction | D36: 🟡 ToM partial

Sheet 🗺️ Scene Graph & Places
A1: 🗺️ A7DO SCENE GRAPH & PERSISTENT PLACES — Spatial World Model
A2: Scene graph G = {N, E}: nodes=objects/places, edges=spatial/semantic relations. Persistent across occlusions.
A3: Source: Scene Graph & Places sheet (v18) · engines_extended.py ObjectPermanenceState · World & Space sheet
A5: A. SCENE GRAPH EQUATIONS
A6: Equation | B6: Formula | C6: Variables | D6: Notes
A7: Graph structure | B7: G = {N, E} | C7: N=nodes (objects/places), E=edges (relations) | D7: Directed labelled graph
A8: Relation classifier | B8: R(A,B) = classify(pos_A, pos_B, context) | C8: pos=world coordinates, context=semantic | D8: Outputs: near, inside, on, beside, part-of
A9: Place recognition | B9: P(place | features) = softmax(W·features) | C9: W=learned place embedding | D9: Enables room/location labelling
A10: Navigation | B10: path(A→B) = Dijkstra(G, A, B) | C10: G=scene graph as navigation graph | D10: Requires persistent place nodes
A11: Persistence update | B11: conf(node,t+1) = conf(node,t)·(1−λ) + λ·visible(t) | C11: λ=0.001 decay, 0.1 reactivation | D11: From ObjectPermanenceState
A13: B. PLACE NODE REGISTRY (BeenFore world — from World Data sheet)
A14: Place ID | B14: Label | C14: Type | D14: World X | E14: World Y | F14: Persistence | G14: Notes
A15: PLACE_HOSPITAL | B15: Hospital (Birth) | C15: Building | D15: 0 | E15: 0 | F15: 1 | G15: World origin — birth location
A16: PLACE_H8 | B16: A7DO Home (H8) | C16: House | D16: 1090 | E16: 880 | F16: 1 | G16: Primary residence — Lorraine
A17: PLACE_H1 | B17: H1 — Alexis & Evelyn | C17: House | D17: 1050 | E17: 900 | F17: 0.8 | G17: Secondary family home
A18: PLACE_H7 | B18: H7 — James & Olivia | C18: House | D18: 1100 | E18: 870 | F18: 0.6 | G18: Neighbour home
A19: PLACE_BEDROOM | B19: Bedroom | C19: Room | D19: 1090 | E19: 882 | F19: 1 | G19: Sleep location — inside H8
A20: PLACE_LIVING | B20: Living Room | C20: Room | D20: 1090 | E20: 878 | F20: 1 | G20: Play area — inside H8
A21: PLACE_KITCHEN | B21: Kitchen | C21: Room | D21: 1092 | E21: 880 | F21: 1 | G21: Feeding location — inside H8
A22: PLACE_GARDEN | B22: Garden | C22: Outdoor | D22: 1090 | E22: 875 | F22: 0.9 | G22: Exploration area — beside H8
A23: PLACE_LANE | B23: BeenFore Lane | C23: Street | D23: 1090 | E23: 860 | F23: 1 | G23: Street — H8 is on this
A24: PLACE_CITY | B24: BeenFore City | C24: City | D24: 1000 | E24: 1000 | F24: 1 | G24: City centre — world reference
A26: C. SCENE RELATION TABLE (current — Wk 125 default)
A27: Node A | B27: Relation | C27: Node B | D27: Confidence | E27: Last Updated (Week) | F27: Persistence Type
A28: lorraine | B28: inside | C28: PLACE_H8 | D28: 1 | E28: 125 | F28: Persistent
A29: A7DO | B29: inside | C29: PLACE_H8 | D29: 1 | E29: 125 | F29: Persistent
A30: Toys | B30: inside | C30: PLACE_LIVING | D30: 0.8 | E30: 125 | F30: Semi-persistent
A31: Bed | B31: inside | C31: PLACE_BEDROOM | D31: 1 | E31: 125 | F31: Persistent
A32: PLACE_H8 | B32: beside | C32: PLACE_H7 | D32: 1 | E32: 125 | F32: Persistent
A33: PLACE_H8 | B33: on | C33: PLACE_LANE | D33: 1 | E33: 125 | F33: Persistent
A34: PLACE_LANE | B34: part-of | C34: PLACE_CITY | D34: 1 | E34: 125 | F34: Persistent
A36: D. INTEGRATION POINTS
A37: System | B37: Direction | C37: Data Shared | D37: Status
A38: Object Permanence | B38: Core | C38: Object nodes → scene graph nodes | D38: ✅ Object registry built
A39: World & Space | B39: Input | C39: World coordinates for place nodes | D39: ✅ Coordinates live
A40: Language Grounding | B40: Output | C40: Place names → grounded spatial words | D40: 🟡 Language partial
A41: NPC Engine | B41: Bidirectional | C41: NPC locations in scene graph | D41: ✅ NPC exists
A42: Episodic Memory | B42: Output | C42: Place context for episodic events | D42: ✅ Memory built
A43: Predictive Simulation | B43: Input | C43: Navigation graph for planning | D43: 🟡 Prediction partial

Sheet 👁️ Object Permanence
A1: 👁️ A7DO OBJECT PERMANENCE ENGINE — Full Specification v1.0 | Core Cognitive Subsystem for A7DO v2.0
A2: Transforms: reactive perception → persistent cognition | frame-based world → continuous world | visible-only → predictive reasoning
A3: Without object permanence: world resets every frame · planning collapses · prediction collapses · identity continuity weakens · language grounding fails · social cognition cannot emerge. This is Priority #2 in the v2.0 Critical Path (after Proprioception).
A4: 📐 CORE EQUATIONS & MATHEMATICAL FRAMEWORK
A5: # | B5: Equation Name | C5: Formula | D5: Variables | E5: Purpose | F5: Runtime Frequency | G5: Notes
A6: 1 | B6: Bayesian Permanence Estimator | C6: P(O_t | O_{1:t-1}, V_t, M_t, E_t) | D6: O_t=current object state; O_{1:t-1}=history; V_t=visual input; M_t=memory; E_t=environment | E6: Probability that object still exists — core permanence belief | F6: Every tick | G6: Bayesian update; prior from history, likelihood from vision
A7: 2 | B7: Confidence Decay Model | C7: C_i(t) = C_0 · exp(-λ · (t - t_lastSeen)) | D7: C_i=confidence object exists; λ=decay constant; t_lastSeen=last observation tick | E7: Models uncertainty and forgetting when object not visible | F7: Every tick per object | G7: λ higher for less important objects; emotional valence modulates λ
A8: 3 | B8: Emotional Permanence Modulation | C8: λ = λ_0 · (1 - valence) | D8: λ_0=base decay; valence=emotional importance [0,1] | E8: High-valence objects (caregiver, food) decay slower — persist longer in memory | F8: On valence update | G8: Attachment objects: valence→1, λ→0 (never forgotten)
A9: 4 | B9: Motion Prediction (Kinematic) | C9: x̂_{t+1} = x_t + v_t·Δt + ½·a_t·(Δt)² | D9: x=position; v=velocity; a=acceleration; Δt=time step | E9: Predicts where hidden object will be — enables pursuit and reaching | F9: Every tick for occluded objects | G9: Kalman filter wraps this for uncertainty propagation
A10: 5 | B10: Bayesian Permanence Filter | C10: P(O_t) = α·P_vision + β·P_memory + γ·P_prediction | D10: α+β+γ=1; P_vision=visual evidence; P_memory=memory evidence; P_prediction=motion model | E10: Fuses three evidence sources into single permanence belief | F10: Every tick | G10: α=0.6 (visible), 0.0 (occluded); β=0.3; γ=0.1 (visible), 0.7 (occluded)
A11: 6 | B11: Social Permanence (Agents) | C11: C_agent(t) = C_0 · exp(-λ_social · t) | D11: λ_social < λ_object (agents persist longer than objects) | E11: Agents (NPCs, caregivers) have stronger permanence than inanimate objects | F11: Every tick per agent | G11: λ_social = 0.001 (very slow decay); attachment agents: λ→0
A12: 7 | B12: Surprise Signal | C12: S = |x̂_t - x_actual| | D12: S=surprise magnitude; x̂=predicted position; x_actual=observed position | E12: Drives attention, learning, and prediction correction | F12: On object reappearance | G12: High S → attention spike → learning update → model correction
A13: 8 | B13: Occlusion State Function | C13: O_i.state = f(FOV, obstacles, motion, memory) | D13: FOV=field of view; obstacles=scene geometry; motion=object velocity | E13: Determines visibility state: Visible / Occluded / Lost / Forgotten | F13: Every tick | G13: Static occlusion (wall), dynamic (NPC), self-occlusion (body)
A14: 9 | B14: Scene Graph Update | C14: G = {N, E}; N=objects/agents/body; E=relations(under,behind,holding,inside,touching) | D14: N=nodes; E=edges with relation type and confidence | E14: Maintains persistent relational world model | F14: Every tick | G14: ball→under→table; NPC→behind→wall; hand→holding→cup
A15: 10 | B15: Object Registry Entry | C15: O_i = {id, type, x, y, z, v, a, state, importance, valence} | D15: v=velocity; a=acceleration; state=visible/occluded/lost; importance=relevance; valence=emotion | E15: Persistent entity record — world model backbone | F15: Created on first detection; updated every tick | G15: Registry is the persistent world model
A17: 📋 OBJECT REGISTRY — Visibility States & Transitions
A18: State | B18: Meaning | C18: Confidence Range | D18: Decay Active? | E18: Motion Prediction? | F18: Memory Source | G18: Transition To | H18: Trigger
A19: Visible | B19: In FOV, high certainty | C19: 0.85–1.0 | D19: No | E19: No (direct obs) | F19: Visual input | G19: Occluded | H19: Object leaves FOV or blocked
A20: Occluded | B20: Hidden but predicted | C20: 0.4–0.85 | D20: Yes | E20: Yes (kinematic) | F20: Memory + prediction | G20: Visible / Lost | H20: Object reappears / confidence drops below 0.4
A21: Lost | B21: Uncertain, decaying confidence | C21: 0.1–0.4 | D21: Yes (fast) | E21: Yes (uncertain) | F21: Memory only | G21: Forgotten / Visible | H21: Confidence → 0 / Object found
A22: Forgotten | B22: Removed from active registry | C22: < 0.1 | D22: N/A | E22: No | F22: LTM archive | G22: Visible (re-encode) | H22: Object detected again → surprise signal
A24: 📈 DEVELOPMENTAL STAGES — Object Permanence Across A7DO Lifecycle
A25: Stage | B25: A7DO Weeks | C25: Age Equivalent | D25: Capability | E25: Confidence Decay λ | F25: Motion Prediction | G25: Scene Graph | H25: Social Permanence | I25: Current A7DO?
A26: 0 — None | B26: 0–40 | C26: Prenatal | D26: No permanence — world resets every frame | E26: N/A | F26: None | G26: None | H26: None | I26: No (past)
A27: 1 — Short Persistence | B27: 40–80 | C27: 0–10 months | D27: Brief object persistence (1–2 seconds) | E27: 0.5/tick | F27: None | G27: None | H27: None | I27: No (past)
A28: 2 — Hidden Tracking | B28: 80–120 | C28: 10–15 months | D28: Tracks hidden objects for up to 10 seconds | E28: 0.1/tick | F28: Linear only | G28: Basic | H28: Caregiver only | I28: No (past)
A29: 3 — Trajectory Pred. | B29: 120–200 | C29: 15–25 months | D29: Predicts trajectory of hidden moving objects | E29: 0.05/tick | F29: Kinematic | G29: Relational | H29: Caregiver + familiar | I29: ★ CURRENT (Wk 125)
A30: 4 — Abstract Perm. | B30: 200–350 | C30: 25–67 months | D30: Abstract permanence — objects exist even unseen | E30: 0.01/tick | F30: Full physics | G30: Full scene | H30: All agents | I30: No (future)
A31: 5 — Social Perm. | B31: 350+ | C31: 67+ months | D31: Social permanence — tracks agents' mental states | E31: 0.001/tick | F31: Intentional | G31: Social graph | H31: Full ToM | I31: No (future)
A33: 🔄 RUNTIME LOOP — Object Permanence Tick Execution Order
A34: Step | B34: Process | C34: Input | D34: Output | E34: Equation Used | F34: Frequency | G34: Notes
A35: 1 | B35: Visual Update | C35: FOV + retinal input | D35: Detected objects list | E35: FOV geometry + saccade model | F35: Every tick | G35: Only objects in FOV with sufficient confidence
A36: 2 | B36: Object Detection | C36: Visual update output | D36: New / updated object entries | E36: Object Registry O_i | F36: Every tick | G36: New objects: create entry; known: update position
A37: 3 | B37: Permanence Update | C37: Detection + memory + motion | D37: Updated confidence C_i(t) | E37: Bayesian filter P(O_t) | F37: Every tick | G37: Fuse vision, memory, prediction
A38: 4 | B38: Confidence Decay | C38: Time since last seen | D38: Decayed confidence values | E38: C_i(t) = C_0·exp(-λ·Δt) | F38: Every tick for occluded | G38: λ modulated by valence
A39: 5 | B39: Motion Prediction | C39: Last known v, a, position | D39: Predicted position x̂_{t+1} | E39: Kinematic equation | F39: Every tick for occluded | G39: Kalman filter for uncertainty
A40: 6 | B40: Scene Graph Update | C40: Object positions + relations | D40: Updated G = {N, E} | E40: Scene graph G | F40: Every tick | G40: Update spatial relations between all objects
A41: 7 | B41: Attention Weighting | C41: Confidence + importance + valence | D41: Attention priority list | E41: Importance × valence × C_i | F41: Every tick | G41: High-priority objects get more processing
A42: 8 | B42: Motor Planning Feed | C42: Predicted positions | D42: Reach/grasp targets | E42: x̂_{t+1} for motor system | F42: Every motor tick | G42: Enables reaching for hidden objects
A43: 9 | B43: Memory Consolidation | C43: Object events + emotions | D43: Episodic memory entries | E43: E_ep = {O_i, emotion, time} | F43: On state change | G43: Object disappearance/reappearance → episodic event
A44: 10 | B44: Surprise Detection | C44: Predicted vs actual position | D44: Surprise signal S | E44: S = |x̂_t - x_actual| | F44: On reappearance | G44: High S → attention + learning update
A46: 🔗 CROSS-SYSTEM INTEGRATION MAP
A47: System | B47: Integration Type | C47: Data Flow | D47: What Object Permanence Provides | E47: What It Receives | F47: Coupling Strength | G47: v1.0 Sheet
A48: Vision / FOV | B48: Bidirectional | C48: FOV → detection; attention → gaze direction | D48: Attention targets for saccades; predicted object locations | E48: Detected objects, visual confidence | F48: 🔴 Critical | G48: 🫀 Body Systems
A49: Episodic Memory | B49: Bidirectional | C49: Object events → episodic store; memory → prior | D49: Object disappearance/reappearance events with emotional tags | E49: Historical object states as Bayesian prior | F49: 🔴 Critical | G49: 🧠 Mind & Cognition
A50: Language Engine | B50: Output only | C50: Stable referents → noun grounding | D50: Stable object identities that nouns can refer to; pronoun persistence | E50: Object labels from semantic memory | F50: 🟡 Major | G50: 🧠 Mind & Cognition
A51: Motor Planning | B51: Output only | C51: Predicted positions → reach/grasp targets | D51: Hidden object positions for predictive reaching and grasping | E51: Motor execution feedback | F51: 🔴 Critical | G51: 🫀 Body Systems
A52: Emotion Module | B52: Bidirectional | C52: Valence → λ decay; emotion → importance | D52: Emotional weighting of objects (caregiver=high valence) | E52: Emotional state affecting attention and decay rates | F52: 🟡 Major | G52: 🧠 Mind & Cognition
A53: NPC / Theory of Mind | B53: Bidirectional | C53: Agent tracking → ToM; ToM → social permanence | D53: Persistent agent representations for belief/desire attribution | E53: Agent identity and relationship data | F53: 🔴 Critical | G53: 👥 NPC Engine
A54: Reality Bridge | B54: Bidirectional | C54: World state → object positions; predictions → actions | D54: Persistent world model; predicted object states | E54: Sensory fusion of object positions | F54: 🔴 Critical | G54: 🌍 World Systems
A55: Predictive Simulation | B55: Bidirectional | C55: Object trajectories → simulation; sim → predictions | D55: Object motion models for forward simulation | E55: Predicted future states | F55: 🟡 Major | G55: 🧠 Mind & Cognition
A56: Value System | B56: Input only | C56: Object importance → attention priority | D56: Importance-weighted attention allocation | E56: Object utility and survival relevance | F56: 🟡 Major | G56: 🧠 Mind & Cognition
A57: DNA Loop Engine | B57: Input only | C57: Current week → developmental stage | D57: Stage-appropriate permanence capabilities | E57: Current week for developmental gating | F57: 🟡 Major | G57: 🧬 DNA Loop Engine
A59: 👂 MULTI-SENSORY INTEGRATION — Vision + Hearing + Smell
A60: Modality | B60: Contribution to Permanence | C60: Equation Extension | D60: When Primary | E60: Confidence Weight | F60: Notes
A61: Vision | B61: Primary — direct object detection and position | C61: P_vision = f(FOV, retinal confidence, occlusion) | D61: Object in FOV | E61: α=0.6 (visible), 0.0 (occluded) | F61: Highest precision; degrades with distance and occlusion
A62: Hearing | B62: Auditory cues confirm presence when occluded; sound source localisation | C62: P_audio = f(sound_direction, sound_identity, distance) | D62: Object occluded but making sound | E62: β_audio=0.3 (occluded with sound) | F62: Footsteps, voice, object sounds; directional hearing → position estimate
A63: Smell | B63: Olfactory signals confirm identity in low-visibility; scent trails | C63: P_smell = f(scent_strength, scent_identity, decay_rate) | D63: Low visibility, familiar objects/agents | E63: β_smell=0.15 (low visibility) | F63: Especially important for food, caregivers; scent trails enable tracking
A64: Touch | B64: Confirms object existence and position when in contact | C64: P_touch = f(contact_force, contact_area, proprioception) | D64: Object in hand or touching body | E64: α_touch=0.95 (contact) | F64: Highest confidence when touching; enables blind reaching
A65: Combined | B65: Bayesian fusion of all modalities | C65: P(O_t) = Σ_m w_m · P_m; Σw_m = 1 | D65: Always — weighted by reliability | E65: Adaptive weights based on context | F65: Cross-modal binding: consistent signals reinforce; conflicting → surprise
A67: ⚙️ PARAMETER REFERENCE — Object Permanence Engine
A68: Parameter | B68: Symbol | C68: Value | D68: Units | E68: Description | F68: Age-Dependent?
A69: Base confidence | B69: C_0 | C69: 1.0 | D69: — | E69: Initial confidence when object first seen | F69: No
A70: Base decay constant | B70: λ_0 | C70: 0.05 | D70: /tick | E70: Default confidence decay rate | F70: Yes — decreases with age
A71: Emotional decay modifier | B71: valence | C71: 0–1 | D71: — | E71: High valence → slower decay | F71: No
A72: Social decay constant | B72: λ_social | C72: 0.001 | D72: /tick | E72: Agent permanence decay (very slow) | F72: No
A73: Occluded weight (vision) | B73: α_occluded | C73: 0.0 | D73: — | E73: Vision weight when object not visible | F73: No
A74: Memory weight | B74: β | C74: 0.3 | D74: — | E74: Memory evidence weight | F74: Yes — increases with age
A75: Prediction weight | B75: γ | C75: 0.1→0.7 | D75: — | E75: Motion model weight (higher when occluded) | F75: No
A76: Visible threshold | B76: θ_vis | C76: 0.85 | D76: — | E76: Confidence above which = Visible state | F76: No
A77: Lost threshold | B77: θ_lost | C77: 0.4 | D77: — | E77: Confidence below which = Lost state | F77: No
A78: Forgotten threshold | B78: θ_forget | C78: 0.1 | D78: — | E78: Confidence below which = Forgotten | F78: No
A79: Max registry size | B79: N_max | C79: 50 | D79: objects | E79: Maximum objects in active registry | F79: Yes — grows with age
... A83: Current A7DO stage | B83: stage | C83: 3 | D83: — | E83: Trajectory prediction (Wk 125) | F83: Current
A85: 📁 RECOMMENDED FILE STRUCTURE — Object_Permanence_Runtime.md
A86: File / Section | B86: Contents | C86: Format | D86: Links To | E86: Priority
A87: Object_Permanence_Runtime.md | B87: Master specification document | C87: Markdown | D87: All subsystems | E87: 🔴 Create now
A88: ├── Object Registry | B88: O_i = {id, type, x,y,z, v, a, state, importance, valence} | C88: JSON schema | D88: World Inventory, Reality Bridge | E88: 🔴 Create now
A89: ├── Visibility States | B89: State machine: Visible/Occluded/Lost/Forgotten + transitions | C89: State diagram | D89: FOV system, Memory | E89: 🔴 Create now
A90: ├── Confidence Decay | B90: C_i(t) = C_0·exp(-λ·Δt) with valence modulation | C90: Equation + params | D90: Emotion Module | E90: 🔴 Create now
A91: ├── Motion Prediction | B91: Kinematic + Kalman filter for hidden object tracking | C91: Equation + code | D91: Motor Planning | E91: 🔴 Create now
A92: ├── Occlusion Handling | B92: Static/dynamic/self-occlusion detection and handling | C92: Algorithm | D92: FOV, World Systems | E92: 🟡 Phase 1
A93: ├── Scene Graph | B93: G = {N, E} with spatial relations and confidence | C93: Graph schema | D93: World Inventory, Language | E93: 🟡 Phase 1
A94: ├── Developmental Stages | B94: Stage 0–5 with week ranges and capability gates | C94: Table | D94: DNA Loop Engine, Growth Timeline | E94: 🔴 Create now
